Workbook

Sheet SFPO
A1: City Government of Panabo
A2: Province of Davao del Norte
A3: STATEMENT OF FINANCIAL POSITION
A4: All Funds
A5: As at December 31, 2021
A6: (With Comparative Figures for CY 2020)
A7: (In Philippine Peso)
B9: Note | D9: 2021 | E9: 2020
A10: ASSETS
A11: Current Assets
A12: Cash and Cash Equivalents | B12: 4 | D12: 1.3550813e+09 | E12: 1.1541891e+09 | G12: =D12-#REF! -> #REF! | H12: =E12-#REF! -> #REF!
A13: Investments | B13: 5 | D13: 27751603 | E13: 29688483 | G13: =D13-#REF! -> #REF! | H13: =E13-#REF! -> #REF!
A14: Receivables | B14: 6 | D14: 1.8293766e+08 | E14: 1.9895473e+08 | G14: =D14-#REF! -> #REF! | H14: =E14-#REF! -> #REF!
A15: Inventories | B15: 7 | D15: 1.4565748e+08 | E15: 1.2649496e+08 | G15: =D15-#REF! -> #REF! | H15: =E15-#REF! -> #REF!
A16: Prepayments and Deferred Charges | B16: 8 | D16: 15970831 | E16: 26630545 | G16: =D16-#REF! -> #REF! | H16: =E16-#REF! -> #REF!
A17: Total Current Assets | D17: =SUM(D12:D16) -> 1.7273988e+09 | E17: =SUM(E12:E16) -> 1.5359579e+09 | G17: =D17-#REF! -> #REF! | H17: =E17-#REF! -> #REF!
A19: Non-Current Assets
A20: Property, Plant and Equipment | B20: 9 | D20: 2.4551166e+09 | E20: 2.2326611e+09 | G20: =D20-#REF! -> #REF! | H20: =E20-#REF! -> #REF!
A21: Biological Assets | B21: 10 | D21: 124150 | E21: 124150 | G21: =D21-#REF! -> #REF! | H21: =E21-#REF! -> #REF!
A22: Intangible Assets | B22: 11 | D22: 430673.03 | E22: 779625.45 | G22: =D22-#REF! -> #REF! | H22: =E22-#REF! -> #REF!
A23: Total Non-Current Assets | D23: =SUM(D20:D22) -> 2.4556715e+09 | E23: =SUM(E20:E22) -> 2.2335649e+09 | G23: =D23-#REF! -> #REF! | H23: =E23-#REF! -> #REF!
A24: Total Assets | D24: =D23+D17 -> 4.1830703e+09 | E24: =E23+E17 -> 3.7695227e+09 | G24: =D24-#REF! -> #REF! | H24: =E24-#REF! -> #REF!
A26: LIABILITIES
A27: Current Liabilities
A28: Financial Liabilities | B28: 12 | D28: =127235905.41+749493.83 -> 1.279854e+08 | E28: 1.7895065e+08 | G28: =D28-#REF! -> #REF! | H28: =E28-#REF! -> #REF!
A29: Inter-Agency Payables | B29: 13 | D29: 4.897553e+08 | E29: 1.6829602e+08 | G29: =D29-#REF! -> #REF! | H29: =E29-#REF! -> #REF!
A30: Intra-Agency Payables | B30: 14 | D30: 80916349 | E30: 63163976 | G30: =D30-#REF! -> #REF! | H30: =E30-#REF! -> #REF!
A31: Trust Liabilities | B31: 15 | D31: 1.1420422e+08 | E31: 1.0482222e+08 | G31: =D31-#REF! -> #REF! | H31: =E31-#REF! -> #REF!
A32: Provisions | B32: 16 | D32: 528146.84 | E32: 528146.84 | G32: =D32-#REF! -> #REF! | H32: =E32-#REF! -> #REF!
A33: Deferred Credits/Unearned Income | B33: 17 | D33: 19610913 | E33: 29580039 | G33: =D33-#REF! -> #REF! | H33: =E33-#REF! -> #REF!
A34: Other Payables | B34: 18 | D34: 73845619 | E34: 58866464 | G34: =D34-#REF! -> #REF! | H34: =E34-#REF! -> #REF!
A35: Total Current Liabilities | D35: =SUM(D28:D34) -> 9.0684594e+08 | E35: =SUM(E28:E34) -> 6.0420752e+08 | G35: =D35-#REF! -> #REF!
A37: Non-Current Liabilities
A38: Financial Liabilities | B38: 12 | D38: 2.4759494e+08 | E38: 2.1447313e+08 | G38: =D38-#REF! -> #REF! | H38: =E38-#REF! -> #REF!
A39: Deferred Credits/Unearned Income | B39: 17 | D39: 1572986 | E39: 1209890.2 | G39: =D39-#REF! -> #REF! | H39: =E39-#REF! -> #REF!
A40: Total Non-Current Liabilities | D40: =SUM(D38:D39) -> 2.4916793e+08 | E40: =SUM(E38:E39) -> 2.1568302e+08 | G40: =D40-#REF! -> #REF! | H40: =E40-#REF! -> #REF!
A41: Total Liabilities | D41: =D35+D40 -> 1.1560139e+09 | E41: =E35+E40 -> 8.1989054e+08 | G41: =D41-#REF! -> #REF! | H41: =E41-#REF! -> #REF!
A43: NET ASSETS/EQUITY
A44: Government Equity | B44: 32 | D44: =SCNAE!D18 -> 3.0270564e+09 | E44: =SCNAE!E18 -> 2.9496322e+09 | G44: =D44-#REF! -> #REF! | H44: =E44-#REF! -> #REF!
A45: Total Liabilities and Net Assets/Equity | D45: =D44+D41 -> 4.1830703e+09 | E45: =E44+E41 -> 3.7695227e+09 | G45: =D45-#REF! -> #REF! | H45: =E45-#REF! -> #REF!
A47: (See accompanying Notes to Financial Statements.)
D49: =D24-D45 -> 0 | E49: =E24-E45 -> -0.0030007362

Sheet SFPER
A1: City Government of Panabo
A2: Province of Davao del Norte
A3: STATEMENT OF FINANCIAL PERFORMANCE
A4: All Funds
A5: For the Year Ended December 31, 2021
A6: (With Comparative Figures for CY 2020)
A7: (In Philippine Peso)
B9: Note/s | D9: 2021 | E9: 2020
A10: Revenue
A11: Tax Revenue | B11: 19 | D11: 2.9471068e+08 | E11: 2.8585649e+08 | F11: =D11-#REF! -> #REF! | H11: =E11-#REF! -> #REF!
A12: Share from Internal Revenue Collections | B12: 20 | D12: 889216030 | E12: 829672451 | F12: =D12-#REF! -> #REF! | H12: =E12-#REF! -> #REF!
A13: Other Shares from National Taxes | B13: 20 | D13: 72609 | E13: 719689.03 | F13: =D13-#REF! -> #REF! | H13: =E13-#REF! -> #REF!
A14: Service and Business Income | B14: 21, 29 | D14: =145627048.48-2157631.59 -> 1.4346942e+08 | E14: 1.1825248e+08 | F14: =D14-#REF! -> #REF! | H14: =E14-#REF! -> #REF!
A15: Shares, Grants and Donations | B15: 23 | D15: 4548753.6 | E15: 72801491 | F15: =D15-#REF! -> #REF! | H15: =E15-#REF! -> #REF!
A16: Total Revenue | D16: =SUM(D11:D15) -> 1.3320175e+09 | E16: =SUM(E11:E15) -> 1.3073026e+09
A18: Less: Current Operating Expenses
A19: Personnel Services | B19: 25 | D19: 3.8409563e+08 | E19: 3.6425925e+08 | F19: =D19-#REF! -> #REF! | H19: =E19-#REF! -> #REF!
A20: Maintenance & Other Operating Expenses | B20: 26 | D20: 4.923733e+08 | E20: 6.1035046e+08 | F20: =D20-#REF! -> #REF! | H20: =E20-#REF! -> #REF!
A21: Non-cash Expenses | B21: 27 | D21: 1.2077748e+08 | E21: 1.0638918e+08 | F21: =D21-#REF! -> #REF! | H21: =E21-#REF! -> #REF!
A22: Financial Expenses | B22: 28 | D22: 10687840 | E22: 11836409 | F22: =D22-#REF! -> #REF! | H22: =E22-#REF! -> #REF!
A23: Current Operating Expenses | D23: =SUM(D19:D22) -> 1.0079343e+09 | E23: =SUM(E19:E22) -> 1.0928353e+09 | F23: =D23-#REF! -> #REF! | H23: =E23-#REF! -> #REF!
A25: Surplus (Deficit) from Current Operation | D25: =D16-D23 -> 3.2408323e+08 | E25: =E16-E23 -> 2.1446729e+08 | F25: =D25-#REF! -> #REF! | H25: =E25-#REF! -> #REF!
A26: Add (Deduct):
A27: Transfers, Assistance and Subsidy From | B27: 22 | D27: 1.5304759e+08 | E27: 1.9077542e+08 | F27: =D27-#REF! -> #REF! | H27: =E27-#REF! -> #REF!
A28: Transfers, Assistance and Subsidy To | B28: 30, 31 | D28: -55694875 | E28: -39429975 | F28: =D28-#REF! -> #REF! | H28: =E28+#REF! -> #REF!
A29: Miscellaneous Income | B29: 24 | D29: 1643931.5 | E29: 642196.59 | F29: =D29-#REF! -> #REF! | H29: =E29-#REF! -> #REF!
A30: Surplus(Deficit) for the period | D30: =SUM(D25:D29) -> 4.2307988e+08 | E30: =SUM(E25:E29) -> 3.6645493e+08 | F30: =D30-#REF! -> #REF! | H30: =E30-#REF! -> #REF!
A32: (See accompanying Notes to Financial Statements.)

Sheet SCNAE
A1: City Government of Panabo
A2: Province of Davao del Norte
A3: STATEMENT OF CHANGES IN NET ASSETS/EQUITY
A4: All Funds
A5: For the Year Ended December 31, 2021
A6: (With Comparative Figures for CY 2020)
A7: (In Philippine Peso)
B9: Note | D9: 2021 | E9: 2020
A10: Balance at January 1 | D10: =+E18 -> 2.9496322e+09 | E10: 2.7744008e+09 | G10: =D10-#REF! -> #REF! | H10: =E10-#REF! -> #REF!
A11: Add (Deduct):
A12: Changes in Accounting Policy | H12: =E12-#REF! -> #REF!
A13: Prior Period Errors | B13: 33 | D13: -3.4565567e+08 | E13: -1.9122355e+08 | G13: =D13-#REF! -> #REF! | H13: =E13-#REF! -> #REF!
A14: Restated Balance | D14: =SUM(D10:D13) -> 2.6039765e+09 | E14: =E10+E12+E13 -> 2.5831773e+09 | G14: =D14-#REF! -> #REF! | H14: =E14-#REF! -> #REF!
A15: Add (Deduct) Changes in net assets/equity during the year
A16: Surplus (Deficit) for the period | D16: =SFPER!D30 -> 4.2307988e+08 | E16: =SFPER!E30 -> 3.6645493e+08 | G16: =D16-#REF! -> #REF! | H16: =E16-#REF! -> #REF!
A17: Total changes during the year | D17: =D16 -> 4.2307988e+08 | E17: =E16 -> 3.6645493e+08
A18: Balance at December 31 | D18: =D14+D16 -> 3.0270564e+09 | E18: =E14+E16 -> 2.9496322e+09
A20: (See accompanying Notes to Financial Statements.)

Sheet SCF
A1: City Government of Panabo
A2: Province of Davao del Norte
A3: STATEMENT OF CASH FLOWS
A4: All Funds
A5: For the Year Ended December 31, 2021
A6: (With Comparative Figures for CY 2020)
A7: (In Philippine Peso)
B9: Note | D9: 2021 | F9: 2020
A10: Cash Flows from Operating Activities
A11: Cash Inflows
A12: Collection from taxpayers | D12: 2.9727308e+08 | F12: 2.8823036e+08
A13: Share from Internal Revenue Allotment | D13: 889216030 | F13: 6.6373796e+08
A14: Receipts from business/service income | D14: 1.0571275e+08 | F14: 1.1585381e+08
A15: Interest Income | D15: 385197.82 | F15: 2641158.5
A16: Other Receipts | D16: 1.2311718e+09 | F16: 9.4958274e+08
A17: Total Cash Inflows | D17: =+SUM(D12:D16) -> 2.5237588e+09 | F17: =+SUM(F12:F16) -> 2.020046e+09
A18: Cash Outflows
A19: Payment of expenses | D19: 3.3530866e+08 | F19: 4.6311603e+08
A20: Payments to suppliers and creditors | D20: 1.8193685e+08 | F20: 1.9567671e+08
A21: Payments to employees | D21: 2.581936e+08 | F21: 2.6055775e+08
A22: Interest Expense | D22: 10419963 | F22: 11780899
A23: Other Expenses | D23: 9.816656e+08 | F23: 6.8148464e+08
A24: Total Cash Outflows | D24: =+SUM(D19:D23) -> 1.7675247e+09 | F24: =+SUM(F19:F23) -> 1.612616e+09
A25: Less: Adjustments made to Cash Account:
A26: Adjustments due to double entry, staled checks & inappropriate fund/SL | F26: 0
A27: Net Cash Flows from Operating Activities | D27: =D17-D24-D26 -> 7.5623416e+08 | F27: =F17-F24-F26 -> 4.0743001e+08
A28: Cash Flow from Investing Activities
A29: Cash Inflows
A30: Proceeds from Sale/Disposal of PPE | D30: 0 | F30: 0
A31: Total Cash Inflows | D31: =+D30 -> 0 | F31: =+F30 -> 0
A32: Cash Outflows
A33: Purchase/Construction of PPE | D33: 5.3812719e+08 | F33: 2.5541602e+08
A34: Total Cash Outflows | D34: =+D33 -> 5.3812719e+08 | F34: =+F33 -> 2.5541602e+08
A35: Net Cash Flows from Investing Activities | D35: =+D31-D34 -> -5.3812719e+08 | F35: =+F31-F34 -> -2.5541602e+08
A36: Cash Flows from Financing Activities
A37: Cash Inflows
A38: Proceeds from Domestic Loans | D38: 9564783 | F38: 1.0993888e+08
A39: Total Cash Inflows | D39: =+D38 -> 9564783 | F39: =+F38 -> 1.0993888e+08
A40: Cash Outflows
A41: Payment of Long-Term Liabilities | D41: 26694021 | F41: 27389241
A42: Total Cash Outflows | D42: =+D41 -> 26694021 | F42: =+F41 -> 27389241
A43: Cash Flows from Financing Activities | D43: =D39-D42 -> -17129238 | F43: =F39-F42 -> 82549636
A44: Total Cash Provided by Operating, Investing
A45: and Financing Activities | D45: =D27+D35+D43 -> 2.0097774e+08 | F45: =F27+F35+F43 -> 2.3456362e+08
A46: Add: Cash at the Beginning of the year | D46: =F48 -> 1.1541891e+09 | F46: 9.1946492e+08
A47: Adjustment to prior year cash balance | D47: -85620.82 | F47: 160596.45
A48: Cash Balance at the End of the Year | B48: 34 | D48: =SUM(D45:D47) -> 1.3550813e+09 | F48: =SUM(F45:F47) -> 1.1541891e+09
A50: (See accompanying Notes to Financial Statements.)
D54: =D48-SFPO!D12 -> 0.001999855 | F54: =F48-SFPO!E12 -> 0

Sheet SCBAA
A1: City Government of Panabo
A2: Province of Davao del Norte
A3: STATEMENT OF COMPARISON OF BUDGET AND ACTUAL AMOUNTS
A4: For the Year Ended December 31, 2021
A5: (In Philippine Peso)
A7: PARTICULARS | F7: Note | G7: Budgeted | K7: Difference | P7: Difference
G8: Amounts | K8: Original and | N8: Actual | P8: Final Budget
H9: Original | J9: Final | K9: Final Budget | N9: Amounts | P9: and Actual
A11: Revenue
B12: A. Local Sources
C13: 1. Tax Revenue
D14: a. Tax Revenue - Property | H14: 106300000 | J14: 106300000 | L14: =H14-J14 -> 0 | N14: 91214084 | P14: =J14-N14 -> 15085916
D15: b. Tax Revenue - Goods and Services | H15: 154170000 | J15: 154170000 | L15: =H15-J15 -> 0 | N15: 1.7229295e+08 | P15: =J15-N15 -> -18122948
D16: c. Other Local Taxes | H16: 9770000 | J16: 9770000 | L16: =H16-J16 -> 0 | N16: 17703663 | P16: =J16-N16 -> -7933662.6
C17: Total Tax Revenue | H17: =SUM(H14:H16) -> 270240000 | J17: =SUM(J14:J16) -> 270240000 | L17: =SUM(L14:L16) -> 0 | N17: =SUM(N14:N16) -> 2.8121069e+08 | P17: =SUM(P14:P16) -> -10970694
C18: 2. Non-Tax Revenue
D19: a. Service Income | H19: 54570000 | J19: 54570000 | L19: =H19-J19 -> 0 | N19: 51945013 | P19: =J19-N19 -> 2624987.3
D20: b. Business Income | H20: 97051835 | J20: 97051835 | L20: =H20-J20 -> 0 | N20: 90126956 | P20: =J20-N20 -> 6924878.6
D21: c. Other Income and Receipts | H21: 5.050527e+08 | J21: 6.4103138e+08 | L21: =H21-J21 -> -1.3597868e+08 | N21: 4.2772997e+08 | P21: =J21-N21 -> 2.1330141e+08
C22: Total Non-Tax Revenue | H22: =SUM(H19:H21) -> 6.5667454e+08 | J22: =SUM(J19:J21) -> 7.9265321e+08 | L22: =SUM(L19:L21) -> -1.3597868e+08 | N22: =SUM(N19:N21) -> 5.6980194e+08 | P22: =SUM(P19:P21) -> 2.2285128e+08
B23: B. External Sources
C24: 1. Share from the National Internal Revenue Taxes (IRA) | H24: 829672451 | J24: 889216030 | L24: =H24-J24 -> -59543579 | N24: 889216030 | P24: =J24-N24 -> 0
C25: 2. Share from GOCCs
D26: a. Share from PCSO | H26: 700000 | J26: 700000 | L26: =H26-J26 -> 0 | N26: 1192785.3 | P26: =J26-N26 -> -492785.32
C27: 3. Other Shares from National Tax Collections
D28: a. Share from Ecozone | L28: 0 | N28: 72609 | P28: =J28-N28 -> -72609
D29: b. Share from National Wealth | L29: =H29-J29 -> 0 | P29: =J29-N29 -> 0
C30: 4. Other Receipts | P30: =J30-N30 -> 0
C31: 4. Other Receipts
D32: a. Grants and Donations | L32: =H32-J32 -> 0 | P32: =J32-N32 -> 0
D33: b. Other Subsidy Income | J33: 15122372 | L33: =H33-J33 -> -15122372 | N33: 15122372 | P33: =J33-N33 -> 0
C34: 5. Inter-local Transfer | L34: =H34-J34 -> 0 | P34: =J34-N34 -> 0
C35: 6. Capital /Investment Receipts
D36: a. Sale of Capital Assets | L36: =H36-J36 -> 0 | P36: =J36-N36 -> 0
D37: b. Sale of Investments | L37: =H37-J37 -> 0 | P37: =J37-N37 -> 0
D38: c. Proceeds from Collections of Loan Receivable | L38: =H38-J38 -> 0 | N38: 549735 | P38: =J38-N38 -> -549735
B39: C. Receipts from Borrowings | P39: =J39-N39 -> 0
D40: a. Grants and Donations | L40: =H40-J40 -> 0 | P40: =J40-N40 -> 0
D41: b. Other Subsidy Income | L41: =H41-J41 -> 0 | P41: =J41-N41 -> 0
B42: C. Receipts from Borrowings | J42: 600000000 | L42: =H42-J42 -> -600000000 | N42: 9564783 | P42: =J42-N42 -> 590435217
A43: Total Revenue and Receipts | H43: =H17+H22+H24+H26+H28+H29+H40+H41+H42+H34 -> 1.757287e+09 | J43: =J17+J22+J24+J26+J28+J29+J40+J41+J42+J34+J32+J33 -> 2.5679316e+09 | L43: =L17+L22+L24+L26+L28+L29+L40+L41+L42+L34+L32+L33 -> -8.1064463e+08 | N43: =N17+N22+N24+N26+N28+N29+N40+N41+N42+N34+N33+N38 -> 1.7667309e+09 | P43: =P17+P22+P24+P26+P28+P29+P40+P41+P42+P34+P32+P33+P38 -> 8.0120067e+08
A44: Continuing Appropriations | L44: =H44-J44 -> 0 | P44: =J44-N44 -> 0
A45: Grand Total Revenue and Receipts | H45: =+H43+H44 -> 1.757287e+09 | I45: =+I43+I44 -> 0 | J45: =+J43+J44 -> 2.5679316e+09 | K45: =+K43+K44 -> 0 | L45: =+L43+L44 -> -8.1064463e+08 | M45: =+M43+M44 -> 0 | N45: =+N43+N44 -> 1.7667309e+09 | O45: =+O43+O44 -> 0 | P45: =+P43+P44 -> 8.0120067e+08
A46: Expenditures
A47: Current Aprropriations
B48: General Public Services
C49: Personnel Services | H49: 2.7485241e+08 | J49: 271983899 | L49: =H49-J49 -> 2868506.2 | N49: 2.3924396e+08 | P49: =J49-N49 -> 32739943
C50: Maintenance and Other Operating Expenses | H50: 2.4471711e+08 | J50: 2.5431194e+08 | L50: =H50-J50 -> -9594833.2 | N50: 2.3421127e+08 | P50: =J50-N50 -> 20100672
C51: Capital Outlay | H51: 9446000 | J51: 76131000 | L51: =H51-J51 -> -66685000 | N51: 14473179 | P51: =J51-N51 -> 61657821
B52: Education
C53: Personnel Services | H53: 11460000 | J53: 15468653 | L53: =H53-J53 -> -4008653.5 | N53: 15411440 | P53: =J53-N53 -> 57213.28
C54: Maintenance and Other Operating Expenses | H54: 13490000 | J54: 11035839 | L54: =H54-J54 -> 2454161 | N54: 4578103.2 | P54: =J54-N54 -> 6457735.8
C55: Capital Outlay | H55: 26800000 | J55: 46486000 | L55: =H55-J55 -> -19686000 | N55: 16827123 | P55: =J55-N55 -> 29658877
B56: Health, Nutrition and Population Control
C57: Personnel Services | H57: 53662362 | J57: 54027770 | L57: =H57-J57 -> -365407.83 | N57: 47047732 | P57: =J57-N57 -> 6980037.8
C58: Maintenance and Other Operating Expenses | H58: 29302211 | J58: 37744802 | L58: =H58-J58 -> -8442590.6 | N58: 25637293 | P58: =J58-N58 -> 12107509
C59: Capital Outlay | H59: 864000 | J59: 864000 | L59: =H59-J59 -> 0 | N59: 776348 | P59: =J59-N59 -> 87652
B60: Labor and Employment
C61: Personnel Services | L61: =H61-J61 -> 0 | P61: =J61-N61 -> 0
C62: Maintenance and Other Operating Expenses | L62: =H62-J62 -> 0 | P62: =J62-N62 -> 0
C63: Capital Outlay | L63: =H63-J63 -> 0 | P63: =J63-N63 -> 0
B64: Housing and Community Development
C65: Personnel Services | L65: =H65-J65 -> 0 | P65: =J65-N65 -> 0
C66: Maintenance and Other Operating Expenses | L66: =H66-J66 -> 0 | P66: =J66-N66 -> 0
C67: Capital Outlay | L67: =H67-J67 -> 0 | P67: =J67-N67 -> 0
B68: Social Services and Social Welfare
C69: Personnel Services | H69: 16749566 | J69: 16485149 | L69: =H69-J69 -> 264416.52 | N69: 14109582 | P69: =J69-N69 -> 2375567.7
C70: Maintenance and Other Operating Expenses | H70: 26684076 | J70: 37924586 | L70: =H70-J70 -> -11240509 | N70: 35595276 | P70: =J70-N70 -> 2329309.8
C71: Capital Outlay | H71: 120000 | J71: 2010000 | L71: =H71-J71 -> -1890000 | N71: 1788696.4 | P71: =J71-N71 -> 221303.6
B72: Economic Services
C73: Personnel Services | H73: 78418085 | J73: 74912064 | L73: =H73-J73 -> 3506021.3 | N73: 62314376 | P73: =J73-N73 -> 12597688
C74: Maintenance and Other Operating Expenses | H74: 1.4207639e+08 | J74: 1.5128018e+08 | L74: =H74-J74 -> -9203789 | N74: 1.190309e+08 | P74: =J74-N74 -> 32249281
C75: Capital Outlay | H75: 164165000 | J75: 6.1886982e+08 | L75: =H75-J75 -> -4.5470482e+08 | N75: 55892241 | P75: =J75-N75 -> 5.6297758e+08
B76: Other Purposes:
C77: Debt Service
D78: Financial Expense | L78: =H78-J78 -> 0 | P78: =J78-N78 -> 0
C79: Debt Service
D80: Financial Expense | H80: 45965581 | J80: 49108874 | L80: =H80-J80 -> -3143293.5 | N80: 10687840 | P80: =J80-N80 -> 38421034
D81: Amortization | L81: 0 | N81: 27653354 | P81: =J81-N81 -> -27653354
C82: LDRRMF
D83: Maintenance and Other Operating Expenses | H83: 29003942 | J83: 58628415 | L83: =H83-J83 -> -29624473 | N83: 51789959 | P83: =J83-N83 -> 6838456
D84: Capital Outlay | H84: 26342531 | J84: 14704025 | L84: =H84-J84 -> 11638506 | N84: 0 | P84: =J84-N84 -> 14704025
C85: 20% Development Fund
D86: Maintenance and Other Operating Expenses | L86: =H86-J86 -> 0 | N86: 423852.48 | P86: =J86-N86 -> -423852.48
D87: Capital Outlay | H87: 11000000 | J87: 195599800 | L87: =H87-J87 -> -184599800 | N87: 1.3295925e+08 | P87: =J87-N87 -> 62640552
C88: Share from National Wealth
D89: Maintenance and Other Operating Expenses | L89: =H89-J89 -> 0 | P89: =J89-N89 -> 0
D90: Capital Outlay | L90: =H90-J90 -> 0 | P90: =J90-N90 -> 0
C91: Allocation for Senior Citizens and PWD
C92: Allocation for Senior Citizens and PWD
D93: Maintenance and Other Operating Expenses | L93: =H93-J93 -> 0 | P93: =J93-N93 -> 0
D94: Capital Outlay | L94: =H94-J94 -> 0 | P94: =J94-N94 -> 0
C95: Others
D96: Aid to Barangays | H96: 2800000 | J96: 2800000 | L96: =H96-J96 -> 0 | M96: 2396000 | N96: 2660000 | P96: =J96-N96 -> 140000
D97: Confidential Fund | H97: 28440000 | J97: 28440000 | L97: =H97-J97 -> 0 | N97: 28440000 | P97: =J97-N97 -> 0
D98: 2% Discretionary Fund | H98: 672389.99 | J98: 672389.99 | L98: =H98-J98 -> 0 | N98: 672292.51 | P98: =J98-N98 -> 97.48
D99: MPBF | J99: 44632622 | L99: =H99-J99 -> -44632622 | N99: 43168830 | P99: =J99-N99 -> 1463792.5
D100: Subsidy to Economic Enterprise/Special Accounts | J100: 15122372 | L100: =H100-J100 -> -15122372 | N100: 15122372 | P100: =J100-N100 -> 0
D101: Subsidy to Other Funds | L101: =H101-J101 -> 0 | P101: =J101-N101 -> 0
C102: Total Current Approrpiations | H102: =SUM(H49:H101) -> 1.2370316e+09 | J102: =SUM(J49:J101) -> 2.0792442e+09 | L102: =SUM(L49:L101) -> -8.4221255e+08 | N102: =SUM(N49:N101) -> 1.2005153e+09 | P102: =SUM(P49:P101) -> 8.7872894e+08
...
