Workbook

Sheet A
A1: City Government of Panabo
A2: CONSOLIDATED DETAILED STATEMENT OF FINANCIAL POSITION (BY FUND)
A3: As at December 31, 2021
A4: (With Comparative Figures for CY 2020)
A5: (In Philippine Peso)
A7: PARTICULARS | F7: 2021 | K7: 2020 | P7: 2019
F8: TOTAL | G8: GF | H8: SEF | I8: TF | K8: TOTAL | L8: GF | M8: SEF | N8: TF | P8: TOTAL | Q8: GF | R8: SEF | S8: TF
A9: ASSETS
A10: CURRENT ASSETS
B11: CASH AND CASH EQUIVALENTS
C12: Cash on Hand
D13: Cash Local Treasury | F13: =G13+H13+I13 -> 2681394.5 | G13: 1489852.3 | H13: 1191542.2 | I13: 0 | K13: =L13+M13+N13 -> 4330941 | L13: 2950687.1 | M13: 1376653.9 | N13: 3600 | P13: =Q13+R13+S13 -> 18646663 | Q13: 11921215 | R13: 5695870.5 | S13: 1029577
D14: Petty Cash | F14: =G14+H14+I14 -> 0 | K14: =L14+M14+N14 -> 0 | P14: =Q14+R14+S14 -> 0
C15: Cash in Bank-Local Currency
D16: Cash in Bank -Local Currency, Current Account | F16: =G16+H16+I16 -> 1.3523999e+09 | G16: 7.7697196e+08 | H16: 80064146 | I16: 4.9536376e+08 | K16: =L16+M16+N16 -> 1.1498582e+09 | L16: 9.0900227e+08 | M16: 77943922 | N16: 1.6291201e+08 | P16: =Q16+R16+S16 -> 8.4300502e+08 | Q16: 7.1307069e+08 | R16: 50529243 | S16: 79405087
D17: Cash in Bank -Local Currency, Savings Account | F17: =G17+H17+I17 -> 0 | K17: =L17+M17+N17 -> 0 | P17: =Q17+R17+S17 -> 0
C18: Cash in Bank- Foreign Currency
D19: Cash in Bank - Foreign Currency, Current Account | F19: =G19+H19+I19 -> 0 | K19: =L19+M19+N19 -> 0 | P19: =Q19+R19+S19 -> 0
D20: Cash in Bank - Foreign Currency, Savings Account | F20: =G20+H20+I20 -> 0 | K20: =L20+M20+N20 -> 0 | P20: =Q20+R20+S20 -> 0
C21: Investments in Time Deposits (90 days)
D22: Cash in Bank - Local Currency, Time Deposits | F22: =G22+H22+I22 -> 0 | G22: 0 | H22: 0 | I22: 0 | K22: =L22+M22+N22 -> 0 | L22: 0 | M22: 0 | N22: 0 | P22: =Q22+R22+S22 -> 57813241 | Q22: 57813241 | R22: 0 | S22: 0
D23: Cash in Bank - Foreign Currency, Time Deposits | F23: =G23+H23+I23 -> 0 | K23: =L23+M23+N23 -> 0 | P23: =Q23+R23+S23 -> 0
D24: Treasury Bills | F24: =G24+H24+I24 -> 0 | K24: =L24+M24+N24 -> 0 | P24: =Q24+R24+S24 -> 0
C25: Total Cash and Cash Equivalent | F25: =SUM(F13:F24) -> 1.3550813e+09 | G25: =SUM(G13:G24) -> 7.7846181e+08 | H25: =SUM(H13:H24) -> 81255688 | I25: =SUM(I13:I24) -> 4.9536376e+08 | K25: =SUM(K13:K24) -> 1.1541891e+09 | L25: =SUM(L13:L24) -> 9.1195295e+08 | M25: =SUM(M13:M24) -> 79320576 | N25: =SUM(N13:N24) -> 1.6291561e+08 | P25: =SUM(P13:P24) -> 9.1946492e+08 | Q25: =SUM(Q13:Q24) -> 7.8280515e+08 | R25: =SUM(R13:R24) -> 56225113 | S25: =SUM(S13:S24) -> 80434664 | U25: =+K25-P25 -> 2.3472422e+08
B26: INVESTMENTS
C27: Investments in Time Deposits ( 91 days to 1 year)
D28: Cash in Bank - Local Currency, Time Deposits | F28: =G28+H28+I28 -> 0 | K28: =L28+M28+N28 -> 0 | P28: =Q28+R28+S28 -> 0
D29: Cash in Bank - Foreign Currency, Time Deposits | F29: =G29+H29+I29 -> 0 | K29: =L29+M29+N29 -> 0 | P29: =Q29+R29+S29 -> 0
D30: Treasury Bills | F30: =G30+H30+I30 -> 0 | K30: =L30+M30+N30 -> 0 | P30: =Q30+R30+S30 -> 0
C31: Financial Assets at Fair Value through Surplus or Deficit
D32: Financial Assets Held for Trading | F32: =G32+H32+I32 -> 0 | K32: =L32+M32+N32 -> 0 | P32: =Q32+R32+S32 -> 0
D33: Financial Assets Designated at Fair Value through Surplus or Deficit | F33: =G33+H33+I33 -> 0 | K33: =L33+M33+N33 -> 0 | P33: =Q33+R33+S33 -> 0
C34: Financial Assets - Held to Maturity
D35: Investment in Treasury Bills - Local | F35: =G35+H35+I35 -> 0 | K35: =L35+M35+N35 -> 0 | P35: =Q35+R35+S35 -> 0
D36: Allowance for Impairment - Investment in Treasury Bills - Local | F36: =G36+H36+I36 -> 0 | K36: =L36+M36+N36 -> 0 | P36: =Q36+R36+S36 -> 0
D37: Investment in Bonds - Local | F37: =G37+H37+I37 -> 0 | K37: =L37+M37+N37 -> 0 | P37: =Q37+R37+S37 -> 0
D38: Allowance for Impairment - Investment in Bonds - Local | F38: =G38+H38+I38 -> 0 | K38: =L38+M38+N38 -> 0 | P38: =Q38+R38+S38 -> 0
C39: Financial Assets - Available for Sale
D40: Investments in Stocks | F40: =G40+H40+I40 -> 0 | K40: =L40+M40+N40 -> 0 | P40: =Q40+R40+S40 -> 0
D41: Investments in Bonds | F41: =G41+H41+I41 -> 0 | K41: =L41+M41+N41 -> 0 | P41: =Q41+R41+S41 -> 0
C42: Financial Assets - Others
D43: Deposits on Letters of Credit | F43: =G43+H43+I43 -> 0 | G43: 0 | H43: 0 | I43: 0 | K43: =L43+M43+N43 -> 0 | L43: 0 | M43: 0 | N43: 0 | P43: =Q43+R43+S43 -> 63890000 | Q43: 63890000 | R43: 0 | S43: 0
D44: Allowance for Impairment - Deposit on Letter of Credit | F44: =G44+H44+I44 -> 0 | K44: =L44+M44+N44 -> 0 | P44: =Q44+R44+S44 -> 0
D45: Guaranty Deposits | F45: =G45+H45+I45 -> 27751603 | G45: 27454222 | H45: 175954.67 | I45: 121426.2 | K45: =L45+M45+N45 -> 29688483 | L45: 29391102 | M45: 175954.67 | N45: 121426.2 | P45: =Q45+R45+S45 -> 24102692 | Q45: 23805311 | R45: 175954.67 | S45: 121426.2
D46: Allowance for Impairment - Guaranty Deposits | F46: =G46+H46+I46 -> 0 | K46: =L46+M46+N46 -> 0 | P46: =Q46+R46+S46 -> 0
D47: Other Investments | F47: =G47+H47+I47 -> 0 | K47: =L47+M47+N47 -> 0 | P47: =Q47+R47+S47 -> 0
D48: Allowance for Impairment - Other Investments | F48: =G48+H48+I48 -> 0 | K48: =L48+M48+N48 -> 0 | P48: =Q48+R48+S48 -> 0
C49: Investments in Joint Venture
D50: Investments in Joint Venture | F50: =G50+H50+I50 -> 0 | K50: =L50+M50+N50 -> 0 | P50: =Q50+R50+S50 -> 0
D51: Allowance for Impairment - Investments in Joint Venture | F51: =G51+H51+I51 -> 0 | K51: =L51+M51+N51 -> 0 | P51: =Q51+R51+S51 -> 0
C52: Sinking Fund
D53: Sinking Fund | F53: =G53+H53+I53 -> 0 | K53: =L53+M53+N53 -> 0 | P53: =Q53+R53+S53 -> 0
C54: Total Investments | F54: =SUM(F27:F53) -> 27751603 | G54: =SUM(G27:G53) -> 27454222 | H54: =SUM(H27:H53) -> 175954.67 | I54: =SUM(I27:I53) -> 121426.2 | K54: =SUM(K27:K53) -> 29688483 | L54: =SUM(L27:L53) -> 29391102 | M54: =SUM(M27:M53) -> 175954.67 | N54: =SUM(N27:N53) -> 121426.2 | P54: =SUM(P27:P53) -> 87992692 | Q54: =SUM(Q27:Q53) -> 87695311 | R54: =SUM(R27:R53) -> 175954.67 | S54: =SUM(S27:S53) -> 121426.2 | U54: =+K54-P54 -> -58304209
B55: RECEIVABLES
C56: Loans and Receivable Accounts
D57: Accounts Receivable | F57: =G57+H57+I57 -> 2171875 | G57: 2171875 | H57: 0 | I57: 0 | K57: =L57+M57+N57 -> 2624712 | L57: 2624712 | M57: 0 | N57: 0 | P57: =Q57+R57+S57 -> 2303831.1 | Q57: 2303831.1 | R57: 0 | S57: 0
D58: Allowance for Impairment - Accounts Receivable | K58: =L58+M58+N58 -> 0 | P58: =Q58+R58+S58 -> 0
D59: Real Property Tax Receivable | F59: =G59+H59+I59 -> 1485422.8 | G59: 1485422.8 | H59: 0 | I59: 0 | K59: =L59+M59+N59 -> 10354874 | L59: 10354874 | M59: 0 | N59: 0 | P59: =Q59+R59+S59 -> 10383406 | Q59: 10383406 | S59: 0
D60: Allowance for Impairment - RPT Receivable | F60: =G60+H60+I60 -> 0 | K60: =L60+M60+N60 -> 0 | P60: =Q60+R60+S60 -> 0
D61: Special Education Tax Receivable | F61: =G61+H61+I61 -> 0 | K61: =L61+M61+N61 -> 0 | L61: 0 | M61: 0 | N61: 0 | P61: =Q61+R61+S61 -> 0 | Q61: 0 | R61: 0 | S61: 0
D62: Allowance for Impairment - SET Receivable | F62: =G62+H62+I62 -> 0 | K62: =L62+M62+N62 -> 0 | P62: =Q62+R62+S62 -> 0
D63: Notes Receivable | F63: =G63+H63+I63 -> 0 | K63: =L63+M63+N63 -> 0 | P63: =Q63+R63+S63 -> 0
D64: Allowance for Impairment - Notes Receivable | F64: =G64+H64+I64 -> 0 | K64: =L64+M64+N64 -> 0 | P64: =Q64+R64+S64 -> 0
D65: Loans Receivable-GOCCs | F65: =G65+H65+I65 -> 0 | K65: =L65+M65+N65 -> 0 | P65: =Q65+R65+S65 -> 0
D66: Allowance for Impairment - Loans Receivable-GOCCs | F66: =G66+H66+I66 -> 0 | K66: =L66+M66+N66 -> 0 | P66: =Q66+R66+S66 -> 0
D67: Loans Receivable-LGUs | F67: =G67+H67+I67 -> 0 | K67: =L67+M67+N67 -> 0 | P67: =Q67+R67+S67 -> 0
D68: Allowance for Impairment - Loans Receivable-LGUs | F68: =G68+H68+I68 -> 0 | K68: =L68+M68+N68 -> 0 | P68: =Q68+R68+S68 -> 0
D69: Interests Receivable | F69: =G69+H69+I69 -> 0 | K69: =L69+M69+N69 -> 0 | P69: =Q69+R69+S69 -> 0
D70: Allowance for Impairment - Interests Receivable | F70: =G70+H70+I70 -> 0 | K70: =L70+M70+N70 -> 0 | P70: =Q70+R70+S70 -> 0
D71: Dividends Recievable | F71: =G71+H71+I71 -> 0 | K71: =L71+M71+N71 -> 0 | P71: =Q71+R71+S71 -> 0
D72: Allowance for Impairment - Dividends Receivable | F72: =G72+H72+I72 -> 0 | K72: =L72+M72+N72 -> 0 | P72: =Q72+R72+S72 -> 0
D73: Loans Receivables-Others | F73: =G73+H73+I73 -> 18040344 | G73: 16623833 | H73: 0 | I73: 1416511 | K73: =L73+M73+N73 -> 17070619 | L73: 15693568 | N73: 1377051 | P73: =Q73+R73+S73 -> 15890719 | Q73: 14734468 | S73: 1156251
D74: Allowance for Impairment - Loans Receivable-Others | F74: =G74+H74+I74 -> 0 | K74: =L74+M74+N74 -> 0 | P74: =Q74+R74+S74 -> 0
C75: Lease Receivables
D76: Operating Lease Receivable | F76: =G76+H76+I76 -> 1947493.1 | G76: 1947493.1 | H76: 0 | I76: 0 | K76: =L76+M76+N76 -> 2025653.3 | L76: 2025653.3 | P76: =Q76+R76+S76 -> 0
D77: Allowance for Impairment - Operating Lease Receivable | F77: =G77+H77+I77 -> 0 | K77: =L77+M77+N77 -> 0 | P77: =Q77+R77+S77 -> 0
D78: Finance Lease Receivable | F78: =G78+H78+I78 -> 0 | K78: =L78+M78+N78 -> 0 | P78: =Q78+R78+S78 -> 0
D79: Allowance for Impairment - Finance Lease Receivable | F79: =G79+H79+I79 -> 0 | K79: =L79+M79+N79 -> 0 | P79: =Q79+R79+S79 -> 0
C80: Inter-Agency Receivables
D81: Due from NGAs | F81: =G81+H81+I81 -> 5758287.1 | G81: 5230781.2 | H81: 500000 | I81: 27505.86 | K81: =L81+M81+N81 -> 5732932.2 | L81: 5230781.2 | M81: 500000 | N81: 2151 | P81: =Q81+R81+S81 -> 5930432.2 | Q81: 5428281.2 | R81: 500000 | S81: 2151
D82: Allowance for Impairment - Due from NGAs | F82: =G82+H82+I82 -> 0 | K82: =L82+M82+N82 -> 0 | P82: =Q82+R82+S82 -> 0
D83: Due from GOCCs | F83: =G83+H83+I83 -> 400 | G83: 400 | H83: 0 | K83: =L83+M83+N83 -> 400 | L83: 400 | M83: 0 | N83: 0 | P83: =Q83+R83+S83 -> 400 | Q83: 400 | R83: 0 | S83: 0
D84: Allowance for Impairment - Due from GOCCs | F84: =G84+H84+I84 -> 0 | K84: =L84+M84+N84 -> 0 | P84: =Q84+R84+S84 -> 0
D85: Due from LGUs | F85: =G85+H85+I85 -> 9542870.4 | G85: 9210005.8 | H85: 0 | I85: 332864.57 | K85: =L85+M85+N85 -> 9940238 | L85: 9607373.5 | N85: 332864.57 | P85: =Q85+R85+S85 -> 9560840 | Q85: 9356038.7 | S85: 204801.3
D86: Allowance for Impairment - Due from LGUs | F86: =G86+H86+I86 -> 0 | K86: =L86+M86+N86 -> 0 | P86: =Q86+R86+S86 -> 0
D87: Due from Joint Venture | F87: =G87+H87+I87 -> 0 | K87: =L87+M87+N87 -> 0 | P87: =Q87+R87+S87 -> 0
D88: Allowance for Impairment - Due from Joint Venture | F88: =G88+H88+I88 -> 0 | K88: =L88+M88+N88 -> 0 | P88: =Q88+R88+S88 -> 0
C89: Intra-Agency Receivables
D90: Due from Other Funds | F90: =G90+H90+I90 -> 67477852 | G90: 29602514 | H90: 194476.61 | I90: 37680862 | K90: =L90+M90+N90 -> 61746587 | L90: 33160886 | M90: 319938.2 | N90: 28265763 | P90: =Q90+R90+S90 -> 42922987 | Q90: 35191493 | R90: 503194.86 | S90: 7228299.4
D91: Due from Special Accounts | F91: =G91+H91+I91 -> 17751951 | G91: 17751951 | H91: 0 | I91: 0 | K91: =L91+M91+N91 -> 27246467 | L91: 27246467 | M91: 0 | N91: 0 | P91: =Q91+R91+S91 -> 26031224 | Q91: 26031224 | R91: 0 | S91: 0
D92: Due from Local Economic Enterprise | F92: =G92+H92+I92 -> 3431982.9 | G92: 3431982.9 | H92: 0 | I92: 0 | K92: =L92+M92+N92 -> 9494315.2 | L92: 9494315.2 | M92: 0 | N92: 0 | P92: =Q92+R92+S92 -> 21042802 | Q92: 21042802 | R92: 0 | S92: 0
C93: Advances
D94: Advances for Operating Expenses | F94: =G94+H94+I94 -> 7113194.7 | G94: 7113194.7 | H94: 0 | I94: 0 | K94: =L94+M94+N94 -> 8270000 | L94: 8270000 | M94: 0 | N94: 0 | P94: =Q94+R94+S94 -> 6075000 | Q94: 6075000 | R94: 0 | S94: 0
D95: Advances for Payroll | F95: =G95+H95+I95 -> 3900426 | G95: 3900606 | H95: -180 | I95: 0 | K95: =L95+M95+N95 -> 660644.89 | L95: 620045.15 | M95: 37899.74 | N95: 2700 | P95: =Q95+R95+S95 -> 658366.46 | Q95: 539974.67 | R95: 118391.79 | S95: 0
D96: Advances to Special Disbursing Officer | F96: =G96+H96+I96 -> 0 | K96: =L96+M96+N96 -> 0 | P96: =Q96+R96+S96 -> 0
D97: Advances to Officers and Employees | F97: =G97+H97+I97 -> 24484.04 | G97: 24484.04 | H97: 0 | I97: 0 | K97: =L97+M97+N97 -> 62515.32 | L97: 62515.32 | M97: 0 | N97: 0 | P97: =Q97+R97+S97 -> 32096.92 | Q97: 32096.92 | R97: 0 | S97: 0
C98: Other Receivables
D99: Receivables - Disallowances/Charges | F99: =G99+H99+I99 -> 862806.31 | G99: 857166.31 | H99: 5640 | K99: =L99+M99+N99 -> 242633.42 | L99: 236993.42 | M99: 5640 | P99: =Q99+R99+S99 -> 290323.42 | Q99: 283993.42 | R99: 6330
D100: Allowance for Impairment - Receivables-Disallowances/Charges | F100: =G100+H100+I100 -> 0 | K100: =L100+M100+N100 -> 0 | P100: =Q100+R100+S100 -> 0
D101: Due from Officers and Employees | F101: =G101+H101+I101 -> 482358.8 | G101: 437295.34 | H101: 45052.01 | I101: 11.45 | K101: =L101+M101+N101 -> 487222.89 | L101: 442199.33 | M101: 45012.11 | N101: 11.45 | P101: =Q101+R101+S101 -> 535071.27 | Q101: 489802.72 | R101: 44998.1 | S101: 270.45
...

Sheet B
A1: City Government of Panabo
A2: CONSOLIDATED DETAILED STATEMENT OF FINANCIAL PERFORMANCE (BY FUND)
A3: For the Year Ended December 31, 2021
A4: (With Comparative figures in 2020)
A5: (In Philippine Peso)
A7: PARTICULARS | F7: 2021 | K7: 2020 | P7: 2019
F8: TOTAL | G8: GF | H8: SEF | I8: TF | K8: TOTAL | L8: GF | M8: SEF | N8: TF | P8: TOTAL | Q8: GF | R8: SEF | S8: TF
A10: REVENUE
B11: TAX REVENUE
C12: Tax Revenue - Individual and Corporation
D13: Professional Tax | F13: =SUM(G13:I13) -> 245025 | G13: 245025 | H13: 0 | I13: 0 | K13: =SUM(L13:N13) -> 277456.5 | L13: 277456.5 | M13: 0 | N13: 0 | P13: =SUM(Q13:S13) -> 255920 | Q13: 255920 | R13: 0 | S13: 0
D14: Community Tax | F14: =SUM(G14:I14) -> 5212532.6 | G14: 5212532.6 | H14: 0 | I14: 0 | K14: =SUM(L14:N14) -> 5438433.1 | L14: 5438433.1 | M14: 0 | N14: 0 | P14: =SUM(Q14:S14) -> 4715687.4 | Q14: 4715687.4 | R14: 0 | S14: 0
C15: Tax Revenue - Property
D16: Real Property Tax- Basic | F16: =SUM(G16:I16) -> 44414879 | G16: 44414879 | H16: 0 | I16: 0 | K16: =SUM(L16:N16) -> 40528682 | L16: 40528682 | M16: 0 | N16: 0 | P16: =SUM(Q16:S16) -> 40306697 | Q16: 40306697 | R16: 0 | S16: 0
D17: Discount on Real Property Tax- Basic | F17: =SUM(G17:I17) -> -3152274.1 | G17: -3152274.1 | H17: 0 | I17: 0 | K17: =SUM(L17:N17) -> -2664119.4 | L17: -2664119.4 | M17: 0 | N17: 0 | P17: =SUM(Q17:S17) -> -2712968.4 | Q17: -2712968.4 | R17: 0 | S17: 0
D18: Special Education Tax | F18: =SUM(G18:I18) -> 63354365 | G18: 0 | H18: 63354365 | I18: 0 | K18: =SUM(L18:N18) -> 59453586 | L18: 0 | M18: 59453586 | N18: 0 | P18: =SUM(Q18:S18) -> 57578153 | Q18: 0 | R18: 57578153 | S18: 0
D19: Discount on Special Education Tax | F19: =SUM(G19:I19) -> -4591616 | G19: 0 | H19: -4591616 | I19: 0 | K19: =SUM(L19:N19) -> -3930162.8 | L19: 0 | M19: -3930162.8 | N19: 0 | P19: =SUM(Q19:S19) -> -3875729.8 | Q19: 0 | R19: -3875729.8 | S19: 0
D20: Special Levy on Idle Lands | F20: =SUM(G20:I20) -> 0 | K20: =SUM(L20:N20) -> 1995681.8 | L20: 1995681.8 | P20: =SUM(Q20:S20) -> 0
D21: Special Levy on Lands Benefited by Public Works Projects | F21: =SUM(G21:I21) -> 0 | K21: =SUM(L21:N21) -> 0 | P21: =SUM(Q21:S21) -> 0
D22: Real Property Transfer Tax | F22: =SUM(G22:I22) -> 4688711.5 | G22: 4688711.5 | H22: 0 | I22: 0 | K22: =SUM(L22:N22) -> 0 | L22: 0 | M22: 0 | N22: 0 | P22: =SUM(Q22:S22) -> 6165311.5 | Q22: 6165311.5
C23: Tax Revenue - Goods and Services
D24: Business Tax | F24: =SUM(G24:I24) -> 1.5381983e+08 | G24: 1.5381983e+08 | H24: 0 | I24: 0 | K24: =SUM(L24:N24) -> 1.6547119e+08 | L24: 1.6547119e+08 | M24: 0 | N24: 0 | P24: =SUM(Q24:S24) -> 1.5171474e+08 | Q24: 1.5171474e+08 | R24: 0 | S24: 0
D25: Tax on Sand, Gravel and Other Quarry Products | F25: =SUM(G25:I25) -> 3418089.8 | G25: 3418089.8 | H25: 0 | I25: 0 | K25: =SUM(L25:N25) -> 2418823 | L25: 2418823 | M25: 0 | N25: 0 | P25: =SUM(Q25:S25) -> 941796.89 | Q25: 941796.89 | R25: 0 | S25: 0
D26: Tax on Delivery Trucks and Vans | F26: =SUM(G26:I26) -> 2460206.2 | G26: 2460206.2 | H26: 0 | I26: 0 | K26: =SUM(L26:N26) -> 2323700.5 | L26: 2323700.5 | M26: 0 | N26: 0 | P26: =SUM(Q26:S26) -> 2384417.2 | Q26: 2384417.2 | R26: 0 | S26: 0
D27: Amusement Tax | F27: =SUM(G27:I27) -> 441866.53 | G27: 441866.53 | H27: 0 | I27: 0 | K27: =SUM(L27:N27) -> 390725 | L27: 390725 | M27: 0 | N27: 0 | P27: =SUM(Q27:S27) -> 10111883 | Q27: 10111883 | R27: 0 | S27: 0
D28: Franchise Tax | F28: =SUM(G28:I28) -> 12152951 | G28: 12152951 | H28: 0 | I28: 0 | K28: =SUM(L28:N28) -> 3650086.4 | L28: 3650086.4 | P28: =SUM(Q28:S28) -> 592.88 | Q28: 592.88 | R28: 0 | S28: 0
D29: Printing and Publication Tax | F29: =SUM(G29:I29) -> 0 | K29: =SUM(L29:N29) -> 0 | P29: =SUM(Q29:S29) -> 0
C30: Tax Revenue - Others
D31: Other Taxes | F31: =SUM(G31:I31) -> 0 | K31: =SUM(L31:N31) -> 0 | P31: =SUM(Q31:S31) -> 0 | Q31: 0 | R31: 0 | S31: 0
C32: Tax Revenue - Fines and Penalties
D33: Tax Revenue - Fines and Penalties - Taxes on Individual and Corporation | F33: =SUM(G33:I33) -> 4961851.9 | G33: 4961851.9 | H33: 0 | I33: 0 | K33: =SUM(L33:N33) -> 4105374 | L33: 4105374 | M33: 0 | N33: 0 | P33: =SUM(Q33:S33) -> 5080638.7 | Q33: 5080638.7 | R33: 0 | S33: 0
D34: Tax Revenue - Fines and Penalties - Property Taxes | F34: =SUM(G34:I34) -> 7284253.1 | G34: 3017330 | H34: 4266923.1 | I34: 0 | K34: =SUM(L34:N34) -> 6397034.8 | L34: 2633779.1 | M34: 3763255.7 | N34: 0 | P34: =SUM(Q34:S34) -> 7657814.1 | Q34: 3152732.3 | R34: 4505081.8 | S34: 0
D35: Tax Revenue - Fines and Penalties - Taxes on Goods and Services | F35: =SUM(G35:I35) -> 0 | K35: =SUM(L35:N35) -> 0 | P35: =SUM(Q35:S35) -> 0
D36: Tax Revenue - Fines and Penalties - Other Taxes | F36: =SUM(G36:I36) -> 0 | K36: =SUM(L36:N36) -> 0 | P36: =SUM(Q36:S36) -> 0
C37: Total Tax Revenue | F37: =SUM(F12:F36) -> 2.9471068e+08 | G37: =SUM(G12:G36) -> 2.31681e+08 | H37: =SUM(H12:H36) -> 63029672 | I37: =SUM(I12:I36) -> 0 | K37: =SUM(K12:K36) -> 2.8585649e+08 | L37: =SUM(L12:L36) -> 2.2656981e+08 | M37: =SUM(M12:M36) -> 59286679 | N37: =SUM(N12:N36) -> 0 | P37: =SUM(P12:P36) -> 2.8032495e+08 | Q37: 2.2211745e+08 | R37: 58207505 | S37: 0 | U37: =+K37-P37 -> 5531540.3
B38: SHARE FROM NATIONAL TAXES
C39: Share from Internal Revenue Collections (IRA) | F39: =SUM(G39:I39) -> 889216030 | G39: 889216030 | H39: 0 | I39: 0 | K39: =SUM(L39:N39) -> 829672451 | L39: 829672451 | M39: 0 | N39: 0 | P39: =SUM(Q39:S39) -> 7.3921276e+08 | Q39: 7.3921276e+08 | R39: 0 | S39: 0 | U39: =+K39-P39 -> 90459686
B40: OTHER SHARE FROM NATIONAL TAXES
C41: Share from Expanded Value Added Tax | F41: =SUM(G41:I41) -> 0 | K41: =SUM(L41:N41) -> 0 | P41: =SUM(Q41:S41) -> 0
C43: Share from National Wealth | F43: =SUM(G43:I43) -> 0 | G43: 0 | I43: 0 | K43: =SUM(L43:N43) -> 131344.5 | L43: 131344.5 | M43: 0 | N43: 0 | P43: =SUM(Q43:S43) -> 0 | Q43: 0 | R43: 0 | S43: 0
C44: Share from Tobacco Excise Tax (RA 7171 and 8240) | F44: =SUM(G44:I44) -> 0 | K44: =SUM(L44:N44) -> 0 | M44: 0 | N44: 0 | P44: =SUM(Q44:S44) -> 0 | R44: 0 | S44: 0
C45: Share from Economic Zones | F45: =SUM(G45:I45) -> 72609 | G45: 72609 | I45: 0 | K45: =SUM(L45:N45) -> 588344.53 | L45: 588344.53 | M45: 0 | N45: 0 | P45: =SUM(Q45:S45) -> 131334.6 | Q45: 131334.6 | R45: 0 | S45: 0
C46: Total Other Share from National Taxes | F46: =SUM(F41:F45) -> 72609 | G46: =SUM(G41:G45) -> 72609 | H46: =SUM(H41:H45) -> 0 | I46: =SUM(I41:I45) -> 0 | K46: =SUM(K41:K45) -> 719689.03 | L46: =SUM(L41:L45) -> 719689.03 | M46: =SUM(M41:M45) -> 0 | N46: =SUM(N41:N45) -> 0 | P46: =SUM(P41:P45) -> 131334.6 | Q46: 131334.6 | R46: 0 | S46: 0 | U46: =+K46-P46 -> 588354.43
B47: SERVICE AND BUSINESS INCOME
C48: Service Income
D49: Permit Fees | F49: =SUM(G49:I49) -> 27950097 | G49: 27950097 | H49: 0 | I49: 0 | K49: =SUM(L49:N49) -> 26011803 | L49: 26011803 | M49: 0 | N49: 0 | P49: =SUM(Q49:S49) -> 27170394 | Q49: 27170394 | R49: 0 | S49: 0 | U49: =+K49-P49 -> -1158591.1
D50: Registration Fees | F50: =SUM(G50:I50) -> 927476.4 | G50: 927476.4 | H50: 0 | I50: 0 | K50: =SUM(L50:N50) -> 1105333.6 | L50: 1105333.6 | M50: 0 | N50: 0 | P50: =SUM(Q50:S50) -> 1424072.8 | Q50: 1424072.8 | R50: 0 | S50: 0 | U50: =+K50-P50 -> -318739.2
D51: Registration Plates, Tags and Stickers Fees | F51: =SUM(G51:I51) -> 712928 | G51: 712928 | H51: 0 | I51: 0 | K51: =SUM(L51:N51) -> 704436 | L51: 704436 | M51: 0 | N51: 0 | P51: =SUM(Q51:S51) -> 642589.45 | Q51: 642589.45 | R51: 0 | S51: 0 | U51: =+K51-P51 -> 61846.55
D52: Clearance and Certification Fees | F52: =SUM(G52:I52) -> 10777112 | G52: 10777112 | H52: 0 | I52: 0 | K52: =SUM(L52:N52) -> 8643620.3 | L52: 8643620.3 | M52: 0 | N52: 0 | P52: =SUM(Q52:S52) -> 11960683 | Q52: 11960683 | R52: 0 | S52: 0 | U52: =+K52-P52 -> -3317063.1
D53: Supervision and Regulation Enforcement Fees | F53: =SUM(G53:I53) -> 4376013.9 | G53: 4376013.9 | H53: 0 | I53: 0 | K53: =SUM(L53:N53) -> 5019065 | L53: 5019065 | M53: 0 | N53: 0 | P53: =SUM(Q53:S53) -> 5988088 | Q53: 5988088 | R53: 0 | S53: 0 | U53: =+K53-P53 -> -969023
D54: Inspection Fees | F54: =SUM(G54:I54) -> 3716893.8 | G54: 3716893.8 | H54: 0 | I54: 0 | K54: =SUM(L54:N54) -> 3237870.1 | L54: 3237870.1 | M54: 0 | N54: 0 | P54: =SUM(Q54:S54) -> 3471487 | Q54: 3471487 | R54: 0 | S54: 0 | U54: =+K54-P54 -> -233616.96
D55: Verification and Authentication Fees | F55: =SUM(G55:I55) -> 651712 | G55: 651712 | H55: 0 | I55: 0 | K55: =SUM(L55:N55) -> 255327 | L55: 255327 | M55: 0 | N55: 0 | P55: =SUM(Q55:S55) -> 303169 | Q55: 303169 | R55: 0 | S55: 0 | U55: =+K55-P55 -> -47842
D56: Processing Fees | F56: =SUM(G56:I56) -> 1388828 | G56: 1388828 | H56: 0 | I56: 0 | K56: =SUM(L56:N56) -> 1157694 | L56: 1157694 | M56: 0 | N56: 0 | P56: =SUM(Q56:S56) -> 1399737.2 | Q56: 1399737.2 | R56: 0 | S56: 0 | U56: =+K56-P56 -> -242043.25
D57: Occupation Fees | F57: =SUM(G57:I57) -> 0 | H57: 0 | I57: 0 | K57: =SUM(L57:N57) -> 0 | M57: 0 | N57: 0 | P57: =SUM(Q57:S57) -> 0 | U57: =+K57-P57 -> 0
D58: Fishery Rental Fees and Charges | F58: =SUM(G58:I58) -> 0 | H58: 0 | I58: 0 | K58: =SUM(L58:N58) -> 0 | M58: 0 | N58: 0 | P58: =SUM(Q58:S58) -> 0 | U58: =+K58-P58 -> 0
D59: Fees for Sealing and Licensing of Weights and Measures | F59: =SUM(G59:I59) -> 387780 | G59: 387780 | H59: 0 | I59: 0 | K59: =SUM(L59:N59) -> 257160 | L59: 257160 | M59: 0 | N59: 0 | P59: =SUM(Q59:S59) -> 332020 | Q59: 332020 | R59: 0 | S59: 0 | U59: =+K59-P59 -> -74860
D60: Fines and Penalties - Service Income | F60: =SUM(G60:I60) -> 528242.85 | G60: 528242.85 | H60: 0 | I60: 0 | K60: =SUM(L60:N60) -> 207687.24 | L60: 207687.24 | M60: 0 | N60: 0 | P60: =SUM(Q60:S60) -> 328640.09 | Q60: 328640.09 | R60: 0 | S60: 0 | U60: =+K60-P60 -> -120952.85
D61: Other Service Income | F61: =SUM(G61:I61) -> 527929 | G61: 527929 | H61: 0 | I61: 0 | K61: =SUM(L61:N61) -> 459888 | L61: 459888 | M61: 0 | N61: 0 | P61: =SUM(Q61:S61) -> 596390 | Q61: 596390 | R61: 0 | S61: 0 | U61: =+K61-P61 -> -136502
C62: Business Income | U62: =+K62-P62 -> 0
D63: School Fees | F63: =SUM(G63:I63) -> 0 | K63: =SUM(L63:N63) -> 0 | P63: =SUM(Q63:S63) -> 0 | U63: =+K63-P63 -> 0
D64: Affiliation Fees | F64: =SUM(G64:I64) -> 0 | K64: =SUM(L64:N64) -> 0 | P64: =SUM(Q64:S64) -> 0 | U64: =+K64-P64 -> 0
D65: Seminar/Training Fees | F65: =SUM(G65:I65) -> 0 | K65: =SUM(L65:N65) -> 0 | P65: =SUM(Q65:S65) -> 0 | U65: =+K65-P65 -> 0
D66: Rent Income | F66: =SUM(G66:I66) -> 38062440 | G66: 38062440 | H66: 0 | I66: 0 | K66: =SUM(L66:N66) -> 694764.84 | L66: 694764.84 | M66: 0 | N66: 0 | P66: =SUM(Q66:S66) -> 1325939.5 | Q66: 1325939.5 | R66: 0 | S66: 0 | U66: =+K66-P66 -> -631174.66
D67: Communication Network Fees | F67: =SUM(G67:I67) -> 0 | H67: 0 | I67: 0 | K67: =SUM(L67:N67) -> 0 | M67: 0 | N67: 0 | P67: =SUM(Q67:S67) -> 0 | R67: 0 | S67: 0 | U67: =+K67-P67 -> 0
D68: Transportation System Fees | F68: =SUM(G68:I68) -> 0 | H68: 0 | I68: 0 | K68: =SUM(L68:N68) -> 0 | M68: 0 | N68: 0 | P68: =SUM(Q68:S68) -> 0 | R68: 0 | S68: 0 | U68: =+K68-P68 -> 0
D69: Road Network Fees | F69: =SUM(G69:I69) -> 798273 | G69: 798273 | H69: 0 | I69: 0 | K69: =SUM(L69:N69) -> 7935752.8 | L69: 7935752.8 | M69: 0 | N69: 0 | P69: =SUM(Q69:S69) -> 19291493 | Q69: 19291493 | R69: 0 | S69: 0 | U69: =+K69-P69 -> -11355740
D70: Waterworks System Fees | F70: =SUM(G70:I70) -> 0 | H70: 0 | I70: 0 | K70: =SUM(L70:N70) -> 0 | M70: 0 | N70: 0 | P70: =SUM(Q70:S70) -> 0 | R70: 0 | S70: 0 | U70: =+K70-P70 -> 0
D71: Power Supply System Fees | F71: =SUM(G71:I71) -> 0 | H71: 0 | I71: 0 | K71: =SUM(L71:N71) -> 0 | M71: 0 | N71: 0 | P71: =SUM(Q71:S71) -> 0 | R71: 0 | S71: 0 | U71: =+K71-P71 -> 0
D72: Seaport System Fees | F72: =SUM(G72:I72) -> 0 | H72: 0 | I72: 0 | K72: =SUM(L72:N72) -> 0 | M72: 0 | N72: 0 | P72: =SUM(Q72:S72) -> 0 | R72: 0 | S72: 0 | U72: =+K72-P72 -> 0
D73: Parking Fees | F73: =SUM(G73:I73) -> 10320356 | G73: 10320356 | H73: 0 | I73: 0 | K73: =SUM(L73:N73) -> 357323.44 | L73: 357323.44 | M73: 0 | N73: 0 | P73: =SUM(Q73:S73) -> 626781 | Q73: 626781 | R73: 0 | S73: 0 | U73: =+K73-P73 -> -269457.56
D74: Receipts from Operation of Hostels/Dormitories and Other Like Facilities | F74: =SUM(G74:I74) -> 0 | H74: 0 | I74: 0 | K74: =SUM(L74:N74) -> 0 | M74: 0 | N74: 0 | P74: =SUM(Q74:S74) -> 0 | R74: 0 | S74: 0 | U74: =+K74-P74 -> 0
D75: Receipt from Market Operations | F75: =SUM(G75:I75) -> 11742189 | G75: 11742189 | H75: 0 | I75: 0 | K75: =SUM(L75:N75) -> 31086783 | L75: 31086783 | M75: 0 | N75: 0 | P75: =SUM(Q75:S75) -> 40680170 | Q75: 40680170 | R75: 0 | S75: 0 | U75: =+K75-P75 -> -9593387.5
D76: Receipt from Slaughterhouse Operation | F76: =SUM(G76:I76) -> 7172166 | G76: 7172166 | H76: 0 | I76: 0 | K76: =SUM(L76:N76) -> 6034164 | L76: 6034164 | M76: 0 | N76: 0 | P76: =SUM(Q76:S76) -> 6281974.3 | Q76: 6281974.3 | R76: 0 | S76: 0 | U76: =+K76-P76 -> -247810.26
D77: Receipt from Cemetery Operations | F77: =SUM(G77:I77) -> 4422170 | G77: 4422170 | H77: 0 | I77: 0 | K77: =SUM(L77:N77) -> 7111317.7 | L77: 7111317.7 | M77: 0 | N77: 0 | P77: =SUM(Q77:S77) -> 8067690.5 | Q77: 8067690.5 | R77: 0 | S77: 0 | U77: =+K77-P77 -> -956372.88
D78: Receipts from Printing and Publication | F78: =SUM(G78:I78) -> 0 | H78: 0 | I78: 0 | K78: =SUM(L78:N78) -> 0 | M78: 0 | N78: 0 | P78: =SUM(Q78:S78) -> 0 | R78: 0 | S78: 0
D79: Sales Revenue | F79: =SUM(G79:I79) -> 16752591 | G79: 16752591 | H79: 0 | I79: 0 | K79: =SUM(L79:N79) -> 12665759 | L79: 12665759 | M79: 0 | N79: 0 | P79: =SUM(Q79:S79) -> 11661398 | Q79: 11661398 | R79: 0 | S79: 0
D80: Sales Discounts | F80: =SUM(G80:I80) -> 0 | K80: =SUM(L80:N80) -> 0 | P80: =SUM(Q80:S80) -> 0
D81: Cost of Goods Manufactured
E82: Direct Materials | F82: =SUM(G82:I82) -> 0 | K82: =SUM(L82:N82) -> 0 | P82: =SUM(Q82:S82) -> 0
E83: Direct Labor | F83: =SUM(G83:I83) -> 0 | K83: =SUM(L83:N83) -> 0 | P83: =SUM(Q83:S83) -> 0
E84: Manufacturing Overhead | F84: =SUM(G84:I84) -> 0 | K84: =SUM(L84:N84) -> 0 | P84: =SUM(Q84:S84) -> 0
D85: Cost of Sales
E86: Cost of Sales | F86: =SUM(G86:I86) -> 2157631.6 | G86: 2157631.6 | H86: 0 | I86: 0 | K86: =SUM(L86:N86) -> 1923090.6 | L86: 1923090.6 | M86: 0 | N86: 0 | P86: =SUM(Q86:S86) -> 1930440.8 | Q86: 1930440.8 | R86: 0 | S86: 0
E87: Net Sales Revenue | F87: =F79-F86 -> 14594960 | G87: =G79-G86 -> 14594960 | H87: =SUM(H79:H86) -> 0 | I87: =SUM(I79:I86) -> 0 | K87: =K79-K86 -> 10742669 | L87: =L79-L86 -> 10742669 | M87: =SUM(M79:M86) -> 0 | N87: =SUM(N79:N86) -> 0 | P87: =P79-P86 -> 9730957.6 | Q87: 9730957.6 | R87: 0 | S87: 0 | U87: =+K87-P87 -> 1011711.1
D88: Garbage Fees | F88: =SUM(G88:I88) -> 349690 | G88: 349690 | H88: 0 | K88: =SUM(L88:N88) -> 353170 | L88: 353170 | P88: =SUM(Q88:S88) -> 393610 | Q88: 393610 | R88: 0 | S88: 0
D89: Hospital Fees | F89: =SUM(G89:I89) -> 1629607 | G89: 1629607 | H89: 0 | K89: =SUM(L89:N89) -> 2103314.5 | L89: 2103314.5 | P89: =SUM(Q89:S89) -> 2216526.6 | Q89: 2216526.6 | R89: 0 | S89: 0
D90: Dividend Income | F90: =SUM(G90:I90) -> 0 | K90: =SUM(L90:N90) -> 0 | P90: =SUM(Q90:S90) -> 0
D91: Interest Income | F91: =SUM(G91:I91) -> 498300.18 | G91: 463019.52 | H91: 35280.66 | I91: 0 | K91: =SUM(L91:N91) -> 2739676.6 | L91: 2677236.6 | M91: 62440.02 | N91: 0 | P91: =SUM(Q91:S91) -> 1388389.3 | Q91: 1324689.4 | R91: 63699.97 | S91: 0
D92: Service Concession Revenue | F92: =SUM(G92:I92) -> 0 | K92: =SUM(L92:N92) -> 0 | P92: =SUM(Q92:S92) -> 0
D93: Other Service Concession Revenue | F93: =SUM(G93:I93) -> 0 | K93: =SUM(L93:N93) -> 0 | P93: =SUM(Q93:S93) -> 0
D94: Lease Revenue | F94: =SUM(G94:I94) -> 0 | K94: =SUM(L94:N94) -> 0 | P94: =SUM(Q94:S94) -> 0
D95: Share in the Profit of Joint Venture | F95: =SUM(G95:I95) -> 0 | K95: =SUM(L95:N95) -> 0 | P95: =SUM(Q95:S95) -> 0
D96: Fines and Penalties - Business Income | F96: =SUM(G96:I96) -> 1934253.7 | G96: 1934253.7 | H96: 0 | K96: =SUM(L96:N96) -> 2033658.3 | L96: 2033658.3 | P96: =SUM(Q96:S96) -> 2234330.7 | Q96: 2234330.7 | R96: 0 | S96: 0
D97: Other Business Income | F97: =SUM(G97:I97) -> 0 | K97: =SUM(L97:N97) -> 0 | P97: =SUM(Q97:S97) -> 0
D98: Total Service and Business Income | F98: =SUM(F49:F78)+SUM(F87:F97) -> 1.4346942e+08 | G98: =SUM(G49:G78)+SUM(G87:G97) -> 1.4343414e+08 | H98: =SUM(H49:H78)+SUM(H87:H97) -> 35280.66 | I98: =SUM(I49:I78)+SUM(I87:I97) -> 0 | K98: =SUM(K49:K78)+SUM(K87:K97) -> 1.1825248e+08 | L98: =SUM(L49:L78)+SUM(L87:L97) -> 1.1819004e+08 | M98: =SUM(M49:M78)+SUM(M87:M97) -> 62440.02 | N98: =SUM(N49:N78)+SUM(N87:N97) -> 0 | P98: =SUM(P49:P78)+SUM(P87:P97) -> 1.4585513e+08 | Q98: 1.4579143e+08 | R98: 63699.97 | S98: 0 | U98: =+K98-P98 -> -27602656
B99: SHARES, GRANTS AND DONATIONS
C100: Share
D101: Share from PAGCOR | F101: =SUM(G101:I101) -> 0 | G101: 0 | H101: 0 | I101: 0 | K101: =SUM(L101:N101) -> 0 | L101: 0 | M101: 0 | N101: 0 | P101: =SUM(Q101:S101) -> 0 | Q101: 0 | R101: 0 | S101: 0
D102: Share from PCSO | F102: =SUM(G102:I102) -> 1192785.3 | G102: 1192785.3 | H102: 0 | I102: 0 | K102: =SUM(L102:N102) -> 218580.68 | L102: 218580.68 | M102: 0 | N102: 0 | P102: =SUM(Q102:S102) -> 637969.8 | Q102: 637969.8 | R102: 0 | S102: 0
C103: Grants and Donations
...

Sheet C
A1: City Government of Panabo
A2: CONSOLIDATED DETAILED STATEMENT OF CHANGES IN NET ASSETS/EQUITY (BY FUND)
A3: For the Year Ended December 31, 2021
A4: (With Comparative figures in 2020)
A5: (In Philippine Peso)
A8: PARTICULARS | E8: 2021 | J8: 2020 | O8: 2019
E9: TOTAL | F9: GF | G9: SEF | H9: TF | J9: TOTAL | K9: GF | L9: SEF | M9: TF | O9: TOTAL | P9: GF | Q9: SEF | R9: TF
A10: NET ASSETS/EQUITY
B11: Balance at January 1 | E11: =F11+G11+H11 -> 2.9496322e+09 | F11: =K27 -> 2.616398e+09 | G11: =L27 -> 2.9652596e+08 | H11: =M27 -> 36708289 | J11: =K11+L11+M11 -> 2.7744008e+09 | K11: =+P27 -> 2.4647606e+09 | L11: =+Q27 -> 2.7664128e+08 | M11: =+R27 -> 32998941 | O11: =P11+Q11+R11 -> 2.3950854e+09 | P11: 2.109949e+09 | Q11: 2.4300416e+08 | R11: 42132187
B12: Adjustment to Government Equity, beginning | E12: =F12+G12+H12 -> 0 | J12: =K12+L12+M12 -> 0 | O12: 0 | P12: 0 | Q12: 0 | R12: 0
C13: Add (Deduct) | Q13: 0 | R13: 0
D14: Change in Accounting Policy | E14: =F14+G14+H14 -> 0 | F14: 0 | G14: 0 | H14: 0 | J14: =K14+L14+M14 -> 0 | K14: 0 | L14: 0 | M14: 0 | O14: =P14+Q14+R14 -> 0 | P14: 0 | Q14: 0 | R14: 0
D15: Prior Period Errors | E15: =F15+G15+H15 -> -3.4565567e+08 | F15: -1.6363516e+08 | G15: -1.8061434e+08 | H15: -1406171.7 | J15: =K15+L15+M15 -> -1.9122355e+08 | K15: -1.7841096e+08 | L15: -11650871 | M15: -1161725.2 | O15: =P15+Q15+R15 -> -10194319 | P15: -13667844 | Q15: 3680350.3 | R15: -206825.25
B16: Restated Balance | E16: =SUM(E11:E15) -> 2.6039765e+09 | F16: =SUM(F11:F15) -> 2.4527628e+09 | G16: =SUM(G11:G15) -> 1.1591162e+08 | H16: =SUM(H11:H15) -> 35302117 | J16: =SUM(J11:J15) -> 2.5831773e+09 | K16: =SUM(K11:K15) -> 2.2863497e+09 | L16: =SUM(L11:L15) -> 2.6499041e+08 | M16: =SUM(M11:M15) -> 31837216 | O16: =SUM(O11:O15) -> 2.3848911e+09 | P16: 2.0962812e+09 | Q16: 2.4668451e+08 | R16: 41925362
B17: Add (Deduct) Changes in net assets/equity during the Year
C18: Adjustment of net revenue recognized directly in net assets/equity | E18: =F18+G18+H18 -> 0 | F18: 0 | G18: 0 | H18: 0 | J18: =K18+L18+M18 -> 0 | K18: 0 | L18: 0 | M18: 0 | O18: =P18+Q18+R18 -> 0 | P18: 0 | Q18: 0 | R18: 0
C19: Unrealized Gain/(Loss) from Changes in the Fair Value of Financial Assets | E19: =F19+G19+H19 -> 0 | F19: 0 | G19: 0 | H19: 0 | J19: =K19+L19+M19 -> 0 | K19: 0 | L19: 0 | M19: 0 | O19: =P19+Q19+R19 -> 0 | P19: 0 | Q19: 0 | R19: 0
C20: Suplus (Deficit) for the period | E20: =F20+G20+H20 -> 4.2307988e+08 | F20: =B!G328 -> 2.8236966e+08 | G20: =B!H328 -> 43668115 | H20: =B!I328 -> 97042105 | J20: =K20+L20+M20 -> 3.6645493e+08 | K20: =+B!L328 -> 3.3004831e+08 | L20: =+B!M328 -> 31535552 | M20: =+B!N328 -> 4871072.4 | O20: =P20+Q20+R20 -> 3.8950977e+08 | P20: 3.6847942e+08 | Q20: 29956769 | R20: -8926420.5
C21: Total recognized revenue and expenses for the period | E21: =SUM(E18:E20) -> 4.2307988e+08 | F21: =SUM(F18:F20) -> 2.8236966e+08 | G21: =SUM(G18:G20) -> 43668115 | H21: =SUM(H18:H20) -> 97042105 | J21: =SUM(J18:J20) -> 3.6645493e+08 | K21: =SUM(K18:K20) -> 3.3004831e+08 | L21: =SUM(L18:L20) -> 31535552 | M21: =SUM(M18:M20) -> 4871072.4 | O21: =SUM(O18:O20) -> 3.8950977e+08 | P21: 3.6847942e+08 | Q21: 29956769 | R21: -8926420.5
B22: Add (Deduct): Others | E22: =F22+G22+H22 -> 0 | F22: 0 | G22: 0 | H22: 0 | J22: =K22+L22+M22 -> 0 | K22: 0 | L22: 0 | M22: 0 | O22: =P22+Q22+R22 -> 0 | P22: 0 | Q22: 0 | R22: 0
D23: Transfer of Completed Infra. Projects/PPE to Registry | E23: =F23+G23+H23 -> 0 | J23: =K23+L23+M23 -> 0 | O23: =P23+Q23+R23 -> 0
D24: Transfer of Funds (from) / to Other Funds | E24: =F24+G24+H24 -> 0 | J24: =K24+L24+M24 -> 0 | O24: =P24+Q24+R24 -> 0
D25: Prior Period Adjustments | E25: =F25+G25+H25 -> 0 | J25: =K25+L25+M25 -> 0 | O25: =P25+Q25+R25 -> 0
D26: Other Adjustments | E26: =F26+G26+H26 -> 0 | J26: =K26+L26+M26 -> 0 | O26: =P26+Q26+R26 -> 0
B27: Balance at December 31 | E27: =E16+E21+E23+E24+E25+E26 -> 3.0270564e+09 | F27: =F16+F21+F23+F24+F25+F26 -> 2.7351325e+09 | G27: =G16+G21+G23+G24+G25+G26 -> 1.5957973e+08 | H27: =H16+H21+H23+H24+H25+H26 -> 1.3234422e+08 | J27: =J16+J21+J23+J24+J25+J26 -> 2.9496322e+09 | K27: =K16+K21+K23+K24+K25+K26 -> 2.616398e+09 | L27: =L16+L21+L23+L24+L25+L26 -> 2.9652596e+08 | M27: =M16+M21+M23+M24+M25+M26 -> 36708289 | O27: =O16+O21+O23+O24+O25+O26 -> 2.7744008e+09 | P27: 2.4647606e+09 | Q27: 2.7664128e+08 | R27: 32998941
A29: PER FINANCIAL PERFORMANCE (Surplus/(Deficit) | J29: =K29+L29+M29 -> 3.6645493e+08 | K29: =B!L328 -> 3.3004831e+08 | L29: =B!M328 -> 31535552 | M29: =B!N328 -> 4871072.4 | O29: =P29+Q29+R29 -> 3.8950977e+08 | P29: =B!Q328 -> 3.6847942e+08 | Q29: =B!R328 -> 29956769 | R29: =B!S328 -> -8926420.5
A30: DIFFERENCE | J30: =K30+L30+M30 -> 0 | K30: =SUM(K20-K29) -> 0 | L30: =SUM(L20-L29) -> 0 | M30: =SUM(M20-M29) -> 0 | O30: =P30+Q30+R30 -> 2.3469329e-07 | P30: =SUM(P20-P29) -> 2.3841858e-07 | Q30: =SUM(Q20-Q29) -> -3.7252903e-09 | R30: =SUM(R20-R29) -> 0
A32: PER FINANCIAL POSITIONS (Net Asset/Equity) | J32: =K32+L32+M32 -> 2.9496322e+09 | K32: =A!L545 -> 2.616398e+09 | L32: =A!M545 -> 2.9652596e+08 | M32: =A!N545 -> 36708289 | O32: =P32+Q32+R32 -> 2.7744008e+09 | P32: =A!Q545 -> 2.4647606e+09 | Q32: =A!R545 -> 2.7664128e+08 | R32: =A!S545 -> 32998941
A33: DIFFERENCE | J33: =K33+L33+M33 -> 0 | K33: =SUM(K27-K32) -> 0 | L33: =SUM(L27-L32) -> 0 | M33: =SUM(M27-M32) -> 0 | O33: =P33+Q33+R33 -> 0 | P33: =SUM(P27-P32) -> 0 | Q33: =SUM(Q27-Q32) -> 0 | R33: =SUM(R27-R32) -> 0

Sheet D
A1: City Government of Panabo
A2: CONSOLIDATED STATEMENT OF CASH FLOWS (BY FUND)
A3: For the Year Ended December 31, 2021
A4: (With Comparative figures in 2020)
A5: (In Philippine Peso)
A7: PARTICULARS | F7: 2021 | K7: 2020 | P7: 2019
F8: TOTAL | G8: GF | H8: SEF | I8: TF | K8: TOTAL | L8: GF | M8: SEF | N8: TF | P8: TOTAL | Q8: GF | R8: SEF | S8: TF
A9: Cash Flow from Operating Activities
B10: Cash Inflows
C11: Collection from taxpayers | F11: =G11+H11+I11 -> 2.9727308e+08 | G11: 2.3382968e+08 | H11: 63443403 | I11: 0 | K11: =L11+M11+N11 -> 2.8823036e+08 | L11: 2.2968414e+08 | M11: 58546218 | N11: 0 | P11: =Q11+R11+S11 -> 2.8880623e+08 | Q11: 2.272369e+08 | R11: 61569328 | S11: 0
C12: Share from Internal Revenue Allotment | F12: =G12+H12+I12 -> 889216030 | G12: 889216030 | H12: 0 | I12: 0 | K12: =L12+M12+N12 -> 6.6373796e+08 | L12: 6.6373796e+08 | M12: 0 | N12: 0 | P12: =Q12+R12+S12 -> 6.628859e+08 | Q12: 6.628859e+08 | R12: 0 | S12: 0
C13: Receipts from business/service income | F13: =G13+H13+I13 -> 1.0571275e+08 | G13: 1.0571275e+08 | H13: 0 | I13: 0 | K13: =L13+M13+N13 -> 1.1585381e+08 | L13: 1.1585381e+08 | M13: 0 | N13: 0 | P13: =Q13+R13+S13 -> 1.4601479e+08 | Q13: 1.4601479e+08 | R13: 0 | S13: 0
C14: Interest Income | F14: =G14+H14+I14 -> 385197.82 | G14: 349917.16 | H14: 35280.66 | I14: 0 | K14: =L14+M14+N14 -> 2641158.5 | L14: 2578718.4 | M14: 62440.02 | N14: 0 | P14: =Q14+R14+S14 -> 1296924 | Q14: 1233224 | R14: 63699.97 | S14: 0
C15: Other Receipts | F15: =G15+H15+I15 -> 1.2311718e+09 | G15: 7.4069827e+08 | H15: 1339435.2 | I15: 4.8913407e+08 | K15: =L15+M15+N15 -> 9.4958274e+08 | L15: 6.4122837e+08 | M15: 283663.95 | N15: 3.0807071e+08 | P15: =Q15+R15+S15 -> 3.5907348e+08 | Q15: 3.1838397e+08 | R15: 4544077.9 | S15: 36145439
B16: Total Cash Inflows | F16: =G16+H16+I16 -> 2.5237588e+09 | G16: =SUM(G11:G15) -> 1.9698066e+09 | H16: =SUM(H11:H15) -> 64818119 | I16: =SUM(I11:I15) -> 4.8913407e+08 | K16: =L16+M16+N16 -> 2.020046e+09 | L16: =SUM(L11:L15) -> 1.653083e+09 | M16: =SUM(M11:M15) -> 58892322 | N16: =SUM(N11:N15) -> 3.0807071e+08 | P16: =Q16+R16+S16 -> 1.4580773e+09 | Q16: 1.3557548e+09 | R16: 66177106 | S16: 36145439
B17: Cash OutFlows
C18: Payments of expenses | F18: =G18+H18+I18 -> 3.3530866e+08 | G18: 3.1948847e+08 | H18: 11339962 | I18: 4480229.1 | K18: =L18+M18+N18 -> 4.6311603e+08 | L18: 2.8412163e+08 | M18: 8271822.5 | N18: 1.7072258e+08 | P18: =Q18+R18+S18 -> 3.1166237e+08 | Q18: 2.9964603e+08 | R18: 10012852 | S18: 2003488.6
C19: Payment to suppliers and creditors | F19: =G19+H19+I19 -> 1.8193685e+08 | G19: 1.5999827e+08 | H19: 8656964.6 | I19: 13281610 | K19: =L19+M19+N19 -> 1.9567671e+08 | L19: 1.7764442e+08 | M19: 9258431.6 | N19: 8773858.2 | P19: =Q19+R19+S19 -> 82428377 | Q19: 72626546 | R19: 8002196 | S19: 1799634.1
C20: Payment to employees | F20: =G20+H20+I20 -> 2.581936e+08 | G20: 2.581936e+08 | H20: 0 | I20: 0 | K20: =L20+M20+N20 -> 2.6055775e+08 | L20: 2.6025207e+08 | M20: 0 | N20: 305675.97 | P20: =Q20+R20+S20 -> 2.1147304e+08 | Q20: 2.1147304e+08 | R20: 0 | S20: 0
C21: Interest Expense | F21: =G21+H21+I21 -> 10419963 | G21: 10419963 | H21: 0 | I21: 0 | K21: =L21+M21+N21 -> 11780899 | L21: 11780899 | M21: 0 | N21: 0 | P21: =Q21+R21+S21 -> 11009435 | Q21: 10907855 | R21: 101579.81 | S21: 0
C22: Other Expenses | F22: =G22+H22+I22 -> 9.816656e+08 | G22: 9.2922932e+08 | H22: 11535297 | I22: 40900978 | K22: =L22+M22+N22 -> 6.8148464e+08 | L22: 6.4295289e+08 | M22: 6954738.7 | N22: 31577006 | P22: =Q22+R22+S22 -> 4.7248982e+08 | Q22: 4.5184384e+08 | R22: 9296907.4 | S22: 11349068
B23: Total Cash Outflows | F23: =G23+H23+I23 -> 1.7675247e+09 | G23: =SUM(G18:G22) -> 1.6773296e+09 | H23: =SUM(H18:H22) -> 31532224 | I23: =SUM(I18:I22) -> 58662817 | K23: =L23+M23+N23 -> 1.612616e+09 | L23: =SUM(L18:L22) -> 1.3767519e+09 | M23: =SUM(M18:M22) -> 24484993 | N23: =SUM(N18:N22) -> 2.1137912e+08 | P23: =Q23+R23+S23 -> 1.089063e+09 | Q23: 1.0464973e+09 | R23: 27413535 | S23: 15152191
A24: Net Cash Flows from Operating Activities | F24: =G24+H24+I24 -> 7.5623416e+08 | G24: =G16-G23 -> 2.9247702e+08 | H24: =H16-H23 -> 33285895 | I24: =I16-I23 -> 4.3047125e+08 | K24: =L24+M24+N24 -> 4.0743001e+08 | L24: =L16-L23 -> 2.763311e+08 | M24: =M16-M23 -> 34407329 | N24: =N16-N23 -> 96691584 | P24: =Q24+R24+S24 -> 3.6901428e+08 | Q24: 3.0925746e+08 | R24: 38763571 | S24: 20993248
A25: Cash Flow from Investing Activities
B26: Cash Inflows
C27: Proceeds from Sale of PPE | F27: =G27+H27+I27 -> 0 | G27: 0 | H27: 0 | I27: 0 | K27: =L27+M27+N27 -> 0 | L27: 0 | M27: 0 | N27: 0 | P27: =Q27+R27+S27 -> 10280.05 | Q27: 10280.05 | R27: 0 | S27: 0
B28: Total Cash Inflows | F28: =G28+H28+I28 -> 0 | G28: 0 | H28: 0 | I28: 0 | K28: =L28+M28+N28 -> 0 | L28: 0 | M28: 0 | N28: 0 | P28: =Q28+R28+S28 -> 10280.05 | Q28: 10280.05 | R28: 0 | S28: 0
B29: Cash OutFlows
C30: Purchase/Construction of Property, Plant and Equipment | F30: =G30+H30+I30 -> 5.3812719e+08 | G30: 4.087661e+08 | H30: 31337980 | I30: 98023106 | K30: =L30+M30+N30 -> 2.5541602e+08 | L30: 2.2989347e+08 | M30: 11311922 | N30: 14210634 | P30: =Q30+R30+S30 -> 2.8469323e+08 | Q30: 2.2671978e+08 | R30: 37267027 | S30: 20706419
B31: Total Cash Outflows | F31: =G31+H31+I31 -> 5.3812719e+08 | G31: =G30 -> 4.087661e+08 | H31: =H30 -> 31337980 | I31: =I30 -> 98023106 | K31: =L31+M31+N31 -> 2.5541602e+08 | L31: =L30 -> 2.2989347e+08 | M31: =M30 -> 11311922 | N31: =N30 -> 14210634 | P31: =Q31+R31+S31 -> 2.8469323e+08 | Q31: 2.2671978e+08 | R31: 37267027 | S31: 20706419
A32: Net Cash Flows from Investing Activities | F32: =G32+H32+I32 -> -5.3812719e+08 | G32: =-G31 -> -4.087661e+08 | H32: =-H31 -> -31337980 | I32: =-I31 -> -98023106 | K32: =L32+M32+N32 -> -2.5541602e+08 | L32: =-L31 -> -2.2989347e+08 | M32: =-M31 -> -11311922 | N32: =-N31 -> -14210634 | P32: =Q32+R32+S32 -> -2.8468295e+08 | Q32: -2.267095e+08 | R32: -37267027 | S32: -20706419
A33: Cash Flow from Financing Activities
B34: Cash Inflows
C35: Proceeds from Issuance of Bills and Bonds | F35: =G35+H35+I35 -> 0 | K35: =L35+M35+N35 -> 0 | P35: =Q35+R35+S35 -> 0
C36: Proceeds from Domestic and Foreign Loans | F36: =G36+H36+I36 -> 9564783 | G36: 9564783 | H36: 0 | I36: 0 | K36: =L36+M36+N36 -> 1.0993888e+08 | L36: 1.0993888e+08 | M36: 0 | N36: 0 | P36: =Q36+R36+S36 -> 94028150 | Q36: 94028150 | R36: 0 | S36: 0
B37: Total Cash Inflows | F37: =G37+H37+I37 -> 9564783 | G37: =SUM(G35:G36) -> 9564783 | H37: =SUM(H35:H36) -> 0 | I37: =SUM(I35:I36) -> 0 | K37: =L37+M37+N37 -> 1.0993888e+08 | L37: =SUM(L35:L36) -> 1.0993888e+08 | M37: =SUM(M35:M36) -> 0 | N37: =SUM(N35:N36) -> 0 | P37: =Q37+R37+S37 -> 94028150 | Q37: 94028150 | R37: 0 | S37: 0
B38: Cash OutFlows
C39: Payment of Long-Term Liabilities | F39: =G39+H39+I39 -> 26694021 | G39: 26694021 | H39: 0 | I39: 0 | K39: =L39+M39+N39 -> 27389241 | L39: 27389241 | M39: 0 | N39: 0 | P39: =Q39+R39+S39 -> 28330579 | Q39: 26709270 | R39: 1621309.1 | S39: 0
C40: Retirement/Redemption of debt securities | F40: =G40+H40+I40 -> 0 | K40: =L40+M40+N40 -> 0 | P40: =Q40+R40+S40 -> 0
C41: Payment of loan amortization | F41: =G41+H41+I41 -> 0 | K41: =L41+M41+N41 -> 0 | P41: =Q41+R41+S41 -> 0
B42: Total Cash Outflows | F42: =G42+H42+I42 -> 26694021 | G42: =SUM(G39:G41) -> 26694021 | H42: =SUM(H39:H41) -> 0 | I42: =SUM(I39:I41) -> 0 | K42: =L42+M42+N42 -> 27389241 | L42: =SUM(L39:L41) -> 27389241 | M42: =SUM(M39:M41) -> 0 | N42: =SUM(N39:N41) -> 0 | P42: =Q42+R42+S42 -> 28330579 | Q42: 26709270 | R42: 1621309.1 | S42: 0
A43: Net Cash Flows from Financing Activities | F43: =G43+H43+I43 -> -17129238 | G43: =G37-G42 -> -17129238 | H43: =H37-H42 -> 0 | I43: =I37-I42 -> 0 | K43: =L43+M43+N43 -> 82549636 | L43: =L37-L42 -> 82549636 | M43: =M37-M42 -> 0 | N43: =N37-N42 -> 0 | P43: =Q43+R43+S43 -> 65697571 | Q43: 67318880 | R43: -1621309.1 | S43: 0
A44: Total Cash Provided by Operating, Investing and Financing Activities | F44: =G44+H44+I44 -> 2.0097774e+08 | G44: =G24+G32+G43 -> -1.3341832e+08 | H44: =H24+H32+H43 -> 1947914.9 | I44: =I24+I32+I43 -> 3.3244814e+08 | K44: =L44+M44+N44 -> 2.3456362e+08 | L44: =L24+L32+L43 -> 1.2898727e+08 | M44: =M24+M32+M43 -> 23095407 | N44: =N24+N32+N43 -> 82480950 | P44: =Q44+R44+S44 -> 1.500289e+08 | Q44: 1.4986684e+08 | R44: -124764.98 | S44: 286828.89
A45: Add : Cash at the Beginning of the year | F45: =G45+H45+I45 -> 1.1541891e+09 | G45: =L47 -> 9.1195295e+08 | H45: =M47 -> 79320576 | I45: =N47 -> 1.6291561e+08 | K45: =L45+M45+N45 -> 9.1946492e+08 | L45: 7.8280515e+08 | M45: 56225113 | N45: 80434664 | P45: =Q45+R45+S45 -> 7.6943602e+08 | Q45: 6.3293831e+08 | R45: 56349878 | S45: 80147835
A46: Adjustment to cash balance prior year | F46: =G46+H46+I46 -> -85620.82 | G46: -72818 | H46: -12802.82 | I46: 0 | K46: =L46+M46+N46 -> 160596.45 | L46: 160540.95 | M46: 55.5 | N46: 0 | P46: =Q46+R46+S46 -> 0 | Q46: 0 | R46: 0 | S46: 0
A47: Cash Balance Ending, December 31 | F47: =G47+H47+I47 -> 1.3550813e+09 | G47: =G45+G44+G46 -> 7.7846181e+08 | H47: =H45+H44+H46 -> 81255688 | I47: =I45+I44 -> 4.9536376e+08 | K47: =L47+M47+N47 -> 1.1541891e+09 | L47: =L45+L44+L46 -> 9.1195295e+08 | M47: =M45+M44+M46 -> 79320576 | N47: =N45+N44 -> 1.6291561e+08 | P47: =Q47+R47+S47 -> 9.1946492e+08 | Q47: =Q45+Q44+Q46 -> 7.8280515e+08 | R47: =R45+R44+R46 -> 56225113 | S47: =S45+S44+S46 -> 80434664
A48: from Statement of Financial Position | K48: =SUM(L48:N48) -> 6.180785e+08 | L48: =+'[3]FPOS-'!G23 -> 4.8977024e+08 | M48: ='[3]FPOS-'!H23 -> 53854360 | N48: ='[3]FPOS-'!I23 -> 74453898 | P48: =SUM(Q48:S48) -> 5.311779e+08 | Q48: ='[3]FPOS-'!L23 -> 3.821049e+08 | R48: ='[3]FPOS-'!M23 -> 59007197 | S48: ='[3]FPOS-'!N23 -> 90065802
A49: discrepancies | K49: =K47-K48 -> 5.3611064e+08 | L49: =L47-L48 -> 4.2218271e+08 | M49: =M47-M48 -> 25466216 | N49: =N47-N48 -> 88461716 | P49: =P47-P48 -> 3.8828703e+08 | Q49: =Q47-Q48 -> 4.0070025e+08 | R49: =R47-R48 -> -2782083.7 | S49: =S47-S48 -> -9631138.4
A50: AS SUBMITTED | K50: =SUM(L50:N50) -> 6.180785e+08 | L50: 4.8977024e+08 | M50: 53854360 | N50: 74453898 | P50: =SUM(Q50:S50) -> 0
A51: DIFFERENCE | K51: =K47-K50 -> 5.3611064e+08 | L51: =L47-L50 -> 4.2218271e+08 | M51: =M47-M50 -> 25466216 | N51: =N47-N50 -> 88461716 | P51: =P47-P50 -> 9.1946492e+08 | Q51: =Q47-Q50 -> 7.8280515e+08 | R51: =R47-R50 -> 56225113 | S51: =S47-S50 -> 80434664
A55: PARTICULARS
B57: Cash Flow from Operating Activities
B58: Cash Flow from Investing Activities
B59: Cash Flow from Financing Activities
B60: Net Cash Provided by (Used in)
B61: Cash Balance Beginning
B62: Cash Balance Ending
A65: Notes to Cash Flow Statement
A67: a) Cash and Cash Equivalent
E69: Cash and cash equivalents consist of cash on hand, balances with banks, and investment in money market instruments. Cash and cash equivalents included in the cash flow statement comprise the following statement of financial position amounts:
E71: (absolute amount)
A72: PARTICULARS
E75: Cash on hand and balances with banks
E76: Cash Equivalents
E77: TOTAL Cash and Cash Equivalent
A79: b) Reconciliation of Net Cash Flows from Operating Activities to Surplus/(Deficit)
E81: (absolute amount)
E82: Surplus/(Deficit)
E83: Non-cash transactions
E84: Depreciation
E85: Amortization
E86: Increase in payables
E87: Increase in provisions relating to employee cost
E88: Increase in other current assets
E89: Increase in investments due to revaluation
E90: Increase in receivables
E91: Grants in Kind
E92: Loss on Sale of PPE
... E96: Net Cash from Operating Activities
B103: Cash at the End of the Period
E105: Bal vs Cash on Hand per SFPo | K105: =K47-A!K25 -> 0 | L105: =L47-A!L25 -> 0 | M105: =M47-A!M25 -> 0 | N105: =N47-A!N25 -> 0 | P105: =P47-A!P25 -> 0 | Q105: =A!Q25-D!Q47 -> 0 | R105: =R47-A!R25 -> 0 | S105: =S47-A!S25 -> 0
G106: =A!G25 -> 7.7846181e+08 | H106: =A!H25 -> 81255688 | I106: =A!I25 -> 4.9536376e+08
G109: =G47-G106 -> 0.0020000935 | H109: =H47-H106 -> 0 | I109: =I47-I106 -> 0

Sheet E
A1: CITY GOVERNMENT OF PANABO
A2: Statement of Comparison of Budget and Actual Amounts
A3: For the Year Ended December 31, 2021
A4: (With Comparative figures in 2020)
A5: (In Philippine Peso)
A7: Particulars | F7: Notes | G7: 2021 | R7: 2020 | AA7: 2019
H8: Budgeted | K8: Difference | P8: Difference | R8: Budgeted | U8: Difference | Z8: Difference | AA8: Budgeted | AE8: Difference | AJ8: Difference
H9: Amounts | K9: Original and | N9: Actual | P9: Final Budget | R9: Amounts | U9: Original and | X9: Actual | Z9: Final Budget | AA9: Amounts | AE9: Original and | AH9: Actual | AJ9: Final Budget
H10: Original | J10: Final | K10: Final Budget | N10: Amounts | P10: and Actual | R10: Original | T10: Final | U10: Final Budget | X10: Amounts | Z10: and Actual | AB10: Original | AD10: Final | AE10: Final Budget | AH10: Amounts | AJ10: and Actual
A12: General Fund
A13: Revenue
B14: A. Local Sources
C15: 1. Tax Revenue
D16: a. Tax Revenue - Property | H16: 48300000 | J16: 48300000 | L16: =H16-J16 -> 0 | N16: 40423521 | P16: =J16-N16 -> 7876479.3 | R16: 40500000 | T16: 40500000 | V16: =R16-T16 -> 0 | X16: 31653941 | Z16: =T16-X16 -> 8846058.8 | AB16: 36000000 | AD16: 36000000 | AF16: =AB16-AD16 -> 0 | AH16: 37314897 | AJ16: =AD16-AH16 -> -1314896.7
D17: b. Tax Revenue - Goods and Services | H17: 154170000 | J17: 154170000 | L17: =H17-J17 -> 0 | N17: 1.7229295e+08 | P17: =J17-N17 -> -18122948 | R17: 146850000 | T17: 146850000 | V17: =R17-T17 -> 0 | X17: 1.7425452e+08 | Z17: =T17-X17 -> -27404524 | AB17: 138668000 | AD17: 138668000 | AF17: =AB17-AD17 -> 0 | AH17: 1.6515343e+08 | AJ17: =AD17-AH17 -> -26485428
D18: c. Other Local Taxes | H18: 9770000 | J18: 9770000 | L18: =H18-J18 -> 0 | N18: 13436740 | P18: =J18-N18 -> -3666739.5 | R18: 2200000 | T18: 2200000 | V18: =R18-T18 -> 0 | X18: 12455043 | Z18: =T18-X18 -> -10255043 | AB18: 5200000 | AD18: 5200000 | AF18: =AB18-AD18 -> 0 | AH18: 13204978 | AJ18: =AD18-AH18 -> -8004978.5
C19: Total Tax Revenue | H19: =SUM(H16:H18) -> 212240000 | J19: =SUM(J16:J18) -> 212240000 | L19: =SUM(L16:L18) -> 0 | N19: =SUM(N16:N18) -> 2.2615321e+08 | P19: =SUM(P16:P18) -> -13913208 | R19: =SUM(R16:R18) -> 189550000 | T19: =SUM(T16:T18) -> 189550000 | V19: =SUM(V16:V18) -> 0 | X19: =SUM(X16:X18) -> 2.1836351e+08 | Z19: =SUM(Z16:Z18) -> -28813508 | AB19: =SUM(AB16:AB18) -> 179868000 | AD19: =SUM(AD16:AD18) -> 179868000 | AF19: =SUM(AF16:AF18) -> 0 | AH19: =SUM(AH16:AH18) -> 2.156733e+08 | AJ19: =SUM(AJ16:AJ18) -> -35805303
C20: 2. Non-Tax Revenue
D21: a. Service Income | H21: 54570000 | J21: 54570000 | L21: =H21-J21 -> 0 | N21: 51945013 | P21: =J21-N21 -> 2624987.3 | R21: 53991350 | T21: 53991350 | V21: =R21-T21 -> 0 | X21: 47059884 | Z21: =T21-X21 -> 6931465.8 | AB21: 42342950 | AD21: 43089070 | AF21: =AB21-AD21 -> -746120.15 | AH21: 53617271 | AJ21: =AD21-AH21 -> -10528201
D22: b. Business Income | H22: 97051835 | J22: 97051835 | L22: =H22-J22 -> 0 | N22: 90091676 | P22: =J22-N22 -> 6960159.3 | R22: 81149298 | T22: 86897710 | V22: =R22-T22 -> -5748411.7 | X22: 70689542 | Z22: =T22-X22 -> 16208167 | AB22: 80379756 | AD22: 83715756 | AF22: =AB22-AD22 -> -3336000 | AH22: 94104604 | AJ22: =AD22-AH22 -> -10388848
D23: c. Other Income and Receipts | H23: 4.6198823e+08 | J23: 5.8996691e+08 | L23: =H23-J23 -> -1.2797868e+08 | N23: 3.8883641e+08 | P23: =J23-N23 -> 2.011305e+08 | R23: 7300000 | T23: 4.1548309e+08 | V23: =R23-T23 -> -4.0818309e+08 | X23: 625391.86 | Z23: =T23-X23 -> 4.148577e+08 | AB23: 1110000 | AD23: 2.4468154e+08 | AF23: =AB23-AD23 -> -2.4357154e+08 | AH23: 3751280.3 | AJ23: =AD23-AH23 -> 2.4093026e+08
C24: Total Non-Tax Revenue | H24: =SUM(H21:H23) -> 6.1361007e+08 | J24: =SUM(J21:J23) -> 7.4158874e+08 | L24: =SUM(L21:L23) -> -1.2797868e+08 | N24: =SUM(N21:N23) -> 5.308731e+08 | P24: =SUM(P21:P23) -> 2.1071565e+08 | R24: =SUM(R21:R23) -> 1.4244065e+08 | T24: =SUM(T21:T23) -> 5.5637215e+08 | V24: =SUM(V21:V23) -> -4.1393151e+08 | X24: =SUM(X21:X23) -> 1.1837482e+08 | Z24: =SUM(Z21:Z23) -> 4.3799734e+08 | AB24: =SUM(AB21:AB23) -> 1.2383271e+08 | AD24: =SUM(AD21:AD23) -> 3.7148637e+08 | AF24: =SUM(AF21:AF23) -> -2.4765366e+08 | AH24: =SUM(AH21:AH23) -> 151473155 | AJ24: =SUM(AJ21:AJ23) -> 2.2001321e+08
B25: B. External Sources
C26: 1. Share from the National Internal Revenue Taxes (IRA) | H26: 829672451 | J26: 889216030 | L26: =H26-J26 -> -59543579 | N26: 889216030 | P26: =J26-N26 -> 0 | R26: 734827207 | T26: 829672451 | V26: =R26-T26 -> -94845244 | X26: 829672451 | Z26: =T26-X26 -> 0 | AB26: 734827207 | AD26: 739212765 | AF26: =AB26-AD26 -> -4385558 | AH26: 7.3921276e+08 | AJ26: =AD26-AH26 -> 0
C27: 2. Share from GOCCs | AF27: =AB27-AD27 -> 0 | AJ27: =AD27-AH27 -> 0
D28: a. Share from Ecozone | E28: Share from PCSO | H28: 700000 | J28: 700000 | L28: =H28-J28 -> 0 | N28: 1192785.3 | P28: =J28-N28 -> -492785.32 | R28: 650000 | V28: =R28-T28 -> 650000 | X28: 218580.68 | Z28: =T28-X28 -> -218580.68 | AB28: 450000 | AD28: 450000 | AF28: =AB28-AD28 -> 0 | AH28: 637969.8 | AJ28: =AD28-AH28 -> -187969.8
C29: 3. Other Shares from National Tax Collections | AF29: =AB29-AD29 -> 0 | AH29: =AH30 -> 131334.6 | AJ29: =AD29-AH29 -> -131334.6
D30: a. Share from Ecozone | L30: 0 | N30: 72609 | P30: =J30-N30 -> -72609 | V30: 0 | X30: 588344.53 | Z30: =T30-X30 -> -588344.53 | AF30: =AB30-AD30 -> 0 | AH30: 131334.6 | AJ30: =AD30-AH30 -> -131334.6
D31: b. Share from EVAT | L31: 0 | P31: 0 | V31: 0 | X31: 0 | Z31: 0 | AF31: =AB31-AD31 -> 0 | AJ31: =AD31-AH31 -> 0
D32: c. Share from National Wealth | L32: 0 | P32: =J32-N32 -> 0 | V32: 0 | X32: 131344.5 | Z32: =T32-X32 -> -131344.5 | AF32: =AB32-AD32 -> 0 | AJ32: =AD32-AH32 -> 0
D33: d. Share from Tobacco Excise Tax | L33: 0 | P33: 0 | V33: 0 | X33: 0 | Z33: 0 | AF33: =AB33-AD33 -> 0 | AJ33: =AD33-AH33 -> 0
C34: 4. Other Receipts | AF34: =AB34-AD34 -> 0 | AJ34: =AD34-AH34 -> 0
D35: a. Grants and Donations | H35: 0 | J35: 0 | L35: =H35-J35 -> 0 | P35: =J35-N35 -> 0 | T35: 69139371 | V35: =R35-T35 -> -69139371 | X35: 69139371 | Z35: =T35-X35 -> 0 | AF35: =AB35-AD35 -> 0 | AJ35: =AD35-AH35 -> 0
D36: b. Other Subsidy Income | H36: 0 | J36: 15122372 | L36: =H36-J36 -> -15122372 | N36: 15122372 | P36: =J36-N36 -> 0 | R36: 3936955.6 | T36: 5111182.1 | V36: =R36-T36 -> -1174226.5 | X36: 9681863.8 | Z36: =T36-X36 -> -4570681.7 | AF36: =AB36-AD36 -> 0 | AJ36: =AD36-AH36 -> 0
C37: 5. Inter-local Transfer | L37: 0 | P37: =J37-N37 -> 0 | V37: 0 | X37: 0 | Z37: =T37-X37 -> 0 | AD37: 11696870 | AF37: =AB37-AD37 -> -11696870 | AH37: 12932884 | AJ37: =AD37-AH37 -> -1236013.8
C38: 6. Capital /Investment Receipts | P38: 0 | Z38: 0 | AF38: =AB38-AD38 -> 0 | AJ38: =AD38-AH38 -> 0
D39: a. Sale of Capital Assets | H39: 0 | J39: 0 | L39: 0 | P39: 0 | R39: 0 | T39: 0 | V39: 0 | X39: 0 | Z39: 0 | AF39: =AB39-AD39 -> 0 | AJ39: =AD39-AH39 -> 0
D40: b. Sale of Investments | H40: 0 | J40: 0 | L40: 0 | P40: 0 | R40: 0 | T40: 0 | V40: 0 | X40: 0 | Z40: 0 | AF40: =AB40-AD40 -> 0 | AJ40: =AD40-AH40 -> 0
D41: c. Proceeds from Collections of Loan Receivable | H41: 0 | L41: 0 | N41: 549735 | P41: 0 | R41: 0 | V41: 0 | X41: 0 | Z41: 0 | AF41: =AB41-AD41 -> 0 | AJ41: =AD41-AH41 -> 0
B42: C. Receipts from Borrowings | J42: 600000000 | L42: 0 | N42: 9564783 | P42: =J42-N42 -> 590435217 | V42: 0 | X42: 1.0993888e+08 | Z42: =T42-X42 -> -1.0993888e+08 | AF42: =AB42-AD42 -> 0 | AH42: 94028150 | AJ42: =AD42-AH42 -> -94028150
A43: Total Revenue and Receipts | H43: =H28+H26+H24+H19+H36 -> 1.6562225e+09 | J43: =J36+J35+J26+J24+J19 -> 1.8581671e+09 | L43: =L36+L26+L24+L28+L35 -> -2.0264463e+08 | N43: =N42+N37+N29+N28+N26+N24+N191+N19+N35+N36+N32+N30 -> 1.6721949e+09 | O43: =O42+O37+O30+O28+O26+O24+O191+O19 -> 0 | P43: =P19+P24+P28+P29+P37+P42+P36+P32+P30 -> 7.8667226e+08 | R43: =R28+R26+R24+R19+R36 -> 1.0714048e+09 | T43: =T36+T35+T26+T24+T19 -> 1.6498452e+09 | V43: =V36+V26+V24+V28+V35 -> -5.7844035e+08 | X43: =X42+X37+X29+X28+X26+X24+X191+X19+X35+X36+X32+X30 -> 1.3561092e+09 | Y43: =Y42+Y37+Y30+Y28+Y26+Y24+Y191+Y19 -> 0 | Z43: =Z19+Z24+Z28+Z29+Z37+Z42+Z36+Z32+Z30 -> 2.93736e+08 | AB43: =AB19+AB24+AB26+AB28+AB27+AB34+AB37+AB38+AB42 -> 1.0389779e+09 | AD43: =AD19+AD24+AD26+AD27+AD28+AD34+AD37+AD38+AD42 -> 1.302714e+09 | AF43: =AF19+AF24+AF26+AF27+AF29+AF34+AF37+AF38+AF42 -> -2.6373609e+08 | AH43: =AH19+AH24+AH26+AH27+AH29+AH28+AH37+AH42 -> 1.2140896e+09 | AJ43: =AJ19+AJ24+AJ26+AJ27+AJ29+AJ34+AJ37+AJ38+AJ42+AJ28 -> 88624439
A44: Funded Continuing Appropriations | L44: =H44-J44 -> 0 | P44: =J44-N44 -> 0 | R44: 5.6815452e+08 | T44: 4.3209207e+08 | V44: =R44-T44 -> 1.3606245e+08 | X44: 4.3209207e+08 | Z44: =T44-X44 -> 0 | AB44: 4.7911828e+08 | AD44: 4.7911828e+08 | AF44: 0 | AH44: 4.7911828e+08 | AJ44: 0
A45: Grand Total Revenue and Receipts | H45: =H43+H44 -> 1.6562225e+09 | J45: =J43+J44 -> 1.8581671e+09 | L45: =L43+L44 -> -2.0264463e+08 | N45: =N43+N44 -> 1.6721949e+09 | P45: =P43+P44 -> 7.8667226e+08 | R45: =R43+R44 -> 1.6395593e+09 | T45: =T43+T44 -> 2.0819372e+09 | V45: =V43+V44 -> -4.423779e+08 | X45: =X43+X44 -> 1.7882012e+09 | Z45: =Z43+Z44 -> 2.93736e+08 | AB45: =AB43+AB44 -> 1.5180962e+09 | AD45: =AD43+AD44 -> 1.7818323e+09 | AF45: =AF43+AF44 -> -2.6373609e+08 | AH45: =AH43+AH44 -> 1.6932078e+09 | AJ45: =AJ43+AJ44 -> 88624439
A46: Expenditures
A47: Current Aprropriations
B48: General Public Services
C49: Personnel Services | H49: 2.7485241e+08 | J49: 271983899 | L49: =H49-J49 -> 2868506.2 | N49: 2.3924396e+08 | P49: =J49-N49 -> 32739943 | R49: 2.451575e+08 | T49: 2.4223926e+08 | V49: =R49-T49 -> 2918235.7 | X49: 2.0464e+08 | Z49: =T49-X49 -> 37599258 | AB49: 2.0773873e+08 | AD49: 2.2316041e+08 | AF49: =AB49-AD49 -> -15421687 | AH49: 1.970391e+08 | AJ49: =AD49-AH49 -> 26121316
C50: Maintenance and Other Operating Expenses | H50: 2.4471711e+08 | J50: 2.5431194e+08 | L50: =H50-J50 -> -9594833.2 | N50: 2.3421127e+08 | P50: =J50-N50 -> 20100672 | R50: 2.1507765e+08 | T50: 2.7708765e+08 | V50: =R50-T50 -> -62009993 | X50: 2.656119e+08 | Z50: =T50-X50 -> 11475745 | AB50: 1.7531849e+08 | AD50: 2.0883649e+08 | AF50: =AB50-AD50 -> -33518005 | AH50: 1.9374127e+08 | AJ50: =AD50-AH50 -> 15095221
C51: Capital Outlay | H51: 9446000 | J51: 76131000 | L51: =H51-J51 -> -66685000 | N51: 14473179 | P51: =J51-N51 -> 61657821 | R51: 2273000 | T51: 59216215 | V51: =R51-T51 -> -56943215 | X51: 13340459 | Z51: =T51-X51 -> 45875756 | AB51: 11207420 | AD51: 18734583 | AF51: =AB51-AD51 -> -7527162.6 | AH51: 12427985 | AJ51: =AD51-AH51 -> 6306598
B52: Education | AF52: =AB52-AD52 -> 0
C53: Personnel Services | L53: =H53-J53 -> 0 | P53: =J53-N53 -> 0 | V53: =R53-T53 -> 0 | Z53: =T53-X53 -> 0 | AF53: =AB53-AD53 -> 0 | AJ53: =AD53-AH53 -> 0
C54: Maintenance and Other Operating Expenses | L54: =H54-J54 -> 0 | P54: =J54-N54 -> 0 | V54: =R54-T54 -> 0 | Z54: =T54-X54 -> 0 | AF54: =AB54-AD54 -> 0 | AJ54: =AD54-AH54 -> 0
C55: Capital Outlay | L55: =H55-J55 -> 0 | P55: =J55-N55 -> 0 | V55: =R55-T55 -> 0 | Z55: =T55-X55 -> 0 | AF55: =AB55-AD55 -> 0 | AJ55: =AD55-AH55 -> 0
B56: Health, Nutrition and Population Control
C57: Personnel Services | H57: 53662362 | J57: 54027770 | L57: =H57-J57 -> -365407.83 | N57: 47047732 | P57: =J57-N57 -> 6980037.8 | R57: 43730134 | T57: 46686094 | V57: =R57-T57 -> -2955959.9 | X57: 34965524 | Z57: =T57-X57 -> 11720570 | AB57: 37754767 | AD57: 33810312 | AF57: =AB57-AD57 -> 3944454.7 | AH57: 28736008 | AJ57: =AD57-AH57 -> 5074303.6
C58: Maintenance and Other Operating Expenses | H58: 29302211 | J58: 37744802 | L58: =H58-J58 -> -8442590.6 | N58: 25637293 | P58: =J58-N58 -> 12107509 | R58: 24615896 | T58: 28753183 | V58: =R58-T58 -> -4137286.4 | X58: 23186294 | Z58: =T58-X58 -> 5566888.3 | AB58: 17808064 | AD58: 19132987 | AF58: =AB58-AD58 -> -1324922.9 | AH58: 16571804 | AJ58: =AD58-AH58 -> 2561183.4
C59: Capital Outlay | H59: 864000 | J59: 864000 | L59: =H59-J59 -> 0 | N59: 776348 | P59: =J59-N59 -> 87652 | T59: 1162740 | V59: =R59-T59 -> -1162740 | X59: 348580 | Z59: =T59-X59 -> 814160 | AB59: 515000 | AD59: 998820.15 | AF59: =AB59-AD59 -> -483820.15 | AH59: 218261 | AJ59: =AD59-AH59 -> 780559.15
B60: Labor and Employment | AF60: =AB60-AD60 -> 0
C61: Personnel Services | AF61: =AB61-AD61 -> 0 | AJ61: =AD61-AH61 -> 0
C62: Maintenance and Other Operating Expenses | AF62: =AB62-AD62 -> 0 | AJ62: =AD62-AH62 -> 0
C63: Capital Outlay | AF63: =AB63-AD63 -> 0 | AJ63: =AD63-AH63 -> 0
B64: Housing and Community Development | AF64: =AB64-AD64 -> 0
C65: Personnel Services | AF65: =AB65-AD65 -> 0 | AJ65: =AD65-AH65 -> 0
C66: Maintenance and Other Operating Expenses | AF66: =AB66-AD66 -> 0 | AJ66: =AD66-AH66 -> 0
C67: Capital Outlay | AF67: =AB67-AD67 -> 0 | AJ67: =AD67-AH67 -> 0
B68: Social Services and Social Welfare | V68: =R68-T68 -> 0
C69: Personnel Services | H69: 16749566 | J69: 16485149 | L69: =H69-J69 -> 264416.52 | N69: 14109582 | P69: =J69-N69 -> 2375567.7 | R69: 14649639 | T69: 15461635 | V69: =R69-T69 -> -811996.04 | X69: 13904995 | Z69: =T69-X69 -> 1556639.9 | AB69: 17647422 | AD69: 11899037 | AF69: =AB69-AD69 -> 5748384.4 | AH69: 10696013 | AJ69: =AD69-AH69 -> 1203024.5
C70: Maintenance and Other Operating Expenses | H70: 26684076 | J70: 37924586 | L70: =H70-J70 -> -11240509 | N70: 35595276 | P70: =J70-N70 -> 2329309.8 | R70: 23181399 | T70: 25645116 | V70: =R70-T70 -> -2463717.3 | X70: 20549167 | Z70: =T70-X70 -> 5095949.4 | AB70: 45958546 | AD70: 25248425 | AF70: =AB70-AD70 -> 20710121 | AH70: 24243671 | AJ70: =AD70-AH70 -> 1004753.4
C71: Capital Outlay | H71: 120000 | J71: 2010000 | L71: =H71-J71 -> -1890000 | N71: 1788696.4 | P71: =J71-N71 -> 221303.6 | R71: 0 | T71: 330000 | V71: =R71-T71 -> -330000 | X71: 305947 | Z71: =T71-X71 -> 24053 | AB71: 170000 | AD71: 170000 | AF71: =AB71-AD71 -> 0 | AH71: 99100 | AJ71: =AD71-AH71 -> 70900
B72: Economic Services
C73: Personnel Services | H73: 78418085 | J73: 74912064 | L73: =H73-J73 -> 3506021.3 | N73: 62314376 | P73: =J73-N73 -> 12597688 | R73: 68278997 | T73: 68934196 | V73: =R73-T73 -> -655198.3 | X73: 57639326 | Z73: =T73-X73 -> 11294870 | AB73: 60487789 | AD73: 60708076 | AF73: =AB73-AD73 -> -220286.95 | AH73: 54838172 | AJ73: =AD73-AH73 -> 5869903.9
C74: Maintenance and Other Operating Expenses | H74: 1.4207639e+08 | J74: 1.5128018e+08 | L74: =H74-J74 -> -9203789 | N74: 1.190309e+08 | P74: =J74-N74 -> 32249281 | R74: 1.3527503e+08 | T74: 1.4475834e+08 | V74: =R74-T74 -> -9483308.3 | X74: 1.2643187e+08 | Z74: =T74-X74 -> 18326469 | AB74: 1.1288513e+08 | AD74: 1.2283509e+08 | AF74: =AB74-AD74 -> -9949967.8 | AH74: 1.1388694e+08 | AJ74: =AD74-AH74 -> 8948150.7
C75: Capital Outlay | H75: 164165000 | J75: 6.1886982e+08 | L75: =H75-J75 -> -4.5470482e+08 | N75: 55892241 | P75: =J75-N75 -> 5.6297758e+08 | R75: 11810000 | T75: 1.6774271e+08 | V75: =R75-T75 -> -1.5593271e+08 | X75: 21774689 | Z75: =T75-X75 -> 1.4596802e+08 | AB75: 45953000 | AD75: 137173000 | AF75: =AB75-AD75 -> -91220000 | AH75: 77448530 | AJ75: =AD75-AH75 -> 59724470
B76: Other Purposes:
C77: Debt Service
D78: Financial Expense | H78: 45965581 | J78: 49108874 | L78: =H78-J78 -> -3143293.5 | N78: 10687840 | P78: =J78-N78 -> 38421034 | R78: 61400000 | T78: 61574226 | V78: =R78-T78 -> -174226.47 | X78: 11830346 | Z78: =T78-X78 -> 49743880 | AB78: 50486710 | AD78: 50486710 | AF78: =AB78-AD78 -> 0 | AH78: 11576777 | AJ78: =AD78-AH78 -> 38909933
D79: Amortization | N79: 27653354 | P79: =J79-N79 -> -27653354 | X79: 31049721 | Z79: =T79-X79 -> -31049721 | AF79: =AB79-AD79 -> 0 | AH79: 26709270 | AJ79: =AD79-AH79 -> -26709270
C80: CDRRMF
D81: Maintenance and Other Operating Expenses | H81: 29003942 | J81: 58628415 | L81: =H81-J81 -> -29624473 | N81: 51789959 | P81: =J81-N81 -> 6838456 | R81: 25979928 | T81: 40202607 | V81: =R81-T81 -> -14222679 | X81: 39277025 | Z81: =T81-X81 -> 925582.06 | AB81: 25671327 | AD81: 26057405 | AF81: =AB81-AD81 -> -386077.9 | AH81: 7870254.5 | AJ81: =AD81-AH81 -> 18187151
D82: Capital Outlay | H82: 26342531 | J82: 14704025 | L82: =H82-J82 -> 11638506 | P82: =J82-N82 -> 14704025 | R82: 23286500 | T82: 13806083 | V82: =R82-T82 -> 9480416.5 | X82: 2204451 | Z82: =T82-X82 -> 11601632 | AB82: 26203068 | AD82: 26203068 | AF82: =AB82-AD82 -> 0 | AH82: 5225005 | AJ82: =AD82-AH82 -> 20978063
C83: 20% Development Fund
D84: Maintenance and Other Operating Expenses | N84: 423852.48 | P84: =J84-N84 -> -423852.48 | R84: 0 | AB84: 0 | AD84: 0 | AF84: 0 | AH84: 0 | AJ84: =AD84-AH84 -> 0
D85: Capital Outlay | H85: 11000000 | J85: 195599800 | L85: =H85-J85 -> -184599800 | N85: 1.3295925e+08 | P85: =J85-N85 -> 62640552 | R85: 147600000 | T85: 199900000 | V85: =R85-T85 -> -52300000 | X85: 94991421 | Z85: =T85-X85 -> 1.0490858e+08 | AB85: 149700000 | AD85: 1.5096319e+08 | AF85: =AB85-AD85 -> -1263189.5 | AH85: 76570674 | AJ85: =AD85-AH85 -> 74392515
C86: Share from National Wealth | AF86: =AB86-AD86 -> 0 | AJ86: =AD86-AH86 -> 0
D87: Maintenance and Other Operating Expenses | P87: =J87-N87 -> 0 | Z87: =T87-X87 -> 0 | AF87: =AB87-AD87 -> 0 | AJ87: =AD87-AH87 -> 0
D88: Capital Outlay | P88: =J88-N88 -> 0 | Z88: =T88-X88 -> 0 | AF88: =AB88-AD88 -> 0 | AJ88: =AD88-AH88 -> 0
C89: Allocation for Senior Citizens and PWD | AF89: =AB89-AD89 -> 0 | AJ89: =AD89-AH89 -> 0
D90: Maintenance and Other Operating Expenses | P90: =J90-N90 -> 0 | Z90: =T90-X90 -> 0 | AF90: =AB90-AD90 -> 0 | AJ90: =AD90-AH90 -> 0
D91: Capital Outlay | P91: =J91-N91 -> 0 | Z91: =T91-X91 -> 0 | AF91: =AB91-AD91 -> 0 | AJ91: =AD91-AH91 -> 0
C92: Others
D93: Maintenance and Other Operating Expenses | L93: =H93-J93 -> 0 | P93: =J93-N93 -> 0 | R93: 0 | T93: 0 | V93: =R93-T93 -> 0 | X93: 0 | Z93: =T93-X93 -> 0 | AB93: 53472455 | AD93: 94521561 | AF93: =AB93-AD93 -> -41049107 | AH93: 75461428 | AJ93: =AD93-AH93 -> 19060133
D94: Aid to Brgys. | H94: 2800000 | J94: 2800000 | L94: =H94-J94 -> 0 | N94: 2660000 | P94: =J94-N94 -> 140000 | R94: 2800000 | T94: 2800000 | V94: =R94-T94 -> 0 | X94: 2120000 | Z94: =T94-X94 -> 680000 | AB94: 0 | AD94: 0 | AF94: =AB94-AD94 -> 0 | AH94: 0 | AJ94: =AD94-AH94 -> 0
D95: Intelligence/Confidential Fund | H95: 28440000 | J95: 28440000 | L95: =H95-J95 -> 0 | N95: 28440000 | P95: =J95-N95 -> 0 | R95: 15000000 | T95: 28440000 | V95: =R95-T95 -> -13440000 | X95: 28440000 | Z95: =T95-X95 -> 0 | AB95: 0 | AD95: 0 | AF95: =AB95-AD95 -> 0 | AH95: 0 | AJ95: =AD95-AH95 -> 0
D96: 2% Discretionary Fund | H96: 672389.99 | J96: 672389.99 | L96: =H96-J96 -> 0 | N96: 672292.51 | P96: =J96-N96 -> 97.48 | R96: 589491.62 | T96: 589491.62 | V96: =R96-T96 -> 0 | X96: 589491.62 | Z96: =T96-X96 -> 0 | AB96: 0 | AD96: 0 | AF96: =AB96-AD96 -> 0 | AH96: 0 | AJ96: =AD96-AH96 -> 0
D97: MPBF | J97: 44632622 | L97: =H97-J97 -> -44632622 | N97: 43168830 | P97: =J97-N97 -> 1463792.5 | R97: 6762686.2 | T97: 60188900 | V97: =R97-T97 -> -53426214 | X97: 52758166 | Z97: =T97-X97 -> 7430734.1 | AB97: 0 | AD97: 0 | AF97: =AB97-AD97 -> 0 | AH97: 0 | AJ97: =AD97-AH97 -> 0
D98: Subsidy to Economic Enterprise/Special Accounts | J98: 15122372 | L98: =H98-J98 -> -15122372 | N98: 15122372 | P98: =J98-N98 -> 0 | R98: 3936955.6 | T98: 11065285 | V98: =R98-T98 -> -7128329.9 | X98: 9807349.5 | Z98: =T98-X98 -> 1257936 | AB98: 0 | AD98: 0 | AF98: =AB98-AD98 -> 0 | AH98: 0 | AJ98: =AD98-AH98 -> 0
AF99: =AB99-AD99 -> 0 | AJ99: =AD99-AH99 -> 0
C100: Total Current Approrpiations | H100: =SUM(H49:H98) -> 1.1852816e+09 | J100: =SUM(J49:J98) -> 2.0062537e+09 | L100: =SUM(L49:L98) -> -8.2097206e+08 | N100: =SUM(N49:N98) -> 1.1636986e+09 | P100: =SUM(P49:P98) -> 8.4255511e+08 | R100: =SUM(R49:R98) -> 1.0714048e+09 | T100: =SUM(T49:T98) -> 1.4965837e+09 | V100: =SUM(V49:V98) -> -4.2517892e+08 | X100: =SUM(X49:X98) -> 1.0557667e+09 | Z100: =SUM(Z49:Z98) -> 4.40817e+08 | AB100: =SUM(AB49:AB99) -> 1.0389779e+09 | AC100: =SUM(AC49:AC99) -> 0 | AD100: =SUM(AD49:AD99) -> 1.2109392e+09 | AE100: =SUM(AE49:AE99) -> 0 | AF100: =SUM(AF49:AF99) -> -1.7196127e+08 | AG100: =SUM(AG49:AG99) -> 0 | AH100: =SUM(AH49:AH99) -> 9.3336027e+08 | AI100: =SUM(AI49:AI99) -> 0 | AJ100: =SUM(AJ49:AJ99) -> 2.7757891e+08
A101: Continuing Aprropriations
B102: General Public Services
...

Sheet F
A1: City Government of Panabo | D1: Annex F
A2: As of November 30, 2021
A4: Schedule of reconciling items
A6: Account No. | B6: Date | C6: Check No. | D6: Amount
A7: Unrecorded Paid Vouchers
A8: 1742-1006-90 | B8: 43620 | C8: 1395928 | D8: 1200
B9: 44266 | C9: 1482772 | D9: 187500
B10: 44460 | C10: 1514546 | D10: 2230
B11: 44524 | C11: 1515374 | D11: 10000
A12: 1742-1007-03 | B12: 44524 | C12: 1506411 | D12: 46120
A13: 1742-1006-81 | B13: 44529 | C13: 1440965 | D13: 2200
A14: 1742-1037-29 | B14: 44494 | C14: 1459199 | D14: 35493
A15: 1742-1008-35 | B15: 44526 | C15: 1507048 | D15: 228006.7
B16: 44518 | C16: 1507065 | D16: 4032.77
B17: 44523 | C17: 1507082 | D17: 33692.85
B18: 44525 | C18: 1507088 | D18: 122159
B19: 44525 | C19: 1507089 | D19: 49144.97
B20: 44526 | C20: 1507092 | D20: 2300
B21: 44526 | C21: 1507093 | D21: 11600
B22: 44529 | C22: 1507094 | D22: 17861.11
A23: 1742-1037-10 | B23: 44525 | C23: 1491872 | D23: 17458.36
B24: 44525 | C24: 1491872 | D24: 31196
B25: 44495 | C25: 1491840 | D25: 800
B26: 44495 | C26: 1491841 | D26: 200
A27: 1742-1037-96 | B27: 44524 | C27: 1406994 | D27: 2286744.3
B28: Total | D28: =SUM(D8:D27) -> 3089939.1

Sheet G
A1: City Government of Panabo | C1: Annex G
A2: As at December 31, 2021
A4: Schedule of reconciling items
A6: Account No. | B6: Date | C6: Amount
A7: Unrecorded Credit Memo
A8: 1742-1006-90 | B8: CM Ordinary dated 12-03-19 | C8: 40000
B9: CM Ordinary dated 05-25-21 | C9: 6145
B10: CM Ordinary dated 09-21-21 | C10: 200
B11: CM Ordinary remittance mgt Dept. dated 11-29-21 | C11: 150
B12: CM Ordinary dated 11-29-21 | C12: 11
A13: 1742-1007-03 | B13: CM- PYRL/OTHRS dtd 11-28-19 | C13: 30000
A14: 1742-1033-46 | B14: CM-ordinary dtd 8-13-18 | C14: 750
A15: 1742-1037-29 | B15: CM Ordinary dtd 8-13-18 | C15: 750
A16: 1742-1044-07 | B16: CM-auto reansfer | C16: 100
A17: 1742-1043-50 | B17: CA-CM ordinary dtd 1-4-19 | C17: 50000
A18: 1742-1066-55 | B18: CM-Ordinary dtd 9/29/20 | C18: 20000
B19: CM-Ordinary dtd 9/230/20 | C19: 2800
B20: Sub-total | C20: =SUM(C8:C19) -> 150906
A21: Unrecorded Debit Memo
A22: 1742-1006-90 | B22: Authorized transfer dtd 6-10-14 | C22: 2564
B23: DM Ordinary dated 7-14-14 | C23: 2995
B24: DM Ordinary dated 5-16-17 | C24: 1515
B25: DM Ordinary dated 10-19-18 | C25: 2256
B26: DM Ordinary dated 11/16-18 | C26: 1995
B27: DM Ordinary dated 1-29-19 | C27: 2258
B28: DM Ordinary dated 3-20-19 | C28: 2250
B29: DM Ordinary dated 4-12-19 | C29: 2251
B30: DMRT dated 4-10-19 | C30: 27812.96
B31: DM Ordinary dated 7-16-19 | C31: 6855
B32: DM Ordinary dated 9-29-20 | C32: 20000
B33: DM Ordinary dated 10-4-21 | C33: 46579.98
A34: 1742-1006-81 | B34: DM Ordinary dated 11-27-19 | C34: 3000
B35: DMTRA CA DM TRF AUTH dtd 7-13-20 | C35: 246277.89
A36: 1742-1007-03 | B36: DM-ordinary dtd 10-19-18 | C36: 1800
B37: DMTRA CA DM TRF AUTH dtd 8/27/21 | C37: 81000
A38: 1742-1033-46 | B38: DM-ordinary dtd 11-27-19 | C38: 1800
B39: DM-Ordinary dtd 10-5-21 | C39: 1800
A40: 1742-1037-29 | B40: DM-ordinary dtd 7-8-21 | C40: 1800
A41: 1742-1008-35 | B41: DM stubs checkbooks @360 | C41: 1080
B42: DM - ordinary dtd 10-5-21 | C42: 3000
A43: 1742-1037-10 | B43: DM ordinary dtd 10-22-20 | C43: 1800
B44: DM ordinary dtd 10-5-21 | C44: 1800
A45: 1742-1037-96 | B45: DM ordinary dtd 7-8-21 | C45: 1800
A46: 1753-1045-04 | B46: DM- Ordinary dtd 5-8-20 | C46: 600
A47: 1742-1066-55 | B47: DM- Ordinary dtd 10/8/20 | C47: 600
B48: Sub-total | C48: =SUM(C22:C47) -> 467489.83
A49: Book Errors
A50: 1742-1006-90 | B50: Adjustment on JEV-2021-09-014178 was recorded as duplicte deposit with OR No.0237456-7, RCD-2021-09-08 dated 9-3-21 | C50: 39551.88
B51: Adjustment on JEV-2021-11-017438 was recorded as P27,000 instead of P24,000 | C51: 30000
B52: Adjustment on JEV-2021-11-017031 was recorded as P14,296.26 instead of P11,290.82 | C52: 20
B53: Adjustment on JEV-2021-11-017834 was recorded as P14,296.26 instead of P11,290.83 | C53: 0.08
B54: Adjustment on JEV-2021-11-017500 was recorded as P142,330.86 instead of P42,331.47 | C54: 0.61
B55: Sub-total | C55: =SUM(C50:C54) -> 69572.57
A56: Deposits
A57: 1742-1006-81 | B57: Unrecorded deposit dated 8-28-20 | C57: 0.28
B58: Deposit collections | C58: 269103.27
B59: Unrecorded Deposit for the month of March 2020 | C59: 720820.62
A60: 1742-1046-10 | B60: Deposit of collections | C60: 10
A61: 1742-1006-90 | B61: Untraceable deposit in transient | C61: 39156.48
B62: Sub-total | C62: =SUM(C57:C61) -> 1029090.7
A64: Service Charge
A65: 1742-1066-55 | B65: SC Minimum on July & August 2019 | C65: 400
B66: SC Minimum dtd 9/30/19 | C66: 200
B67: SC Minimum dtd 10/31/19 | C67: 200
B68: SC Minimum dtd 11/30/19 | C68: 200
B69: SC Minimum dtd 12/27/19 | C69: 200
B70: SC Minimum dtd 1/31/20 | C70: 200
B71: SC Minimum dtd 2/28/20 | C71: 200
B72: SC Minimum dtd 3/31/20 | C72: 200
B73: SC Minimum dtd4/30/20 | C73: 200
B74: SC Minimum dtd 5/29/20 | C74: 200
B75: SC Minimum dtd 6/30/20 | C75: 200
B76: SC Minimum dtd 7/30/20 | C76: 200
B77: SC Minimum dtd 8/28/20 | C77: 200
... B85: Tax withheld on interest income for the 3Q CY 2021 | C85: 0.77
B86: Sub-total | C86: =SUM(C65:C85) -> 2818.26
B88: Grand Total | C88: =C20+C48+C55+C62+C86 -> 1719877.3

Sheet H
A1: Annex A: Total COVID-19 Vaccines Received by the City of Panabo and its Ending Inventory | M1: Annex H
A2: As of December 31, 2021
E3: Per GSO | H3: Per Audit | M3: Remarks
E4: Received | H4: Received | K4: Ending balance
A5: DATE | B5: PTR No. | C5: Vaccine Brand | D5: Received From | E5: Qty | F5: Price | G5: Total | H5: Qty | I5: Price | J5: Total | K5: Qty | L5: Total
E6: a | F6: b | G6: (a x b) | H6: a | I6: b | J6: (a x b) | K6: c | L6: (c x b)
A7: First Dose
A8: 44266 | B8: CVS-21-03-03 | C8: Astrazeneca | D8: PHO | E8: 22 | F8: 1942.8 | G8: 42741.6 | H8: 22 | I8: 1942.8 | J8: 42741.6 | L8: 0
A9: 44266 | B9: CVS-21-03-03 | C9: Sinovac | D9: PHO | H9: 600 | I9: 714.37 | J9: 428622 | L9: 0 | M9: As per PTR, 600 units of Sinovac with unit price of P714.37, was erroneously totaled as P214,311.00.
A10: 44271 | B10: 21-V-03-20 | C10: Sinovac | D10: PHO | E10: 64 | F10: 714.37 | G10: 45719.68 | H10: 64 | I10: 714.37 | J10: 45719.68 | L10: 0
A11: 44277 | B11: 21-V-03-69 | C11: Astrazeneca | D11: PHO | E11: 70 | F11: 1942.8 | G11: 135996 | H11: 70 | I11: 1942.8 | J11: 135996 | L11: 0
A12: 44292 | B12: V-21-04-16 | C12: Sinovac | D12: PHO | E12: 150 | F12: 715.55 | G12: 107332.5 | H12: 150 | I12: 715.55 | J12: 107332.5 | L12: 0
A13: 44298 | B13: V-21-04-19 | C13: Sinovac | D13: PHO | E13: 303 | F13: 700 | G13: 212100 | H13: 303 | I13: 700 | J13: 212100 | L13: 0
A14: 44306 | B14: V-21-04-35 | C14: Sinovac | D14: PHO | E14: 527 | F14: 683.2 | G14: 360046.4 | H14: 527 | I14: 683.2 | J14: 360046.4 | L14: 0
A15: 44327 | B15: V-21-05-18 | C15: Sinovac | D15: PHO | E15: 700 | F15: 683.2 | G15: 478240 | H15: 700 | I15: 683.2 | J15: 478240 | L15: 0
A16: 44328 | B16: V-21-05-46 | C16: Astrazeneca | D16: PHO | E16: 190 | F16: 1911.2 | G16: 363128 | H16: 190 | I16: 1911.2 | J16: 363128 | L16: 0
A17: 44337 | B17: V-21-05-61 | C17: Sinovac | D17: PHO | E17: 1000 | F17: 683.2 | G17: 683200 | H17: 1000 | I17: 683.2 | J17: 683200 | L17: 0
A18: 44337 | B18: V-21-05-72 | C18: Astrazeneca | D18: PHO | E18: 200 | F18: 1911.2 | G18: 382240 | H18: 200 | I18: 1911.2 | J18: 382240 | L18: 0
A19: 44375 | B19: V-21-06-88 | C19: Sinovac | D19: PHO | E19: 1500 | F19: 669.41 | G19: 1004115 | H19: 1500 | I19: 669.41 | J19: 1004115 | L19: 0
A20: 44379 | B20: V-21-07-08 | C20: Sinovac | D20: PHO | E20: 1000 | F20: 669.41 | G20: 669410 | H20: 1000 | I20: 669.41 | J20: 669410 | L20: 0
A21: 44396 | B21: V-21-07-41 | C21: Sinovac | D21: PHO | E21: 1500 | F21: 669.41 | G21: 1004115 | H21: 1500 | I21: 669.41 | J21: 1004115 | L21: 0
... A33: 44453 | B33: V-21-09-79 | C33: Pfizer | D33: PHO | E33: 170 | F33: 1958.82 | G33: 332999.4 | H33: 170 | I33: 1958.82 | J33: 332999.4 | L33: 0
C34: Pfizer | D34: PHO | E34: 230 | F34: 1958.82 | G34: 450528.6 | H34: 230 | I34: 1958.82 | J34: 450528.6 | L34: 0
A35: 44460 | B35: V-21-09-87 | C35: Sinovac | D35: PHO | E35: 3500 | F35: 669.41 | G35: 2342935 | H35: 3500 | I35: 669.41 | J35: 2342935 | L35: 0
A36: 44468 | B36: V-21-09-108 | C36: Pfizer | D36: PHO | E36: 450 | F36: 1958.82 | G36: 881469 | H36: 450 | I36: 1958.82 | J36: 881469 | L36: 0
A37: 44474 | B37: V-21-10-14 | C37: Sinovac | D37: PHO | E37: 2000 | F37: 669.41 | G37: 1338820 | H37: 2000 | I37: 669.41 | J37: 1338820 | L37: 0
A38: 44477 | B38: V-21-10-24 | C38: Pfizer | D38: PHO | E38: 350 | F38: 1958.82 | G38: 685587 | H38: 350 | I38: 2017.3 | J38: 706055 | L38: 0
A39: 44487 | B39: V-21-10-32 | C39: Pfizer | D39: PHO | E39: 350 | F39: 1958.82 | G39: 685587 | H39: 1200 | I39: 2017.3 | J39: 2420760 | L39: 0
A40: 44494 | B40: V-21-10-66 | C40: Sinovac | D40: PHO | E40: 1000 | F40: 669.41 | G40: 669410 | H40: 1000 | I40: 669.41 | J40: 669410 | L40: 0
A41: 44494 | B41: V-21-10-69 | C41: Sinovac | D41: PHO | E41: 2500 | F41: 669.41 | G41: 1673525 | H41: 2500 | I41: 669.41 | J41: 1673525 | L41: 0
A42: 44495 | B42: V-21-10-74 | C42: Moderna | D42: PHO | E42: 44 | F42: 2098.23 | G42: 92322.12 | H42: 44 | I42: 2098.23 | J42: 92322.12 | L42: 0
A43: 44495 | B43: V-21-10-75 | C43: Pfizer | D43: PHO | E43: 1365 | F43: 2017.3 | G43: 2753614.5 | H43: 1365 | I43: 2017.3 | J43: 2753614.5 | L43: 0
A44: 11/0/2021 | B44: 21-V-11-107 | C44: Astrazeneca | D44: DOH RO XI | E44: 170 | F44: 2021.24 | G44: 343610.8 | H44: 170 | I44: 2021.24 | J44: 343610.8 | L44: 0
A45: 44502 | B45: V-21-11-07 | C45: Pfizer | D45: PHO | E45: 1335 | F45: 2017.3 | G45: 2693095.5 | H45: 1335 | I45: 2017.3 | J45: 2693095.5 | L45: 0
A46: 44512 | B46: V-21-11-44 | C46: Pfizer | D46: PHO | E46: 1000 | F46: 2017.3 | G46: 2017300 | H46: 1000 | I46: 2017.3 | J46: 2017300 | L46: 0
A47: 44518 | B47: V-21-11-79 | C47: Sinovac | D47: PHO | E47: 2000 | F47: 669.41 | G47: 1338820 | H47: 2000 | I47: 669.41 | J47: 1338820 | L47: 0
A48: 44518 | B48: V-21-11-84 | C48: Moderna | D48: PHO | E48: 30 | F48: 2098.23 | G48: 62946.9 | H48: 30 | I48: 2098.23 | J48: 62946.9 | L48: 0
A49: 44524 | B49: V-21-11-106 | C49: Sinovac | D49: PHO | E49: 3000 | F49: 334.54 | G49: 1003620 | H49: 3000 | I49: 334.54 | J49: 1003620 | L49: 0
A50: 44529 | B50: V-21-11-119 | C50: Moderna | D50: PHO | E50: 200 | F50: 2098.23 | G50: 419646 | H50: 200 | I50: 2098.23 | J50: 419646 | L50: 0
A51: 44529 | B51: V-21-11-131 | C51: Astrazeneca | D51: PHO | E51: 50 | F51: 2021.24 | G51: 101062 | H51: 50 | I51: 2021.24 | J51: 101062 | L51: 0
A52: 44529 | B52: V-21-11-145 | C52: Pfizer | D52: PHO | E52: 250 | F52: 2017.3 | G52: 504325 | H52: 250 | I52: 2017.3 | J52: 504325 | L52: 0
A53: 11/0/2021 | B53: 21-V-11-24 | C53: Astrazeneca | D53: DOH RO XI | E53: 300 | F53: 2021.24 | G53: 606372 | H53: 300 | I53: 2021.24 | J53: 606372 | L53: 0 | M53: Correctly recorded in the books
A54: 11/0/2021 | B54: 21-V-11-71 | C54: PFIZER Comirnaty Vaccine | D54: DOH RO XI | E54: 487 | F54: 2017.3 | G54: 982425.1 | H54: 487 | I54: 2017.3 | J54: 982425.1 | L54: 0 | M54: Correctly recorded in the books
A55: 12/0/2021 | B55: 21-V-12-125 | C55: Sinovac | D55: DOH RO XI | E55: 14570 | F55: 611.36 | G55: 8907515.2 | H55: 2480 | I55: 611.36 | J55: 1516172.8 | L55: 0 | M55: - 14,570 vials were the total allocation for Davao del Norte, of which 2,480 vials were received by Panabo. -Correctly recorded in the books
A56: 12/0/2021 | B56: V-21-12-02 | C56: Pfizer | D56: PHO | E56: 218 | F56: 2017.3 | G56: 439771.4 | H56: 218 | I56: 2017.3 | J56: 439771.4 | L56: 0
A57: 44533 | B57: V-21-12-25 | C57: Moderna | D57: PHO | E57: 10 | F57: 2098.23 | G57: 20982.3 | H57: 10 | I57: 2098.23 | J57: 20982.3 | L57: 0
A58: 44536 | B58: V-21-12-49 | C58: Astrazeneca | D58: PHO | E58: 90 | F58: 2021.24 | G58: 181911.6 | H58: 90 | I58: 2021.24 | J58: 181911.6 | L58: 0
A59: 44544 | B59: V-21-12-51 | C59: Astrazeneca | D59: PHO | E59: 85 | F59: 2021.24 | G59: 171805.4 | H59: 85 | I59: 2021.24 | J59: 171805.4 | L59: 0
A60: 44544 | B60: V-21-12-59 | C60: Sinovac | D60: PHO | E60: 3000 | F60: 334.54 | G60: 1003620 | H60: 3000 | I60: 334.54 | J60: 1003620 | K60: 3000 | L60: 1003620
A61: 44545 | B61: V-21-12-70 | C61: Astrazeneca | D61: PHO | E61: 150 | F61: 2021.24 | G61: 303186 | H61: 150 | I61: 2021.24 | J61: 303186 | L61: 0
A62: 44550 | B62: V-21-12-90 | C62: Janssen | D62: PHO | F62: 2017.3 | G62: 0 | H62: 1000 | I62: 2017.3 | J62: 2017300 | K62: 994 | L62: 2005196.2
A63: Second Dose
A64: 44291 | B64: V-21-04-05 | C64: Sinovac | D64: PHO | E64: 664 | F64: 714.37 | G64: 474341.68 | H64: 664 | I64: 714.37 | J64: 474341.68 | L64: 0
A65: 44312 | B65: V-21-04-05 | C65: Sinovac | D65: PHO | E65: 453 | F65: 683.2 | G65: 309489.6 | H65: 453 | I65: 683.2 | J65: 309489.6 | L65: 0
A66: 44323 | B66: V-21-05-08 | C66: Sinovac | D66: PHO | E66: 327 | F66: 683.2 | G66: 223406.4 | H66: 327 | I66: 683.2 | J66: 223406.4 | L66: 0
A67: 44328 | B67: V-21-05-21 | C67: Astrazeneca | D67: PHO | E67: 76 | F67: 1911.2 | G67: 145251.2 | H67: 76 | I67: 1911.2 | J67: 145251.2 | L67: 0
A68: 44363 | B68: V-21-06-06 | C68: Sinovac | D68: PHO | E68: 700 | F68: 683.2 | G68: 478240 | H68: 700 | I68: 683.2 | J68: 478240 | L68: 0
A69: 44363 | B69: V-21-06-34 | C69: Sinovac | D69: PHO | E69: 1000 | F69: 683.2 | G69: 683200 | H69: 1000 | I69: 683.2 | J69: 683200 | L69: 0
A70: 44366 | B70: V-21-06-51 | C70: Astrazeneca | D70: PHO | E70: 280 | F70: 1994.21 | G70: 558378.8 | H70: 280 | I70: 1994.21 | J70: 558378.8 | L70: 0
A71: 44403 | B71: V-21-07-73 | C71: J & J | D71: PHO | E71: 450 | F71: 1892.55 | G71: 851647.5 | H71: 450 | I71: 1892.55 | J71: 851647.5 | L71: 0
A72: 44403 | B72: V-21-07-82 | C72: Sinovac | D72: PHO | E72: 1000 | F72: 669.41 | G72: 669410 | H72: 1000 | I72: 669.41 | J72: 669410 | L72: 0
A73: 44406 | B73: V-21-07-96 | C73: Janssen | D73: PHO | E73: 40 | F73: 1892.55 | G73: 75702 | H73: 40 | I73: 1892.55 | J73: 75702 | L73: 0
A74: 44413 | B74: V-21-08-18 | C74: Sinovac | D74: PHO | E74: 1100 | F74: 669.41 | G74: 736351 | H74: 1100 | I74: 669.41 | J74: 736351 | L74: 0
A75: 44424 | B75: V-21-08-112 | C75: Sinovac | D75: PHO | E75: 2000 | F75: 669.41 | G75: 1338820 | H75: 2000 | I75: 669.41 | J75: 1338820 | L75: 0
... A96: 44525 | B96: V-21-11-93 | C96: Pfizer | D96: PHO | E96: 1335 | F96: 2017.3 | G96: 2693095.5 | H96: 1335 | I96: 2017.3 | J96: 2693095.5 | L96: 0
A97: 44533 | B97: V-21-12-12 | C97: Sinovac | D97: PHO | E97: 2000 | F97: 669.41 | G97: 1338820 | H97: 2000 | I97: 669.41 | J97: 1338820 | K97: 2000 | L97: 1338820
A98: 44533 | B98: V-21-12-37 | C98: Pfizer | D98: PHO | E98: 1000 | F98: 2017.3 | G98: 2017300 | H98: 1000 | I98: 2017.3 | J98: 2017300 | L98: 0
A99: 44544 | B99: V-21-12-106 | C99: Astrazeneca | D99: PHO | E99: 292 | F99: 2021.24 | G99: 590202.08 | H99: 292 | I99: 2021.24 | J99: 590202.08 | L99: 0
A100: 44547 | B100: V-21-12-84 | C100: Pfizer | D100: PHO | E100: 250 | F100: 2017.3 | G100: 504325 | H100: 250 | I100: 2017.3 | J100: 504325 | L100: 0
A101: 44547 | B101: V-21-12-85-A | C101: Pfizer | D101: PHO | E101: 418 | F101: 2017.3 | G101: 843231.4 | H101: 418 | I101: 2017.3 | J101: 843231.4 | L101: 0
A102: 44552 | B102: V-21-12-86-B | C102: Pfizer | D102: PHO | E102: 233 | F102: 2017.3 | G102: 470030.9 | H102: 233 | I102: 2017.3 | J102: 470030.9 | K102: 80 | L102: 161384
A103: 44553 | C103: Astrazeneca | D103: LGU TAGUM | E103: 150 | F103: 2021.24 | G103: 303186 | H103: 150 | I103: 2021.24 | J103: 303186 | L103: 0
A104: 44557 | B104: V-21-12-102 | C104: Astrazeneca | D104: PHO | E104: 28 | F104: 2021.24 | G104: 56594.72 | H104: 28 | I104: 2021.24 | J104: 56594.72 | K104: 88 | L104: 177869.12
A105: 44557 | B105: V-21-12-103 | C105: Moderna | D105: PHO | E105: 50 | F105: 2098.23 | G105: 104911.5 | H105: 50 | I105: 2098.23 | J105: 104911.5 | K105: 6 | L105: 12589.38
D106: TOTAL COVID-19 VACCINES | H106: 82970 | J106: 77559898 | K106: 6168 | L106: 4699478.7

Sheet I
A1: City Government of Panabo | K1: Annex I
A2: As at December 31, 2021
A4: Schedule of Completed Pojects under CIP accounts
A7: No. | B7: Fund | C7: Account Code | D7: Account Title | E7: Description | F7: Amount | G7: Date Completed | H7: Estimated useful life (in months) | I7: No. of months of depreciation as at year-end | J7: Total depreciation | K7: Asset Account
A8: 1 | B8: General Fund | C8: 269 | D8: CIP-Artesian Wells, Reservoirs, Pumping Stations and Conduits | E8: POW#2019-05-204_INSTALLATION OF WATER SYSTEM WITH RAINWATER HARVESTING FACILITY AT PANABO CITY | F8: 1453309.8 | G8: 44245 | H8: 240 | I8: 10 | J8: =((F8*0.9)/H8)*I8 -> 54499.118 | K8: Artesian Wells, Reservoirs, Pumping Stations and Conduits
D9: Sub-total | F9: =SUM(F8) -> 1453309.8 | J9: =SUM(J8) -> 54499.118
A11: 2 | B11: General Fund | C11: 264 | D11: CIP-Agency Assets | E11: POW#2019-10-001_Site Developmentfor Resettlement Areas - Land Development (DAVIN) @ Brgy. San Franci | F11: 347288.06 | G11: 44469 | H11: 120 | I11: 3 | J11: =((F11*0.9)/H11)*I11 -> 7813.9814 | K11: Land Improvement
A12: =A11+1 -> 3 | B12: General Fund | C12: 264 | D12: CIP-Agency Assets | E12: POW#2019-10-001_Site Developmentfor Resettlement Areas - Land Development (DAVIN) @ Brgy. San Franci | F12: 166134.19 | G12: 40816 | H12: 120 | I12: 120 | J12: =((F12*0.9)/H12)*I12 -> 149520.77 | K12: Land Improvement
A13: =A12+1 -> 4 | B13: General Fund | C13: 264 | D13: CIP-Agency Assets | E13: Cons. of 477 li.m. Perimeter Fence Fronting Cityhall Government Center w/Gate Component @ Brgy. JP L | F13: 1841479 | G13: 43016 | H13: 120 | I13: =2+12+12+12+12 -> 50 | J13: =((F13*0.9)/H13)*I13 -> 690554.62 | K13: Land Improvement
A14: =A13+1 -> 5 | B14: General Fund | C14: 273 | D14: CIP-Other Public Infrastructures | E14: Construction of Perimeter Fence at PAnabo City Eternal Garden, Brgy. Datu Abdul, Panabo City/Project | F14: 1417023.7 | G14: 43067 | H14: 120 | I14: =1+12+12+12+12 -> 49 | J14: =((F14*0.9)/H14)*I14 -> 520756.22 | K14: Land Improvement
A15: =A14+1 -> 6 | B15: General Fund | C15: 264 | D15: CIP-Agency Assets | E15: POW#2021-05-004_Site Development for Resettlement Areas @Brgy. San Fracisco | F15: 372713.93 | G15: 44469 | H15: 120 | I15: 3 | J15: =((F15*0.9)/H15)*I15 -> 8386.0634 | K15: Land Improvement
D16: Sub-total | F16: =SUM(F11:F15) -> 4144638.9 | J16: =SUM(J11:J15) -> 1377031.7
A18: 7 | B18: General Fund | C18: 264 | D18: CIP-Agency Assets | E18: POW#2020-07-265_Rehabilitation/ Improvement of Multi-Purpose Building- Salvacion | F18: 15442.77 | G18: 44321 | H18: 60 | I18: 7 | J18: =((F18*0.9)/H18)*I18 -> 1621.4908 | K18: Other Public Infrastructure
A19: =A18+1 -> 8 | B19: General Fund | C19: 264 | D19: CIP-Agency Assets | E19: POW#2019-09-344_CONSTRUCTION OF BATCHING FOUNDATION | F19: 711475.4 | G19: 44545 | H19: 60 | I19: 0 | J19: =((F19*0.9)/H19)*I19 -> 0 | K19: Other Public Infrastructure
A20: =A19+1 -> 9 | B20: General Fund | C20: 264 | D20: CIP-Agency Assets | E20: POW#2020-07-265_Rehabilitation/ Improvement of Multi-Purpose Building- Salvacion | F20: 93654.01 | G20: 44321 | H20: 60 | I20: 7 | J20: =((F20*0.9)/H20)*I20 -> 9833.6711 | K20: Other Public Infrastructure
A21: =A20+1 -> 10 | B21: General Fund | C21: 264 | D21: CIP-Agency Assets | E21: POW#2019-12-484_COMPLETION/OPERATION OF ASPHALT BATCHING PLANT | F21: 2116700 | G21: 44418 | H21: 60 | I21: 4 | J21: =((F21*0.9)/H21)*I21 -> 127002 | K21: Other Public Infrastructure
A22: =A21+1 -> 11 | B22: General Fund | C22: 264 | D22: CIP-Agency Assets | E22: POW#2019-05-195_RENOVATION OF PANABO CITY TEEN CENTER | F22: 614913.86 | G22: 43780 | H22: 60 | I22: =1+12+12 -> 25 | J22: =((F22*0.9)/H22)*I22 -> 230592.7 | K22: Other Public Infrastructure
A23: =A22+1 -> 12 | B23: General Fund | C23: 273 | D23: CIP-Other Public Infrastructures | E23: COMPLETION OF MULTI-PURPOSE GYM, PUROK RAMIHAN, BRGY. DATU ABDUL_POW#2015-06-348 | F23: 1228689.4 | G23: 42641 | H23: 60 | I23: 60 | J23: =((F23*0.9)/H23)*I23 -> 1105820.5 | K23: Other Public Infrastructure
A24: =A23+1 -> 13 | B24: General Fund | C24: 273 | D24: CIP-Other Public Infrastructures | E24: CONSTRUCTION OF PANABO CITY MARICULTURE COMPLEX (BAYWALK PHASE III)_POW#2016-09-466 | F24: 3809282 | G24: 43134 | H24: 60 | I24: =10+12+12+12 -> 46 | J24: =((F24*0.9)/H24)*I24 -> 2628404.6 | K24: Other Public Infrastructure
A25: =A24+1 -> 14 | B25: General Fund | C25: 273 | D25: CIP-Other Public Infrastructures | E25: CONSTRUCTION OF REHABILITATION CENTER FOR CICL_POW # 2015-05-280 | F25: 1000000 | G25: 42431 | H25: 60 | I25: 60 | J25: =((F25*0.9)/H25)*I25 -> 900000 | K25: Other Public Infrastructure
A26: =A25+1 -> 15 | B26: General Fund | C26: 273 | D26: CIP-Other Public Infrastructures | E26: CONSTRUCTION OF WOMEN'S CRISIS CENTER @ BRGY. DATU ABDUL_POW # 2015-06-306 | F26: 593179.45 | G26: 42431 | H26: 60 | I26: 60 | J26: =((F26*0.9)/H26)*I26 -> 533861.51 | K26: Other Public Infrastructure
A27: =A26+1 -> 16 | B27: General Fund | C27: 273 | D27: CIP-Other Public Infrastructures | E27: CONSTRUCTION OF SOLAR DRYER, BRGY. MABUNAO_POW#2016-02-130 | F27: 328407 | G27: 42660 | H27: 60 | I27: 60 | J27: =((F27*0.9)/H27)*I27 -> 295566.3 | K27: Other Public Infrastructure
A28: =A27+1 -> 17 | B28: General Fund | C28: 273 | D28: CIP-Other Public Infrastructures | E28: CONSTRUCTION OF BAYWALK (EXPANSION ON-WARD THE SEASHORE)_POW#2017-05-454 | F28: 3593904.8 | G28: 43223 | H28: 60 | I28: =7+12+12+12 -> 43 | J28: =((F28*0.9)/H28)*I28 -> 2318068.6 | K28: Other Public Infrastructure
A29: =A28+1 -> 18 | B29: General Fund | C29: 273 | D29: CIP-Other Public Infrastructures | E29: Installation of Traffic Lights w/ Controls & Vehicle Sensor at Junction Quirino St. National Highway | F29: 3695633.9 | G29: 42923 | H29: 60 | I29: =5+12+12+12+12 -> 53 | J29: =((F29*0.9)/H29)*I29 -> 2938028.9 | K29: Other Public Infrastructure
A30: =A29+1 -> 19 | B30: General Fund | C30: 273 | D30: CIP-Other Public Infrastructures | E30: Construction of Tennis Court - Brgy. J.P Laurel, Panabo City | F30: 1445157.2 | G30: 43049 | H30: 60 | I30: =1+12+12+12+12 -> 49 | J30: =((F30*0.9)/H30)*I30 -> 1062190.5 | K30: Other Public Infrastructure
A31: =A30+1 -> 20 | B31: General Fund | C31: 273 | D31: CIP-Other Public Infrastructures | E31: CONSTRUCTION OF CONCRETE DRAINAGE, BRGY. UPPER LICANAN_POW#2015-10-587 | F31: 117900 | G31: 42653 | H31: 60 | I31: 60 | J31: =((F31*0.9)/H31)*I31 -> 106110 | K31: Other Public Infrastructure
A32: =A31+1 -> 21 | B32: General Fund | C32: 264 | D32: CIP-Agency Assets | E32: POW#2021-03-118_Construction of Water & Sanitation Facilities(2 seater w/ PWD and sink), Consolacion | F32: 29927.28 | G32: 44431 | H32: 60 | I32: 4 | J32: =((F32*0.9)/H32)*I32 -> 1795.6368 | K32: Other Public Infrastructure
D33: Sub-total | F33: =SUM(F18:F32) -> 19394267 | J33: =SUM(J18:J32) -> 12258896
A35: 22 | B35: General Fund | C35: 264 | D35: CIP-Agency Assets | E35: Renovation of Angel Barachael Drop-in Center Phase II @ Brgy. New Pandan_POW#2016-08-397 | F35: 354011.86 | G35: 42737 | H35: 60 | I35: =11+12+12+12+12 -> 59 | J35: =((F35*0.9)/H35)*I35 -> 313300.5 | K35: Other Structure
D36: Sub-total | F36: =SUM(F35) -> 354011.86 | J36: =SUM(J35) -> 313300.5
A38: 23 | B38: General Fund | C38: 267 | D38: Construction in Progress - Parks, Plazas and Monuments | E38: Improvement of Parks & Plaza: Fencing & Lightings_Old City Hall_POW#2015-04-238 | F38: 39085.07 | G38: 42535 | H38: 240 | I38: 60 | J38: =((F38*0.9)/H38)*I38 -> 8794.1408 | K38: Parks, Plazas and Monuments
A39: 24 | B39: General Fund | C39: 267 | D39: Construction in Progress - Parks, Plazas and Monuments | E39: POW#2019-12-468_Improvement of Parks and Plaza at Old City Hall- New Pandan | F39: 789737.05 | G39: 44032 | H39: 240 | I39: =5+12 -> 17 | J39: =((F39*0.9)/H39)*I39 -> 50345.737 | K39: Parks, Plazas and Monuments
D40: Sub-total | F40: =SUM(F38:F39) -> 828822.12 | J40: =SUM(J38:J39) -> 59139.878
A42: 25 | B42: General Fund | C42: 266 | D42: CIP-Roads, Highways and bridges | E42: POW#2021-05-162_Concreting of Road- Consolacion to Malativas_300mm thick x 6.70m width x 944.50 ln.m | F42: 19975730 | G42: 44477 | H42: 240 | I42: 2 | J42: =((F42*0.9)/H42)*I42 -> 149817.98 | K42: Roads, Highways and bridges
D43: Sub-total | F43: =SUM(F42:F42) -> 19975730 | J43: =SUM(J42:J42) -> 149817.98
A45: 26 | B45: General Fund | C45: 272 | D45: CIP-Waterways, Aqueducts,Seawalls, Riverwalls and Others | E45: POW#2018-12-489_CONSTRUCTION OF DRAINAGE WITHIN PANABO PUBLIC PARK | F45: 1999371.7 | G45: 43726 | H45: 240 | I45: =3+12+12 -> 27 | J45: =((F45*0.9)/H45)*I45 -> 202436.39 | K45: Waterways, Aqueducts,Seawalls, Riverwalls and Others
D46: Sub-total | F46: =SUM(F45) -> 1999371.7 | J46: =SUM(J45) -> 202436.39
D48: Total - GF | F48: =F9+F16+F33+F36+F40+F43+F46 -> 48150152 | J48: =J9+J16+J33+J36+J40+J43+J46 -> 14415122
A51: 27 | B51: SEF | C51: 269 | D51: CIP-Artesian Wells, Reservoirs, Pumping Stations and Conduits | E51: POW#2019-04-191_INSTALLATION OF WATER RESERVOIR/ TANK (BEST TANK, TAGPORE, ES | F51: 175323.86 | G51: 43754 | H51: 240 | I51: =2+12+12 -> 26 | J51: =((F51*0.9)/H51)*I51 -> 17094.076 | K51: Artesian Wells, Reservoirs, Pumping Stations and Conduits
D52: Sub-total | F52: =SUM(F51) -> 175323.86 | J52: =SUM(J51) -> 17094.076
A54: 28 | B54: SEF | C54: 264 | D54: CIP-Agency Assets | E54: Construction of Perimeter Fence @ Sison E.S., Brgy. Sindaton_POW#2016-08-396 | F54: 177540 | G54: 42412 | H54: 120 | I54: 60 | J54: =((F54*0.9)/H54)*I54 -> 79893 | K54: Land Improvement
A55: =A54+1 -> 29 | B55: SEF | C55: 264 | D55: CIP-Agency Assets | E55: POW#2019-04-167_Construction of Perimeter Fence, So. Davao ES @Southern Davao | F55: 403748.93 | G55: 43689 | H55: 120 | I55: =4+12+12 -> 28 | J55: =((F55*0.9)/H55)*I55 -> 84787.275 | K55: Land Improvement
A56: =A55+1 -> 30 | B56: SEF | C56: 264 | D56: CIP-Agency Assets | E56: POW#2019-05-199_CONSTRUCTION OF PERIMETER FENCE, PANABO CITY SHS | F56: 781000.67 | G56: 43822 | H56: 120 | I56: =12+12 -> 24 | J56: =((F56*0.9)/H56)*I56 -> 140580.12 | K56: Land Improvement
A57: =A56+1 -> 31 | B57: SEF | C57: 273 | D57: CIP-Other Public Infrastructures | E57: FENCING OF ELEMENTARY SCHOOL - JP Laurel | F57: 8870 | G57: 42923 | H57: 120 | I57: =5+12+12+12+12 -> 53 | J57: =((F57*0.9)/H57)*I57 -> 3525.825 | K57: Land Improvement
A58: =A57+1 -> 32 | B58: SEF | C58: 273 | D58: CIP-Other Public Infrastructures | E58: CONSTRUCTION OF PERIMETER FENCE , SINDATON E/S_POW#2016-07-358 | F58: 129850 | G58: 43700 | H58: 120 | I58: =4+12+12 -> 28 | J58: =((F58*0.9)/H58)*I58 -> 27268.5 | K58: Land Improvement
A59: =A58+1 -> 33 | B59: SEF | C59: 273 | D59: CIP-Other Public Infrastructures | E59: POW#2019-03-132_Construction of Perimeter Fence P. Changco ES @Brgy. Tibungol | F59: 495053.34 | G59: 43751 | H59: 120 | I59: =2+12+12 -> 26 | J59: =((F59*0.9)/H59)*I59 -> 96535.401 | K59: Land Improvement
D60: Sub-total | F60: =SUM(F54:F59) -> 1996062.9 | J60: =SUM(J54:J59) -> 432590.12
A62: 34 | B62: SEF | C62: 273 | D62: CIP-Other Public Infrastructures | E62: REPAIR AND MAINTENANCE OF SCHOOL BLDG., PANABO CENTRAL E/S, SPED_POW#2016-07-367 | F62: 123946.5 | G62: 42885 | H62: 240 | I62: =7+12+12+12+12 -> 55 | J62: =((F62*0.9)/H62)*I62 -> 25563.966 | K62: Other Public Infrastructure
D63: Sub-total | F63: =SUM(F62) -> 123946.5 | J63: =SUM(J62) -> 25563.966
A65: 35 | B65: SEF | C65: 264 | D65: CIP-Agency Assets | E65: CONST. OF 1 STOREY 2 CLASSROOM SCHOOL BLDG.- NEW MALITBOG HIGH SCHOOL EXT. (PHASE II)_POW # 2016-09- | F65: 113013 | G65: 42766 | H65: 240 | I65: =11+12+12+12+12 -> 59 | J65: =((F65*0.9)/H65)*I65 -> 25004.126 | K65: School Buidling
A66: =A65+1 -> 36 | B66: SEF | C66: 264 | D66: CIP-Agency Assets | E66: IMPROVEMENT OF SCHOOL SITE, AOFES II, BRGY. SAN VICENTE_POW # 2016-08-405 | F66: 1012.07 | G66: 43133 | H66: 240 | I66: =10+12+12+12 -> 46 | J66: =((F66*0.9)/H66)*I66 -> 174.58208 | K66: School Buidling
A67: =A66+1 -> 37 | B67: SEF | C67: 264 | D67: CIP-Agency Assets | E67: POW#2019-01-006_CONSTRUCTION OF SCHOOL BUILDING ONE (1) STOREY 2 CL SCHOOL BUILDING, KASILAK E/S | F67: 2185938.1 | G67: 43731 | H67: 240 | I67: =3+12+12 -> 27 | J67: =((F67*0.9)/H67)*I67 -> 221326.23 | K67: School Buidling
A68: =A67+1 -> 38 | B68: SEF | C68: 264 | D68: CIP-Agency Assets | E68: POW#2019-07-263_COMPLETION OF SCHOOL BUILDING-ONE STOREY 3 CL 7 X 27 SCHOOL BUILDING, PHASE 2 SAN FR | F68: 488727.25 | G68: 43893 | H68: 240 | I68: =9+12 -> 21 | J68: =((F68*0.9)/H68)*I68 -> 38487.271 | K68: School Buidling
D69: Sub-total | F69: =SUM(F65:F68) -> 2788690.4 | J69: =SUM(J65:J68) -> 284992.21
A71: 39 | B71: SEF | C71: 272 | D71: CIP-Waterways, Aqueducts,Seawalls, Riverwalls and Others | E71: POW # 2018-06-257_SCHOOL SITE IMPROVEMENT(CONSTRUCTION OF DRAINAGE SYSTEM)A.O FLOIRENDO NHS | F71: 485364.41 | G71: 43434 | H71: 240 | I71: =1+12+12+12 -> 37 | J71: =((F71*0.9)/H71)*I71 -> 67344.312 | K71: Waterways, Aqueducts,Seawalls, Riverwalls and Others
D72: Sub-total | F72: =SUM(F71) -> 485364.41 | J72: =SUM(J71) -> 67344.312
D74: Total - SEF | F74: =F52+F60+F63+F69+F72 -> 5569388.1 | J74: =J52+J60+J63+J69+J72 -> 827584.68
A77: 40 | B77: Trust Fund | C77: 273 | D77: CIP-Other Public Infrastructures | E77: IMPROVEMENT OF PANABO EMERGENCY CLINIC_POW # 2017-09-653 | F77: 45001 | G77: 43441 | H77: 60 | I77: =12+12+12 -> 36 | J77: =((F77*0.9)/H77)*I77 -> 24300.54 | K77: Other Public Infrastructure
A78: =A77+1 -> 41 | B78: Trust Fund | C78: 264 | D78: CIP-Agency Assets | E78: POW#2020-03-166_Closure and Rehabilitation of Open Dumpsite (Phase II) @New Malitbog, PC | F78: 1409337.4 | G78: 44144 | H78: 60 | I78: =1+12 -> 13 | J78: =((F78*0.9)/H78)*I78 -> 274820.79 | K78: Other Public Infrastructure
A79: =A78+1 -> 42 | B79: Trust Fund | C79: 273 | D79: CIP-Other Public Infrastructures | E79: MATERIAL RECOVERY FACILITY AND SHARP SEPTIC VAULT_POW # 2017-07-564 | F79: 32916.48 | G79: 42988 | H79: 60 | I79: =3+12+12+12+12 -> 51 | J79: =((F79*0.9)/H79)*I79 -> 25181.107 | K79: Other Public Infrastructure
A80: =A79+1 -> 43 | B80: Trust Fund | C80: 273 | D80: CIP-Other Public Infrastructures | E80: CONSTRUCTION OF SEPTIC VAULT FOR DISPOSAL OF USED SHARPS & PLACENTA | F80: 35597.39 | G80: 41785 | H80: 60 | I80: 60 | J80: =((F80*0.9)/H80)*I80 -> 32037.651 | K80: Other Public Infrastructure
D81: Total - TF | F81: =SUM(F77:F80) -> 1522852.3 | J81: =SUM(J77:J80) -> 356340.09
D83: GRAND TOTAL | F83: =F48+F74+F81 -> 55242392 | J83: =J48+J74+J81 -> 15599047

Sheet J
A1: City Government of Panabo | K1: Annex J
A2: As at December 31, 2021
A4: Schedule of Completed Projects under CIP accounts
A7: No. | B7: Fund | C7: Account Code | D7: Account Title | E7: Description | F7: Amount | G7: Date Completed | H7: Estimated useful life (in months) | I7: No. of months of depreciation as at year-end | J7: Total depreciation | K7: Asset Account
A8: 1 | B8: General Fund | C8: 269 | D8: CIP-Artesian Wells, Reservoirs, Pumping Stations and Conduits | E8: POW#2019-05-204_INSTALLATION OF WATER SYSTEM WITH RAINWATER HARVESTING FACILITY AT PANABO CITY | F8: 1453309.8 | G8: 44245 | H8: 240 | I8: 10 | J8: 54499.12 | K8: Artesian Wells, Reservoirs, Pumping Stations and Conduits
D9: Sub-total | F9: =SUM(F8) -> 1453309.8 | J9: =SUM(J8) -> 54499.12
A11: 2 | B11: General Fund | C11: 264 | D11: CIP-Agency Assets | E11: POW#2019-10-001_Site Developmentfor Resettlement Areas - Land Development (DAVIN) @ Brgy. San Franci | F11: 347288.06 | G11: 44469 | H11: 120 | I11: 3 | J11: 7813.98 | K11: Land Improvement
A12: =A11+1 -> 3 | B12: General Fund | C12: 264 | D12: CIP-Agency Assets | E12: POW#2019-10-001_Site Developmentfor Resettlement Areas - Land Development (DAVIN) @ Brgy. San Franci | F12: 166134.19 | G12: 40816 | H12: 120 | I12: 120 | J12: 149520.77 | K12: Land Improvement
A13: =A12+1 -> 4 | B13: General Fund | C13: 264 | D13: CIP-Agency Assets | E13: Cons. of 477 li.m. Perimeter Fence Fronting Cityhall Government Center w/Gate Component @ Brgy. JP L | F13: 1841479 | G13: 43016 | H13: 120 | I13: =2+12+12+12+12 -> 50 | J13: 690554.63 | K13: Land Improvement
A14: =A13+1 -> 5 | B14: General Fund | C14: 273 | D14: CIP-Other Public Infrastructures | E14: Construction of Perimeter Fence at PAnabo City Eternal Garden, Brgy. Datu Abdul, Panabo City/Project | F14: 1417023.7 | G14: 43067 | H14: 120 | I14: =1+12+12+12+12 -> 49 | J14: 520756.22 | K14: Land Improvement
A15: =A14+1 -> 6 | B15: General Fund | C15: 264 | D15: CIP-Agency Assets | E15: POW#2021-05-004_Site Development for Resettlement Areas @Brgy. San Fracisco | F15: 372713.93 | G15: 44469 | H15: 120 | I15: 3 | J15: 8386.06 | K15: Land Improvement
D16: Sub-total | F16: =SUM(F11:F15) -> 4144638.9 | J16: =SUM(J11:J15) -> 1377031.7
A18: 7 | B18: General Fund | C18: 264 | D18: CIP-Agency Assets | E18: POW#2020-07-265_Rehabilitation/ Improvement of Multi-Purpose Building- Salvacion | F18: 15442.77 | G18: 44321 | H18: 60 | I18: 7 | J18: 1621.49 | K18: Other Public Infrastructure
A19: =A18+1 -> 8 | B19: General Fund | C19: 264 | D19: CIP-Agency Assets | E19: POW#2019-09-344_CONSTRUCTION OF BATCHING FOUNDATION | F19: 711475.4 | G19: 44545 | H19: 60 | I19: 0 | J19: 0 | K19: Other Public Infrastructure
A20: =A19+1 -> 9 | B20: General Fund | C20: 264 | D20: CIP-Agency Assets | E20: POW#2020-07-265_Rehabilitation/ Improvement of Multi-Purpose Building- Salvacion | F20: 93654.01 | G20: 44321 | H20: 60 | I20: 7 | J20: 9833.67 | K20: Other Public Infrastructure
A21: =A20+1 -> 10 | B21: General Fund | C21: 264 | D21: CIP-Agency Assets | E21: POW#2019-12-484_COMPLETION/OPERATION OF ASPHALT BATCHING PLANT | F21: 2116700 | G21: 44418 | H21: 60 | I21: 4 | J21: 127002 | K21: Other Public Infrastructure
A22: =A21+1 -> 11 | B22: General Fund | C22: 264 | D22: CIP-Agency Assets | E22: POW#2019-05-195_RENOVATION OF PANABO CITY TEEN CENTER | F22: 614913.86 | G22: 43780 | H22: 60 | I22: =1+12+12 -> 25 | J22: 230592.7 | K22: Other Public Infrastructure
A23: =A22+1 -> 12 | B23: General Fund | C23: 273 | D23: CIP-Other Public Infrastructures | E23: COMPLETION OF MULTI-PURPOSE GYM, PUROK RAMIHAN, BRGY. DATU ABDUL_POW#2015-06-348 | F23: 1228689.4 | G23: 42641 | H23: 60 | I23: 60 | J23: 1105820.5 | K23: Other Public Infrastructure
A24: =A23+1 -> 13 | B24: General Fund | C24: 273 | D24: CIP-Other Public Infrastructures | E24: CONSTRUCTION OF PANABO CITY MARICULTURE COMPLEX (BAYWALK PHASE III)_POW#2016-09-466 | F24: 3809282 | G24: 43134 | H24: 60 | I24: =10+12+12+12 -> 46 | J24: 2628404.6 | K24: Other Public Infrastructure
A25: =A24+1 -> 14 | B25: General Fund | C25: 273 | D25: CIP-Other Public Infrastructures | E25: CONSTRUCTION OF REHABILITATION CENTER FOR CICL_POW # 2015-05-280 | F25: 1000000 | G25: 42431 | H25: 60 | I25: 60 | J25: 900000 | K25: Other Public Infrastructure
A26: =A25+1 -> 15 | B26: General Fund | C26: 273 | D26: CIP-Other Public Infrastructures | E26: CONSTRUCTION OF WOMEN'S CRISIS CENTER @ BRGY. DATU ABDUL_POW # 2015-06-306 | F26: 593179.45 | G26: 42431 | H26: 60 | I26: 60 | J26: 533861.51 | K26: Other Public Infrastructure
A27: =A26+1 -> 16 | B27: General Fund | C27: 273 | D27: CIP-Other Public Infrastructures | E27: CONSTRUCTION OF SOLAR DRYER, BRGY. MABUNAO_POW#2016-02-130 | F27: 328407 | G27: 42660 | H27: 60 | I27: 60 | J27: 295566.3 | K27: Other Public Infrastructure
A28: =A27+1 -> 17 | B28: General Fund | C28: 273 | D28: CIP-Other Public Infrastructures | E28: CONSTRUCTION OF BAYWALK (EXPANSION ON-WARD THE SEASHORE)_POW#2017-05-454 | F28: 3593904.8 | G28: 43223 | H28: 60 | I28: =7+12+12+12 -> 43 | J28: 2318068.6 | K28: Other Public Infrastructure
A29: =A28+1 -> 18 | B29: General Fund | C29: 273 | D29: CIP-Other Public Infrastructures | E29: Installation of Traffic Lights w/ Controls & Vehicle Sensor at Junction Quirino St. National Highway | F29: 3695633.9 | G29: 42923 | H29: 60 | I29: =5+12+12+12+12 -> 53 | J29: 2938028.9 | K29: Other Public Infrastructure
A30: =A29+1 -> 19 | B30: General Fund | C30: 273 | D30: CIP-Other Public Infrastructures | E30: Construction of Tennis Court - Brgy. J.P Laurel, Panabo City | F30: 1445157.2 | G30: 43049 | H30: 60 | I30: =1+12+12+12+12 -> 49 | J30: 1062190.5 | K30: Other Public Infrastructure
A31: =A30+1 -> 20 | B31: General Fund | C31: 273 | D31: CIP-Other Public Infrastructures | E31: CONSTRUCTION OF CONCRETE DRAINAGE, BRGY. UPPER LICANAN_POW#2015-10-587 | F31: 117900 | G31: 42653 | H31: 60 | I31: 60 | J31: 106110 | K31: Other Public Infrastructure
A32: =A31+1 -> 21 | B32: General Fund | C32: 264 | D32: CIP-Agency Assets | E32: POW#2021-03-118_Construction of Water & Sanitation Facilities(2 seater w/ PWD and sink), Consolacion | F32: 29927.28 | G32: 44431 | H32: 60 | I32: 4 | J32: 1795.64 | K32: Other Public Infrastructure
D33: Sub-total | F33: =SUM(F18:F32) -> 19394267 | J33: =SUM(J18:J32) -> 12258896
A35: 22 | B35: General Fund | C35: 264 | D35: CIP-Agency Assets | E35: Renovation of Angel Barachael Drop-in Center Phase II @ Brgy. New Pandan_POW#2016-08-397 | F35: 354011.86 | G35: 42737 | H35: 60 | I35: =11+12+12+12+12 -> 59 | J35: 313300.5 | K35: Other Structure
D36: Sub-total | F36: =SUM(F35) -> 354011.86 | J36: =SUM(J35) -> 313300.5
A38: 23 | B38: General Fund | C38: 267 | D38: Construction in Progress - Parks, Plazas and Monuments | E38: Improvement of Parks & Plaza: Fencing & Lightings_Old City Hall_POW#2015-04-238 | F38: 39085.07 | G38: 42535 | H38: 240 | I38: 60 | J38: 8794.14 | K38: Parks, Plazas and Monuments
A39: 24 | B39: General Fund | C39: 267 | D39: Construction in Progress - Parks, Plazas and Monuments | E39: POW#2019-12-468_Improvement of Parks and Plaza at Old City Hall- New Pandan | F39: 789737.05 | G39: 44032 | H39: 240 | I39: =5+12 -> 17 | J39: 50345.74 | K39: Parks, Plazas and Monuments
D40: Sub-total | F40: =SUM(F38:F39) -> 828822.12 | J40: =SUM(J38:J39) -> 59139.88
A42: 25 | B42: General Fund | C42: 266 | D42: CIP-Roads, Highways and bridges | E42: POW#2021-05-162_Concreting of Road- Consolacion to Malativas_300mm thick x 6.70m width x 944.50 ln.m | F42: 19975730 | G42: 44477 | H42: 240 | I42: 2 | J42: 149817.98 | K42: Roads, Highways and bridges
D43: Sub-total | F43: =SUM(F42:F42) -> 19975730 | J43: =SUM(J42:J42) -> 149817.98
A45: 26 | B45: General Fund | C45: 272 | D45: CIP-Waterways, Aqueducts,Seawalls, Riverwalls and Others | E45: POW#2018-12-489_CONSTRUCTION OF DRAINAGE WITHIN PANABO PUBLIC PARK | F45: 1999371.7 | G45: 43726 | H45: 240 | I45: =3+12+12 -> 27 | J45: 202436.39 | K45: Waterways, Aqueducts,Seawalls, Riverwalls and Others
D46: Sub-total | F46: =SUM(F45) -> 1999371.7 | J46: =SUM(J45) -> 202436.39
D48: Total - GF | F48: =F9+F16+F33+F36+F40+F43+F46 -> 48150152 | J48: =J9+J16+J33+J36+J40+J43+J46 -> 14415122
A51: 27 | B51: SEF | C51: 269 | D51: CIP-Artesian Wells, Reservoirs, Pumping Stations and Conduits | E51: POW#2019-04-191_INSTALLATION OF WATER RESERVOIR/ TANK (BEST TANK, TAGPORE, ES | F51: 175323.86 | G51: 43754 | H51: 240 | I51: =2+12+12 -> 26 | J51: 17094.08 | K51: Artesian Wells, Reservoirs, Pumping Stations and Conduits
D52: Sub-total | F52: =SUM(F51) -> 175323.86 | J52: =SUM(J51) -> 17094.08
A54: 28 | B54: SEF | C54: 264 | D54: CIP-Agency Assets | E54: Construction of Perimeter Fence @ Sison E.S., Brgy. Sindaton_POW#2016-08-396 | F54: 177540 | G54: 42412 | H54: 120 | I54: 60 | J54: 79893 | K54: Land Improvement
A55: =A54+1 -> 29 | B55: SEF | C55: 264 | D55: CIP-Agency Assets | E55: POW#2019-04-167_Construction of Perimeter Fence, So. Davao ES @Southern Davao | F55: 403748.93 | G55: 43689 | H55: 120 | I55: =4+12+12 -> 28 | J55: 84787.27 | K55: Land Improvement
A56: =A55+1 -> 30 | B56: SEF | C56: 264 | D56: CIP-Agency Assets | E56: POW#2019-05-199_CONSTRUCTION OF PERIMETER FENCE, PANABO CITY SHS | F56: 781000.67 | G56: 43822 | H56: 120 | I56: =12+12 -> 24 | J56: 140580.12 | K56: Land Improvement
A57: =A56+1 -> 31 | B57: SEF | C57: 273 | D57: CIP-Other Public Infrastructures | E57: FENCING OF ELEMENTARY SCHOOL - JP Laurel | F57: 8870 | G57: 42923 | H57: 120 | I57: =5+12+12+12+12 -> 53 | J57: 3525.83 | K57: Land Improvement
A58: =A57+1 -> 32 | B58: SEF | C58: 273 | D58: CIP-Other Public Infrastructures | E58: CONSTRUCTION OF PERIMETER FENCE , SINDATON E/S_POW#2016-07-358 | F58: 129850 | G58: 43700 | H58: 120 | I58: =4+12+12 -> 28 | J58: 27268.5 | K58: Land Improvement
A59: =A58+1 -> 33 | B59: SEF | C59: 273 | D59: CIP-Other Public Infrastructures | E59: POW#2019-03-132_Construction of Perimeter Fence P. Changco ES @Brgy. Tibungol | F59: 495053.34 | G59: 43751 | H59: 120 | I59: =2+12+12 -> 26 | J59: 96535.4 | K59: Land Improvement
D60: Sub-total | F60: =SUM(F54:F59) -> 1996062.9 | J60: =SUM(J54:J59) -> 432590.12
A62: 34 | B62: SEF | C62: 273 | D62: CIP-Other Public Infrastructures | E62: REPAIR AND MAINTENANCE OF SCHOOL BLDG., PANABO CENTRAL E/S, SPED_POW#2016-07-367 | F62: 123946.5 | G62: 42885 | H62: 240 | I62: =7+12+12+12+12 -> 55 | J62: 25563.97 | K62: Other Public Infrastructure
D63: Sub-total | F63: =SUM(F62) -> 123946.5 | J63: =SUM(J62) -> 25563.97
A65: 35 | B65: SEF | C65: 264 | D65: CIP-Agency Assets | E65: CONST. OF 1 STOREY 2 CLASSROOM SCHOOL BLDG.- NEW MALITBOG HIGH SCHOOL EXT. (PHASE II)_POW # 2016-09- | F65: 113013 | G65: 42766 | H65: 240 | I65: =11+12+12+12+12 -> 59 | J65: 25004.13 | K65: School Buidling
A66: =A65+1 -> 36 | B66: SEF | C66: 264 | D66: CIP-Agency Assets | E66: IMPROVEMENT OF SCHOOL SITE, AOFES II, BRGY. SAN VICENTE_POW # 2016-08-405 | F66: 1012.07 | G66: 43133 | H66: 240 | I66: =10+12+12+12 -> 46 | J66: 174.58 | K66: School Buidling
A67: =A66+1 -> 37 | B67: SEF | C67: 264 | D67: CIP-Agency Assets | E67: POW#2019-01-006_CONSTRUCTION OF SCHOOL BUILDING ONE (1) STOREY 2 CL SCHOOL BUILDING, KASILAK E/S | F67: 2185938.1 | G67: 43731 | H67: 240 | I67: =3+12+12 -> 27 | J67: 221326.23 | K67: School Buidling
A68: =A67+1 -> 38 | B68: SEF | C68: 264 | D68: CIP-Agency Assets | E68: POW#2019-07-263_COMPLETION OF SCHOOL BUILDING-ONE STOREY 3 CL 7 X 27 SCHOOL BUILDING, PHASE 2 SAN FR | F68: 488727.25 | G68: 43893 | H68: 240 | I68: =9+12 -> 21 | J68: 38487.27 | K68: School Buidling
D69: Sub-total | F69: =SUM(F65:F68) -> 2788690.4 | J69: =SUM(J65:J68) -> 284992.21
A71: 39 | B71: SEF | C71: 272 | D71: CIP-Waterways, Aqueducts,Seawalls, Riverwalls and Others | E71: POW # 2018-06-257_SCHOOL SITE IMPROVEMENT(CONSTRUCTION OF DRAINAGE SYSTEM)A.O FLOIRENDO NHS | F71: 485364.41 | G71: 43434 | H71: 240 | I71: =1+12+12+12 -> 37 | J71: 67344.31 | K71: Waterways, Aqueducts,Seawalls, Riverwalls and Others
D72: Sub-total | F72: =SUM(F71) -> 485364.41 | J72: =SUM(J71) -> 67344.31
D74: Total - SEF | F74: =F52+F60+F63+F69+F72 -> 5569388.1 | J74: =J52+J60+J63+J69+J72 -> 827584.69
A77: 40 | B77: Trust Fund | C77: 273 | D77: CIP-Other Public Infrastructures | E77: IMPROVEMENT OF PANABO EMERGENCY CLINIC_POW # 2017-09-653 | F77: 45001 | G77: 43441 | H77: 60 | I77: =12+12+12 -> 36 | J77: 24300.54 | K77: Other Public Infrastructure
A78: =A77+1 -> 41 | B78: Trust Fund | C78: 264 | D78: CIP-Agency Assets | E78: POW#2020-03-166_Closure and Rehabilitation of Open Dumpsite (Phase II) @New Malitbog, PC | F78: 1409337.4 | G78: 44144 | H78: 60 | I78: =1+12 -> 13 | J78: 274820.79 | K78: Other Public Infrastructure
A79: =A78+1 -> 42 | B79: Trust Fund | C79: 273 | D79: CIP-Other Public Infrastructures | E79: MATERIAL RECOVERY FACILITY AND SHARP SEPTIC VAULT_POW # 2017-07-564 | F79: 32916.48 | G79: 42988 | H79: 60 | I79: =3+12+12+12+12 -> 51 | J79: 25181.11 | K79: Other Public Infrastructure
A80: =A79+1 -> 43 | B80: Trust Fund | C80: 273 | D80: CIP-Other Public Infrastructures | E80: CONSTRUCTION OF SEPTIC VAULT FOR DISPOSAL OF USED SHARPS & PLACENTA | F80: 35597.39 | G80: 41785 | H80: 60 | I80: 60 | J80: 32037.65 | K80: Other Public Infrastructure
D81: Total - TF | F81: =SUM(F77:F80) -> 1522852.3 | J81: =SUM(J77:J80) -> 356340.09
D83: GRAND TOTAL | F83: =F48+F74+F81 -> 55242392 | J83: =J8+J11+J12+J13+J14+J15+J18+J19+J20+J21+J22+J23+J24+J25+J26+J27+J28+J29+J30+J31+J32+J35+J38+J39+J42+J45+J51+J54+J55+J56+J57+J58+J59+J62+J65+J66+J67+J68+J71+J77+J78+J79+J80 -> 15599047

Sheet K
A1: City Government of Panabo | D1: Annex K
A2: As at December 31, 2021
A4: List of beneficiaries at Barangay Quezon
A7: No. | B7: Name | C7: Status | D7: Year Hired
A8: 1 | B8: Acdal, Wilfredo M | C8: permanent | D8: 2010
A9: 2 | B9: Acosta, Lenita B | C9: retired | D9: 1993
A10: 3 | B10: Aguisando, Helene May S | C10: permanent | D10: 2000
A11: 4 | B11: Albasin, Randy A | C11: permanent | D11: 2001
A12: 5 | B12: Almorato, Rex Joy C | C12: permanent | D12: 1993
A13: 6 | B13: Alpuerto, Amy B | C13: permanent | D13: 2000
A14: 7 | B14: Amper, Salee C | C14: permanent | D14: 2002
A15: 8 | B15: Atanoza, Novie Joy M | C15: permanent | D15: 2007
A16: 9 | B16: Bacalso, Perla B | C16: permanent | D16: 1991
A17: 10 | B17: Balaga, Myrna M | C17: permanent | D17: 2007
A18: 11 | B18: Balagot, Edito G | C18: retired | D18: 1999
A19: 12 | B19: Balanay, Erchied J | C19: permanent | D19: 1996
... A126: 119 | B126: Fe Garcia | C126: permanent | D126: 2011

Sheet L
A1: City Government of Panabo | D1: Annex L
A2: As at December 31, 2021
A4: List of beneficiaries who owned a lot
A6: No. | B6: Name
A7: 1 | B7: Acosta, Lenita B | C7: retired
A8: =A7+1 -> 2 | B8: Albasin, Randy A | C8: permanent
A9: =A8+1 -> 3 | B9: Amper, Salee C | C9: permanent
A10: =A9+1 -> 4 | B10: Bacalso, Perla B | C10: permanent
A11: =A10+1 -> 5 | B11: Balaga, Myrna M | C11: permanent
A12: =A11+1 -> 6 | B12: Benedicto, Juliet S | C12: permanent
A13: =A12+1 -> 7 | B13: Bernaldez, Gloria T | C13: retired
A14: =A13+1 -> 8 | B14: Cozo, Crsitito D | C14: permanent
A15: =A14+1 -> 9 | B15: Dela Gente, Jackie Joseph F | C15: permanent
A16: =A15+1 -> 10 | B16: Dela gente, Juliet C | C16: permanent
A17: =A16+1 -> 11 | B17: Deloso, Annabelle A | C17: permanent
A18: =A17+1 -> 12 | B18: Descuatan, Elinita A | C18: permanent
A19: =A18+1 -> 13 | B19: Dianzon, Daisy L | C19: permanent
... A44: =A43+1 -> 38 | B44: Fe Garcia | C44: permanent

Sheet M
C1: Annex M
C2: CY 2021 Financial Reports of Panabo City as posted in FDP Portal
B4: Annual Budget Report; | C4: Annual Budget Report:
B5: Annual Procurement Plan;
B6: Statement of Receipts and Expenditures;
B7: GAD Accomplishment Report;
B8: Local Disaster Risk and Reduction and Management Fund Utilization;
B9: Special Education Fund Utilization
B10: 20% Component of the IRA Utilization;
B13: Trust Fund Utilization | C13: Annual Procurement Plan:
B14: Quarterly Statement of Cash Flows;
B15: Supplemental Procurement Plan; and
B16: Manpower Component
C21: Supplemental Procurement Plan:
C30: Statement of Receipts and Expenditures:
C38: GAD Accomplishment Report:
