Workbook

Sheet SFPOS
A1: City Government of Panabo
A2: Province of Davao del Norte
A3: STATEMENT OF FINANCIAL POSITION
A4: All Funds
A5: As at December 31, 2023
A6: (With Comparative Figures for CY 2022)
A7: (In Philippine Peso)
B9: Note | D9: 2023 | E9: 2022
A10: ASSETS
A11: Current Assets
A12: Cash and Cash Equivalents | B12: 4 | D12: 1.4314898e+09 | E12: 1.5002771e+09 | G12: =D12-#REF! -> #REF! | H12: =E12-#REF! -> #REF!
A13: Investments | B13: 5 | D13: 32094941 | E13: 35790297 | G13: =D13-#REF! -> #REF! | H13: =E13-#REF! -> #REF!
A14: Receivables | B14: 6 | D14: 2.7871473e+08 | E14: 2.7125557e+08 | G14: =D14-#REF! -> #REF! | H14: =E14-#REF! -> #REF!
A15: Inventories | B15: 7 | D15: 75227017 | E15: 1.6258755e+08 | G15: =D15-#REF! -> #REF! | H15: =E15-#REF! -> #REF!
A16: Prepayments and Deferred Charges | B16: 8 | D16: 36498998 | E16: 82238189 | G16: =D16-#REF! -> #REF! | H16: =E16-#REF! -> #REF!
A17: Total Current Assets | D17: =SUM(D12:D16) -> 1.8540255e+09 | E17: =SUM(E12:E16) -> 2.0521487e+09 | G17: =D17-#REF! -> #REF! | H17: =E17-#REF! -> #REF!
A19: Non-Current Assets
A20: Investment Property | B20: 9 | D20: 19421907 | E20: 21468682 | G20: =D20-#REF! -> #REF! | H20: =E20-#REF! -> #REF!
A21: Property, Plant and Equipment | B21: 10 | D21: 3.3038989e+09 | E21: 3.1031818e+09 | G21: =D21-#REF! -> #REF! | H21: =E21-#REF! -> #REF!
A22: Intangible Assets | B22: 10 | D22: 1835383.4 | E22: 42783.33 | G22: =D22-#REF! -> #REF! | H22: =E22-#REF! -> #REF!
A23: Total Non-Current Assets | D23: =SUM(D20:D22) -> 3.3251562e+09 | E23: =SUM(E20:E22) -> 3.1246933e+09 | G23: =D23-#REF! -> #REF! | H23: =E23-#REF! -> #REF!
A24: Total Assets | D24: =D23+D17 -> 5.1791816e+09 | E24: =E23+E17 -> 5.176842e+09 | G24: =D24-#REF! -> #REF! | H24: =E24-#REF! -> #REF!
A26: LIABILITIES
A27: Current Liabilities
A28: Financial Liabilities | B28: 11,12 | D28: 1.8343041e+08 | E28: 1.989913e+08 | G28: =D28-#REF! -> #REF! | H28: =E28-#REF! -> #REF!
A29: Inter-Agency Payables | B29: 13 | D29: 1.0124725e+08 | E29: 2.9464755e+08 | G29: =D29-#REF! -> #REF! | H29: =E29-#REF! -> #REF!
A30: Intra-Agency Payables | B30: 14 | D30: 88777384 | E30: 43743842 | G30: =D30-#REF! -> #REF! | H30: =E30-#REF! -> #REF!
A31: Trust Liabilities | B31: 15 | D31: 1.9650803e+08 | E31: 1.7514942e+08 | G31: =D31-#REF! -> #REF! | H31: =E31-#REF! -> #REF!
A32: Provisions | G32: =D32-#REF! -> #REF! | H32: =E32-#REF! -> #REF!
A33: Deferred Credits/Unearned Income | B33: 16 | D33: 33945927 | E33: 2.6539762e+08 | G33: =D33-#REF! -> #REF! | H33: =E33-#REF! -> #REF!
A34: Other Payables | B34: 17 | D34: 12519225 | E34: 26964251 | G34: =D34-#REF! -> #REF! | H34: =E34-#REF! -> #REF!
A35: Total Current Liabilities | D35: =SUM(D28:D34) -> 6.1642822e+08 | E35: =SUM(E28:E34) -> 1.004894e+09 | G35: =D35-#REF! -> #REF!
A37: Non-Current Liabilities
A38: Financial Liabilities | B38: 12 | D38: 6.3293403e+08 | E38: 5.8605084e+08 | G38: =D38-#REF! -> #REF! | H38: =E38-#REF! -> #REF!
A39: Deferred Credits/Unearned Income | B39: 16 | D39: 1.2180925e+08 | E39: 15168796 | G39: =D39-#REF! -> #REF! | H39: =E39-#REF! -> #REF!
A40: Total Non-Current Liabilities | D40: =SUM(D38:D39) -> 7.5474328e+08 | E40: =SUM(E38:E39) -> 6.0121964e+08 | G40: =D40-#REF! -> #REF! | H40: =E40-#REF! -> #REF!
A41: Total Liabilities | D41: =D35+D40 -> 1.3711715e+09 | E41: =E35+E40 -> 1.6061136e+09 | G41: =D41-#REF! -> #REF! | H41: =E41-#REF! -> #REF!
A43: NET ASSETS/EQUITY
A44: Government Equity | B44: 29 | D44: =SCNAE!D18 -> 3.8080101e+09 | E44: 3.5707283e+09 | G44: =D44-#REF! -> #REF! | H44: =E44-#REF! -> #REF!
A45: Total Liabilities and Net Assets/Equity | D45: =D44+D41 -> 5.1791816e+09 | E45: =E44+E41 -> 5.176842e+09 | G45: =D45-#REF! -> #REF! | H45: =E45-#REF! -> #REF!
A47: (See accompanying Notes to Financial Statements.)
D52: =D24-D45 -> 0 | E52: =E24-E45 -> 0

Sheet SFPER
A1: City Government of Panabo
A2: Province of Davao del Norte
A3: STATEMENT OF FINANCIAL PERFORMANCE
A4: All Funds
A5: For the Year Ended December 31, 2023
A6: (With Comparative Figures for CY 2022)
A7: (In Philippine Peso)
B9: Note | D9: 2023 | E9: 2022
A10: Revenue
A11: Tax Revenue | B11: 18 | D11: 3.4835912e+08 | E11: 3.1547791e+08 | F11: =D11-#REF! -> #REF! | H11: =E11-#REF! -> #REF!
A12: Share from National Taxes | B12: 18 | D12: 1064025769 | E12: 1248221550 | F12: =D12-#REF! -> #REF! | H12: =E12-#REF! -> #REF!
A13: Service and Business Income | B13: 19, 26 | D13: 1.6181036e+08 | E13: 1.6759424e+08 | F13: =D13-#REF! -> #REF! | H13: =E13-#REF! -> #REF!
A14: Shares, Grants and Donations | B14: 21 | D14: 2.1692078e+08 | E14: 84539859 | F14: =D14-#REF! -> #REF! | H14: =E14-#REF! -> #REF!
A15: Total Revenue | D15: =SUM(D11:D14) -> 1.791116e+09 | E15: =SUM(E11:E14) -> 1.8158336e+09 | J15: =D15+D26+D28 -> 1.7950999e+09
A17: Less: Current Operating Expenses
A18: Personnel Services | B18: 23 | D18: 5.0693827e+08 | E18: 4.644253e+08 | F18: =D18-#REF! -> #REF! | H18: =E18-#REF! -> #REF!
A19: Maintenance & Other Operating Expenses | B19: 24 | D19: 4.9731325e+08 | E19: 5.2708073e+08 | F19: =D19-#REF! -> #REF! | H19: =E19-#REF! -> #REF! | J19: =-D27 -> 32248441
A20: Financial Expenses | B20: 25 | D20: 39931715 | E20: 21498605 | F20: =D20-#REF! -> #REF! | H20: =E20-#REF! -> #REF! | J20: =D19+J19 -> 5.2956169e+08
A21: Non-cash Expenses | B21: 27 | D21: 1.8187855e+08 | E21: 1.239231e+08 | F21: =D21-#REF! -> #REF! | H21: =E21-#REF! -> #REF! | J21: =J20+D21 -> 7.1144024e+08
A22: Current Operating Expenses | D22: =SUM(D18:D21) -> 1.2260618e+09 | E22: =SUM(E18:E21) -> 1.1369277e+09 | F22: =D22-#REF! -> #REF! | H22: =E22-#REF! -> #REF!
A24: Surplus (Deficit) from Current Operation | D24: =D15-D22 -> 5.6505425e+08 | E24: =E15-E22 -> 6.7890584e+08 | F24: =D24-#REF! -> #REF! | H24: =E24-#REF! -> #REF!
A25: Add (Deduct):
A26: Transfers, Assistance and Subsidy From | B26: 20 | D26: 1745000 | E26: 10612958 | F26: =D26-#REF! -> #REF! | H26: =E26-#REF! -> #REF!
A27: Transfers, Assistance and Subsidy To | B27: 24 | D27: -32248441 | E27: -21104847 | F27: =D27-#REF! -> #REF! | H27: =E27+#REF! -> #REF!
A28: Miscellaneous Income | B28: 22 | D28: 2238897.7 | E28: 2218956.3 | F28: =D28-#REF! -> #REF! | H28: =E28-#REF! -> #REF!
A29: Surplus(Deficit) for the period | D29: =SUM(D24:D28) -> 5.3678971e+08 | E29: =SUM(E24:E28) -> 6.706329e+08 | F29: =D29-#REF! -> #REF! | H29: =E29-#REF! -> #REF!
A31: (See accompanying Notes to Financial Statements.)

Sheet SCNAE
A1: City Government of Panabo
A2: Province of Davao del Norte
A3: STATEMENT OF CHANGES IN NET ASSETS/EQUITY
A4: All Funds
A5: For the Year Ended December 31, 2023
A6: (With Comparative Figures for CY 2022)
A7: (In Philippine Peso)
B9: Note | D9: 2023 | E9: 2022
A10: Balance at January 1 | D10: =E18 -> 3.5707283e+09 | E10: 3.0270564e+09 | G10: =D10-#REF! -> #REF! | H10: =E10-#REF! -> #REF!
A11: Add (Deduct):
A12: Changes in Accounting Policy | D12: 6756702.7 | H12: =E12-#REF! -> #REF!
A13: Prior Period Errors | B13: 28 | D13: -3.0626462e+08 | E13: -1.2696097e+08 | G13: =D13-#REF! -> #REF! | H13: =E13-#REF! -> #REF!
A14: Restated Balance | D14: =SUM(D10:D13) -> 3.2712204e+09 | E14: =E10+E12+E13 -> 2.9000954e+09 | G14: =D14-#REF! -> #REF! | H14: =E14-#REF! -> #REF!
A15: Add (Deduct) Changes in net assets/equity during the year
A16: Surplus (Deficit) for the period | D16: =SFPER!D29 -> 5.3678971e+08 | E16: =SFPER!E29 -> 6.706329e+08 | G16: =D16-#REF! -> #REF! | H16: =E16-#REF! -> #REF!
A17: Total changes during the year | D17: =D16 -> 5.3678971e+08 | E17: =E16 -> 6.706329e+08
A18: Balance at December 31, 2022 | B18: 29 | D18: =D14+D17 -> 3.8080101e+09 | E18: =E14+E16 -> 3.5707283e+09
A20: (See accompanying Notes to Financial Statements.)

Sheet SCF
A1: City Government of Panabo
A2: Province of Davao del Norte
A3: STATEMENT OF CASH FLOWS
A4: All Funds
A5: For the Year Ended December 31, 2023
A6: (With Comparative Figures for CY 2022)
A7: (In Philippine Peso)
B9: Note | D9: 2023 | F9: 2022
A10: Cash Flows from Operating Activities
A11: Cash Inflows
A12: Collection from Taxpayers | D12: 3.825565e+08 | F12: 3.9815268e+08
A13: Share from Internal Revenue Allotment | D13: 1064025769 | F13: 1248221550
A14: Receipts from Business/Service Income | D14: 1.3896864e+08 | F14: 63908116
A15: Interest Income | D15: 689399.09 | F15: 723892.42
A16: Other Receipts | D16: 3.7983123e+08 | F16: 4.3425308e+08
A17: Total Cash Inflows | D17: =+SUM(D12:D16) -> 1.9660715e+09 | F17: =+SUM(F12:F16) -> 2.1452593e+09
A18: Cash Outflows
A19: Payment of Expenses | D19: 3.1263918e+08 | F19: 2.9027632e+08
A20: Payments to Suppliers and Creditors | D20: 7792407.4 | F20: 1.070058e+08
A21: Payments to Employees | D21: 4.8857866e+08 | F21: 5.3077991e+08
A22: Interest Expense | D22: 38988267 | F22: 20139328
A23: Other Expenses | D23: 6.9111577e+08 | F23: 9.5945754e+08
A24: Total Cash Outflows | D24: =+SUM(D19:D23) -> 1.5391143e+09 | F24: =+SUM(F19:F23) -> 1.9076589e+09
A25: Net Cash Flows from Operating Activities | D25: =D17-D24 -> 4.2695727e+08 | F25: =F17-F24 -> 2.3760043e+08
A26: Cash Flow from Investing Activities
A27: Cash Inflows
A28: Proceeds from Sale/Disposal of PPE | D28: 5782102.5 | F28: 11519.46
A29: Total Cash Inflows | D29: =+D28 -> 5782102.5 | F29: =+F28 -> 11519.46
A30: Cash Outflows
A31: Purchase/Construction of PPE | D31: 5.6124544e+08 | F31: 4.6080316e+08
A32: Total Cash Outflows | D32: =+D31 -> 5.6124544e+08 | F32: =+F31 -> 4.6080316e+08
A33: Net Cash Flows from Investing Activities | D33: =+D29-D32 -> -5.5546334e+08 | F33: =+F29-F32 -> -4.6079165e+08
A34: Cash Flows from Financing Activities
A35: Cash Inflows
A36: Proceeds from Domestic Loans | D36: 125793000 | F36: 4.0106858e+08
A37: Total Cash Inflows | D37: =+D36 -> 125793000 | F37: =+F36 -> 4.0106858e+08
A38: Cash Outflows
A39: Payment of Long-Term Liabilities | D39: 66074240 | F39: 32681550
A40: Total Cash Outflows | D40: =+D39 -> 66074240 | F40: =+F39 -> 32681550
A41: Cash Flows from Financing Activities | D41: =D37-D40 -> 59718760 | F41: =F37-F40 -> 3.6838703e+08
A42: Total Cash Provided by Operating, Investing
A43: and Financing Activities | D43: =D25+D33+D41 -> -68787309 | F43: =F25+F33+F41 -> 1.4519582e+08
A44: Add: Cash at the Beginning of the year | D44: =F46 -> 1.5002771e+09 | F44: 1.3550813e+09
A45: Adjustment to prior year cash balance
A46: Cash Balance at the End of the Year | B46: 4 | D46: =SUM(D43:D45) -> 1.4314898e+09 | F46: =SUM(F43:F45) -> 1.5002771e+09
A48: (See accompanying Notes to Financial Statements.)
D52: =D46-SFPOS!D12 -> 0.0040001869 | F52: =F46-SFPOS!E12 -> 0.0040001869

Sheet SCBAA
A1: City Government of Panabo
A2: Province of Davao del Norte
A3: STATEMENT OF COMPARISON OF BUDGET AND ACTUAL AMOUNTS
A4: For the Year Ended December 31, 2023
A5: (In Philippine Peso)
A7: PARTICULARS | F7: Note | G7: Budgeted | K7: Difference | P7: Difference
G8: Amounts | K8: Original and | N8: Actual | P8: Final Budget
H9: Original | J9: Final | K9: Final Budget | N9: Amounts | P9: and Actual
A11: Revenue | F11: 30
B12: A. Local Sources
C13: 1. Tax Revenue
D14: a. Tax Revenue - Property | H14: 108650000 | J14: 108650000 | L14: =H14-J14 -> 0 | N14: 1.0704474e+08 | P14: =J14-N14 -> 1605257.9
D15: b. Tax Revenue - Goods and Services | H15: 197439494 | J15: 197439494 | L15: =H15-J15 -> 0 | N15: 2.3050126e+08 | P15: =J15-N15 -> -33061769
D16: c. Other Local Taxes | L16: =H16-J16 -> 0 | P16: =J16-N16 -> 0
C17: Total Tax Revenue | H17: =SUM(H14:H16) -> 306089494 | J17: =SUM(J14:J16) -> 306089494 | L17: =SUM(L14:L16) -> 0 | N17: =SUM(N14:N16) -> 3.3754601e+08 | P17: =SUM(P14:P16) -> -31456511
C18: 2. Non-Tax Revenue
D19: a. Service Income | H19: 61137958 | J19: 61476542 | L19: =H19-J19 -> -338585 | N19: 54008621 | P19: =J19-N19 -> 7467921.3
D20: b. Business Income | H20: 98150217 | J20: 98150217 | L20: =H20-J20 -> 0 | N20: 79323256 | P20: =J20-N20 -> 18826961
D21: c. Other Income and Receipts | H21: 7.5012796e+08 | J21: 8.0924072e+08 | L21: =H21-J21 -> -59112763 | N21: 8.0914126e+08 | P21: =J21-N21 -> 99462.52
C22: Total Non-Tax Revenue | H22: =SUM(H19:H21) -> 9.0941613e+08 | J22: =SUM(J19:J21) -> 9.6886748e+08 | L22: =SUM(L19:L21) -> -59451348 | N22: =SUM(N19:N21) -> 9.4247314e+08 | P22: =SUM(P19:P21) -> 26394345
B23: B. External Sources
C24: 1. Share from the National Internal Revenue Taxes (IRA) | H24: 1067605124 | J24: 1067605124 | L24: =H24-J24 -> 0 | N24: 1063987170 | P24: =J24-N24 -> 3617954
C25: 2. Share from GOCCs
D26: a. Share from PCSO | H26: 1300000 | J26: 1300000 | L26: =H26-J26 -> 0 | N26: 1179077.1 | P26: =J26-N26 -> 120922.88
C27: 3. Other Shares from National Tax Collections
D28: a. Share from Ecozone | H28: 0 | J28: 0 | L28: =H28-J28 -> 0 | N28: 38599 | P28: =J28-N28 -> -38599
D29: b. Share from National Wealth | H29: 0 | J29: 0 | L29: =H29-J29 -> 0 | N29: 0 | P29: =J29-N29 -> 0
C30: 4. Other Receipts
D31: a. Grants and Donations | H31: 0 | J31: 0 | L31: =H31-J31 -> 0 | N31: 0 | P31: =J31-N31 -> 0
D32: b. Other Subsidy Income | H32: 0 | J32: 38046101 | L32: =H32-J32 -> -38046101 | N32: 35590327 | P32: =J32-N32 -> 2455773.9
C33: 5. Inter-local Transfer | H33: 0 | J33: 0 | L33: =H33-J33 -> 0 | N33: 0 | P33: =J33-N33 -> 0
C34: 6. Capital /Investment Receipts
D35: a. Sale of Capital Assets | H35: 0 | J35: 0 | L35: =H35-J35 -> 0 | N35: 0 | P35: =J35-N35 -> 0
D36: b. Sale of Investments | H36: 0 | J36: 0 | L36: =H36-J36 -> 0 | N36: 0 | P36: =J36-N36 -> 0
D37: c. Proceeds from Collections of Loan Receivable | H37: 0 | J37: 0 | L37: =H37-J37 -> 0 | N37: 0 | P37: =J37-N37 -> 0
B38: C. Receipts from Grants, Donations and Subsidy | P38: =J38-N38 -> 0
D39: a. Grants and Donations | H39: 0 | J39: 0 | L39: =H39-J39 -> 0 | N39: 0 | P39: =J39-N39 -> 0
D40: b. Other Subsidy Income | H40: 0 | J40: 0 | L40: =H40-J40 -> 0 | N40: 0 | P40: =J40-N40 -> 0
B41: C. Receipts from Borrowings | H41: 0 | J41: 187758600 | L41: =H41-J41 -> -187758600 | N41: 187758600 | P41: =J41-N41 -> 0
A42: Total Revenue and Receipts | H42: =H17+H22+H24+H26+H28+H29+H39+H40+H41+H33+H32 -> 2.2844108e+09 | J42: =J17+J22+J24+J26+J28+J29+J39+J40+J41+J33+J31+J32 -> 2.5696668e+09 | L42: =L17+L22+L24+L26+L28+L29+L39+L40+L41+L33+L31+L32 -> -2.8525605e+08 | N42: =N17+N22+N24+N26+N28+N29+N39+N40+N41+N33+N32+N37 -> 2.5685729e+09 | P42: =P17+P22+P24+P26+P28+P29+P39+P40+P41+P33+P31+P32+P37 -> 1093885.4
A43: Continuing Appropriations | H43: 0 | J43: 0 | L43: =H43-J43 -> 0 | N43: 0 | P43: =J43-N43 -> 0
A44: Grand Total Revenue and Receipts | H44: =+H42+H43 -> 2.2844108e+09 | I44: =+I42+I43 -> 0 | J44: =+J42+J43 -> 2.5696668e+09 | K44: =+K42+K43 -> 0 | L44: =+L42+L43 -> -2.8525605e+08 | M44: =+M42+M43 -> 0 | N44: =+N42+N43 -> 2.5685729e+09 | O44: =+O42+O43 -> 0 | P44: =+P42+P43 -> 1093885.4
A45: Expenditures
A46: Current Aprropriations
B47: General Public Services
C48: Personnel Services | H48: 3.3018509e+08 | J48: 3.1960164e+08 | L48: =H48-J48 -> 10583447 | N48: 2.6479387e+08 | P48: =J48-N48 -> 54807773
C49: Maintenance and Other Operating Expenses | H49: 2.837874e+08 | J49: 3.2440636e+08 | L49: =H49-J49 -> -40618963 | N49: 2.5947709e+08 | P49: =J49-N49 -> 64929270
C50: Capital Outlay | H50: 850000 | J50: 25139281 | L50: =H50-J50 -> -24289281 | N50: 924208.28 | P50: =J50-N50 -> 24215072
B51: Education
C52: Personnel Services | H52: 12810000 | J52: 13410000 | L52: =H52-J52 -> -600000 | N52: 13104309 | P52: =J52-N52 -> 305690.84
C53: Maintenance and Other Operating Expenses | H53: 18010000 | J53: 18965384 | L53: =H53-J53 -> -955383.6 | N53: 11391768 | P53: =J53-N53 -> 7573615.5
C54: Capital Outlay | H54: 23000000 | J54: 46446700 | L54: =H54-J54 -> -23446700 | N54: 27277805 | P54: =J54-N54 -> 19168895
B55: Health, Nutrition and Population Control
C56: Personnel Services | H56: 67772569 | J56: 67935929 | L56: =H56-J56 -> -163359.18 | N56: 65052755 | P56: =J56-N56 -> 2883174.1
C57: Maintenance and Other Operating Expenses | H57: 45068114 | J57: 45730814 | L57: =H57-J57 -> -662700.32 | N57: 34787487 | P57: =J57-N57 -> 10943327
C58: Capital Outlay | H58: 0 | J58: 145485 | L58: =H58-J58 -> -145485 | N58: 127893 | P58: =J58-N58 -> 17592
B59: Labor and Employment
C60: Personnel Services | P60: =J60-N60 -> 0
C61: Maintenance and Other Operating Expenses | P61: =J61-N61 -> 0
C62: Capital Outlay | P62: =J62-N62 -> 0
B63: Housing and Community Development
C64: Personnel Services | P64: =J64-N64 -> 0
C65: Maintenance and Other Operating Expenses | P65: =J65-N65 -> 0
C66: Capital Outlay | P66: =J66-N66 -> 0
B67: Social Services and Social Welfare
C68: Personnel Services | H68: 22018249 | J68: 21540651 | L68: =H68-J68 -> 477598.52 | N68: 16395051 | P68: =J68-N68 -> 5145599.1
C69: Maintenance and Other Operating Expenses | H69: 40411006 | J69: 45319486 | L69: =H69-J69 -> -4908480 | N69: 31991500 | P69: =J69-N69 -> 13327986
C70: Capital Outlay | H70: 0 | J70: 277000 | L70: =H70-J70 -> -277000 | N70: 0 | P70: =J70-N70 -> 277000
B71: Economic Services
C72: Personnel Services | H72: 93184084 | J72: 91174258 | L72: =H72-J72 -> 2009825.7 | N72: 76277817 | P72: =J72-N72 -> 14896441
C73: Maintenance and Other Operating Expenses | H73: 1.6396811e+08 | J73: 1.8560587e+08 | L73: =H73-J73 -> -21637760 | N73: 1.4298214e+08 | P73: =J73-N73 -> 42623739
C74: Capital Outlay | H74: 3000000 | J74: 30627233 | L74: =H74-J74 -> -27627233 | N74: 894011.84 | P74: =J74-N74 -> 29733221
B75: Other Purposes:
C76: Debt Service
D77: Financial Expense | H77: 88599644 | J77: 1.1584369e+08 | L77: =H77-J77 -> -27244044 | N77: 39931715 | P77: =J77-N77 -> 75911974
D78: Amortization | H78: 0 | J78: 0 | L78: =H78-J78 -> 0 | N78: 62660999 | P78: =J78-N78 -> -62660999
C79: LDRRMF
D80: Maintenance and Other Operating Expenses | H80: 39115000 | J80: 39317800 | L80: =H80-J80 -> -202800 | N80: 36056716 | P80: =J80-N80 -> 3261084
D81: Capital Outlay | H81: 29885000 | J81: 39574210 | L81: =H81-J81 -> -9689210 | N81: 6879407.4 | P81: =J81-N81 -> 32694803
C82: 20% Development Fund
D83: Maintenance and Other Operating Expenses | H83: 0 | J83: 0 | L83: =H83-J83 -> 0 | N83: 0 | P83: =J83-N83 -> 0
D84: Capital Outlay | H84: 214000000 | J84: 304382046 | L84: =H84-J84 -> -90382046 | N84: 72548467 | P84: =J84-N84 -> 2.3183358e+08
C85: Share from National Wealth
D86: Maintenance and Other Operating Expenses | P86: =J86-N86 -> 0
D87: Capital Outlay | P87: =J87-N87 -> 0
C88: Allocation for Senior Citizens and PWD
C89: Allocation for Senior Citizens and PWD
D90: Maintenance and Other Operating Expenses | P90: =J90-N90 -> 0
D91: Capital Outlay | P91: =J91-N91 -> 0
C92: Others
D93: Aid to Barangays | H93: 2800000 | J93: 2800000 | L93: =H93-J93 -> 0 | N93: 2550200 | P93: =J93-N93 -> 249800
D94: Confidential Fund | H94: 0 | J94: 6344833.7 | L94: =H94-J94 -> -6344833.7 | N94: 6344833.7 | P94: =J94-N94 -> 0
D95: 2% Discretionary Fund | H95: 703528.73 | J95: 703528.73 | L95: =H95-J95 -> 0 | N95: 703528.72 | P95: =J95-N95 -> 0.01
D96: MPBF | H96: 4778000 | J96: 75291128 | L96: =H96-J96 -> -70513128 | N96: 71314464 | P96: =J96-N96 -> 3976663.7
D97: Subsidy to Economic Enterprise/Special Accounts | H97: 4844226 | J97: 35590327 | L97: =H97-J97 -> -30746101 | N97: 35590327 | P97: =J97-N97 -> -0.020000003
D98: Subsidy to Other Funds | P98: =J98-N98 -> 0
C99: Total Current Approrpiations | H99: =SUM(H48:H98) -> 1.48879e+09 | J99: =SUM(J48:J98) -> 1.8561737e+09 | L99: =SUM(L48:L98) -> -3.6738364e+08 | N99: =SUM(N48:N98) -> 1.2800584e+09 | P99: =SUM(P48:P98) -> 5.761153e+08
A100: Continuing Aprropriations
B101: General Public Services
C102: Capital Outlay | H102: 13730493 | J102: 15548657 | L102: =H102-J102 -> -1818163.2 | N102: 2119982 | P102: =J102-N102 -> 13428675
...
